Workbook

Sheet Start here
B1: Geotechnical News · Q4 2026
B2: Issue window Oct – Dec 2026 · generated 26 Oct 2026
B5: This workbook holds 150 stories from 3 daily digests, 24 Oct 2026 to 26 Oct 2026, in 8 themes and from 108 sources.
B7: What is in this workbook
B8: Dashboard → | C8: Key figures, the Top 10 stories, charts by theme, use, relevance and planning status, a theme × use heat map and a timeline. Choose what it shows with the yellow selectors at the top.
B9: Stories → | C9: Every story as a filterable Excel table, newest digest first; click a headline to open the article. The gold columns – Status, Assigned to and Editor notes – are for you to fill in. Further right: the Primary source to check the facts with, where each story happened (Country, Place) and the Developing story it belongs to. A headline from a non-English source is Claude's English translation; Original headline gives the publisher's own.
B10: By theme → | C10: A read-only reading view: one section per theme, best stories first. Collapse or expand sections with the − / + buttons in the left margin.
B11: Research → | C11: 31 new papers from geotechnical journals for the Academia-to-Industry pages, best rated for use in practice first, with why each matters and a link to the paper. Status and Editor notes work as in Stories.
B12: Events → | C12: The events calendar on 26 Oct 2026: 3 open deadlines (calls for papers, registration) with the days left, and 45 upcoming events (ISSMGE conferences, other conferences, courses and webinars), each linked to its website.
B13: Sources → | C13: The outlets that supplied stories: how many, average relevance, main theme and how many match the current Dashboard selection.
B15: Before you use a story
B16: 1 | C16: Treat the news item as a lead, not as your source.
B17: 2 | C17: Check the facts with the primary source: the authority, the project owner, the company's press release or the official report (“Check with”, where the news desk found it).
B18: 3 | C18: Write the piece in your own words, with your own angle: the magazine angle is a starting point.
B19: 4 | C19: Quote a sentence or two at most, in quotation marks, naming the publication and linking to it.
B20: 5 | C20: For images, use your own, the project's press-kit photos released for media use, or ask permission; never reuse a source's photos, figures or drawings.
B22: How to use the Dashboard selectors
B23: 1 | C23: Open the Dashboard. The yellow boxes at the top are selectors: Theme, Suggested use, Minimum relevance and Issue window.
B24: 2 | C24: Click a yellow box, then the ▼ arrow that appears beside it, and pick a value. Choose “All …” or “Any” to clear that selector.
B25: 3 | C25: The key figures, tables, charts, heat map and the Top 10 list recalculate at once. Headlines in the Top 10 open the article.
B26: 4 | C26: In Stories, set each story’s Status as you plan the issue. The Dashboard’s Planning status table and chart, and the PLANNED figure, count them straight away.
B27: 5 | C27: Filters in the Stories table (▼ in its header) only hide rows; the Dashboard follows the selectors. To list exactly what the Dashboard shows, filter the ‘In Dashboard selection’ column of Stories to ✓.
B29: Planning status (Stories › Status)
B30: To review | C30: New from the scan, not looked at yet (every story starts here)
B31: Shortlisted | C31: Worth considering for the issue
B32: Commissioned | C32: A writer or contributor has been asked to cover it
B33: Published | C33: Used in a published issue or newsletter
B34: Not used | C34: Reviewed and set aside
B36: Relevance scale (AI triage)
B37: 5 / 5 | C37: Rich geotechnical lesson or a major ground-related event
B38: 4 / 5 | C38: Strong ground-engineering content
B39: 3 / 5 | C39: Clear ground-engineering element, worth a brief
B40: 2 / 5 | C40: Weak link to geotechnics
B41: 1 / 5 | C41: Not really geotechnical
B42: – | C42: Shown as –. Not rated by AI: ranked on keyword matches only
B44: Jump to a theme (opens its section in By theme)
B45: Sustainability & the Energy Transition | C45: 4 stories · 1 rated 5 / 5 · 1 feature lead
B46: Digital Geotechnics | C46: 5 stories · 1 rated 5 / 5 · 2 feature leads
B47: Hazards & Resilience | C47: 53 stories · 13 rated 5 / 5 · 34 feature leads
B48: Ground Improvement & Innovation | C48: 2 stories · 2 rated 5 / 5 · 1 feature lead
B49: Infrastructure & the Underground City | C49: 50 stories · 2 rated 5 / 5 · 14 feature leads
B50: Offshore, Coasts & Water | C50: 20 stories · 1 rated 5 / 5 · 8 feature leads
B51: Characterisation & Modelling | C51: 9 stories · 0 rated 5 / 5 · 6 feature leads
B52: Geotechnics & Society | C52: 7 stories · 0 rated 5 / 5 · 2 feature leads
B53: No stories yet | C53: General
B55: Good to know
B56: Blank figures? | C56: The Dashboard is calculated when the file opens. If it shows blanks or zeros in Excel, click Enable Editing in the yellow bar at the top (files from the internet open in Protected View); in LibreOffice press Ctrl+Shift+F9.
B57: Your edits | C57: This file is generated again after every scan. Status, Assigned to and Editor notes are kept only in the copy you save, so keep one working copy per issue.
B58: Lists sheet | C58: A hidden sheet holds the values offered by the dropdowns and some helper cells. There is no need to change it.

Sheet Dashboard
B1: Geotechnical News · Q4 2026
B2: Issue window Oct – Dec 2026 · generated 26 Oct 2026
B4: THEME | G4: SUGGESTED USE | K4: MINIMUM RELEVANCE (OUT OF 5) | N4: ISSUE WINDOW | Q4: Tip: click a yellow box, then its ▼ arrow, to choose. Pick “All …” or “Any” to clear it. Everything below updates.
B5: All themes | G5: All uses | K5: Any | N5: All windows
B6: ="Showing "&Lists!$H$6&" of "&Lists!$H$4&" stories"&IF(Lists!$H$5," – no selector set."," for the selection above. Set every box back to All / Any to see everything.")
B8: =Lists!$H$6 | E8: =IF(Lists!$H$5,Lists!$H$3,COUNTIF(Lists!$K$2:$K$4,">0")) | H8: =COUNTIFS(Stories!$W$4:$W$153,1,Stories!$D$4:$D$153,5) | K8: =COUNTIFS(Stories!$W$4:$W$153,1,Stories!$E$4:$E$153,"Feature lead") | N8: =COUNTIFS(Stories!$W$4:$W$153,1,Stories!$F$4:$F$153,"Shortlisted")+COUNTIFS(Stories!$W$4:$W$153,1,Stories!$F$4:$F$153,"Commissioned")+COUNTIFS(Stories!$W$4:$W$153,1,Stories!$F$4:$F$153,"Published") | Q8: =COUNTIF(Sources!$C$4:$C$111,">0")
B9: STORIES | E9: =IF(Lists!$H$5,"DAILY DIGESTS","DIGESTS WITH MATCHES") | H9: RATED 5 / 5 | K9: FEATURE LEADS | N9: PLANNED | Q9: SOURCES
B10: ="of "&Lists!$H$4&" in this workbook" | E10: =IF(Lists!$H$5,"scans in this period","of "&Lists!$H$3&" scans in this period") | H10: ="rated 4 / 5: "&COUNTIFS(Stories!$W$4:$W$153,1,Stories!$D$4:$D$153,4) | K10: ="news briefs: "&COUNTIFS(Stories!$W$4:$W$153,1,Stories!$E$4:$E$153,"News brief") | N10: ="shortlisted or later · to review: "&COUNTIFS(Stories!$W$4:$W$153,1,Stories!$F$4:$F$153,"To review") | Q10: ="of 108 outlets in this workbook"
B12: Top 10 stories for this selection
B13: # | C13: Headline (click to open the article) | I13: Digest | J13: Theme | M13: Relevance | N13: Suggested use | P13: Source | R13: Story No. | S13: Status
B14: =IF(Lists!$O$2="","",1) | C14: =IF(Lists!$O$2="","No stories match this selection – choose “All …” or “Any” in a box above.",IF(AND(Lists!$P$2<>"",LEN(Lists!$P$2)<=255),HYPERLINK(Lists!$P$2,Lists!$Q$2),HYPERLINK("#'Stories'!B"&(Lists!$O$2+3),Lists!$Q$2))) | I14: =IF(Lists!$O$2="","",INDEX(Stories!$K$4:$K$153,Lists!$O$2)) | J14: =IF(Lists!$O$2="","",INDEX(Stories!$C$4:$C$153,Lists!$O$2)&"") | M14: =IF(Lists!$O$2="","",INDEX(Stories!$D$4:$D$153,Lists!$O$2)) | N14: =IF(Lists!$O$2="","",INDEX(Stories!$E$4:$E$153,Lists!$O$2)&"") | P14: =IF(Lists!$O$2="","",INDEX(Stories!$J$4:$J$153,Lists!$O$2)&"") | R14: =IF(Lists!$O$2="","",INDEX(Stories!$A$4:$A$153,Lists!$O$2)) | S14: =IF(Lists!$O$2="","",INDEX(Stories!$F$4:$F$153,Lists!$O$2)&"")
B15: =IF(Lists!$O$3="","",2) | C15: =IF(Lists!$O$3="","",IF(AND(Lists!$P$3<>"",LEN(Lists!$P$3)<=255),HYPERLINK(Lists!$P$3,Lists!$Q$3),HYPERLINK("#'Stories'!B"&(Lists!$O$3+3),Lists!$Q$3))) | I15: =IF(Lists!$O$3="","",INDEX(Stories!$K$4:$K$153,Lists!$O$3)) | J15: =IF(Lists!$O$3="","",INDEX(Stories!$C$4:$C$153,Lists!$O$3)&"") | M15: =IF(Lists!$O$3="","",INDEX(Stories!$D$4:$D$153,Lists!$O$3)) | N15: =IF(Lists!$O$3="","",INDEX(Stories!$E$4:$E$153,Lists!$O$3)&"") | P15: =IF(Lists!$O$3="","",INDEX(Stories!$J$4:$J$153,Lists!$O$3)&"") | R15: =IF(Lists!$O$3="","",INDEX(Stories!$A$4:$A$153,Lists!$O$3)) | S15: =IF(Lists!$O$3="","",INDEX(Stories!$F$4:$F$153,Lists!$O$3)&"")
B16: =IF(Lists!$O$4="","",3) | C16: =IF(Lists!$O$4="","",IF(AND(Lists!$P$4<>"",LEN(Lists!$P$4)<=255),HYPERLINK(Lists!$P$4,Lists!$Q$4),HYPERLINK("#'Stories'!B"&(Lists!$O$4+3),Lists!$Q$4))) | I16: =IF(Lists!$O$4="","",INDEX(Stories!$K$4:$K$153,Lists!$O$4)) | J16: =IF(Lists!$O$4="","",INDEX(Stories!$C$4:$C$153,Lists!$O$4)&"") | M16: =IF(Lists!$O$4="","",INDEX(Stories!$D$4:$D$153,Lists!$O$4)) | N16: =IF(Lists!$O$4="","",INDEX(Stories!$E$4:$E$153,Lists!$O$4)&"") | P16: =IF(Lists!$O$4="","",INDEX(Stories!$J$4:$J$153,Lists!$O$4)&"") | R16: =IF(Lists!$O$4="","",INDEX(Stories!$A$4:$A$153,Lists!$O$4)) | S16: =IF(Lists!$O$4="","",INDEX(Stories!$F$4:$F$153,Lists!$O$4)&"")
B17: =IF(Lists!$O$5="","",4) | C17: =IF(Lists!$O$5="","",IF(AND(Lists!$P$5<>"",LEN(Lists!$P$5)<=255),HYPERLINK(Lists!$P$5,Lists!$Q$5),HYPERLINK("#'Stories'!B"&(Lists!$O$5+3),Lists!$Q$5))) | I17: =IF(Lists!$O$5="","",INDEX(Stories!$K$4:$K$153,Lists!$O$5)) | J17: =IF(Lists!$O$5="","",INDEX(Stories!$C$4:$C$153,Lists!$O$5)&"") | M17: =IF(Lists!$O$5="","",INDEX(Stories!$D$4:$D$153,Lists!$O$5)) | N17: =IF(Lists!$O$5="","",INDEX(Stories!$E$4:$E$153,Lists!$O$5)&"") | P17: =IF(Lists!$O$5="","",INDEX(Stories!$J$4:$J$153,Lists!$O$5)&"") | R17: =IF(Lists!$O$5="","",INDEX(Stories!$A$4:$A$153,Lists!$O$5)) | S17: =IF(Lists!$O$5="","",INDEX(Stories!$F$4:$F$153,Lists!$O$5)&"")
B18: =IF(Lists!$O$6="","",5) | C18: =IF(Lists!$O$6="","",IF(AND(Lists!$P$6<>"",LEN(Lists!$P$6)<=255),HYPERLINK(Lists!$P$6,Lists!$Q$6),HYPERLINK("#'Stories'!B"&(Lists!$O$6+3),Lists!$Q$6))) | I18: =IF(Lists!$O$6="","",INDEX(Stories!$K$4:$K$153,Lists!$O$6)) | J18: =IF(Lists!$O$6="","",INDEX(Stories!$C$4:$C$153,Lists!$O$6)&"") | M18: =IF(Lists!$O$6="","",INDEX(Stories!$D$4:$D$153,Lists!$O$6)) | N18: =IF(Lists!$O$6="","",INDEX(Stories!$E$4:$E$153,Lists!$O$6)&"") | P18: =IF(Lists!$O$6="","",INDEX(Stories!$J$4:$J$153,Lists!$O$6)&"") | R18: =IF(Lists!$O$6="","",INDEX(Stories!$A$4:$A$153,Lists!$O$6)) | S18: =IF(Lists!$O$6="","",INDEX(Stories!$F$4:$F$153,Lists!$O$6)&"")
B19: =IF(Lists!$O$7="","",6) | C19: =IF(Lists!$O$7="","",IF(AND(Lists!$P$7<>"",LEN(Lists!$P$7)<=255),HYPERLINK(Lists!$P$7,Lists!$Q$7),HYPERLINK("#'Stories'!B"&(Lists!$O$7+3),Lists!$Q$7))) | I19: =IF(Lists!$O$7="","",INDEX(Stories!$K$4:$K$153,Lists!$O$7)) | J19: =IF(Lists!$O$7="","",INDEX(Stories!$C$4:$C$153,Lists!$O$7)&"") | M19: =IF(Lists!$O$7="","",INDEX(Stories!$D$4:$D$153,Lists!$O$7)) | N19: =IF(Lists!$O$7="","",INDEX(Stories!$E$4:$E$153,Lists!$O$7)&"") | P19: =IF(Lists!$O$7="","",INDEX(Stories!$J$4:$J$153,Lists!$O$7)&"") | R19: =IF(Lists!$O$7="","",INDEX(Stories!$A$4:$A$153,Lists!$O$7)) | S19: =IF(Lists!$O$7="","",INDEX(Stories!$F$4:$F$153,Lists!$O$7)&"")
B20: =IF(Lists!$O$8="","",7) | C20: =IF(Lists!$O$8="","",IF(AND(Lists!$P$8<>"",LEN(Lists!$P$8)<=255),HYPERLINK(Lists!$P$8,Lists!$Q$8),HYPERLINK("#'Stories'!B"&(Lists!$O$8+3),Lists!$Q$8))) | I20: =IF(Lists!$O$8="","",INDEX(Stories!$K$4:$K$153,Lists!$O$8)) | J20: =IF(Lists!$O$8="","",INDEX(Stories!$C$4:$C$153,Lists!$O$8)&"") | M20: =IF(Lists!$O$8="","",INDEX(Stories!$D$4:$D$153,Lists!$O$8)) | N20: =IF(Lists!$O$8="","",INDEX(Stories!$E$4:$E$153,Lists!$O$8)&"") | P20: =IF(Lists!$O$8="","",INDEX(Stories!$J$4:$J$153,Lists!$O$8)&"") | R20: =IF(Lists!$O$8="","",INDEX(Stories!$A$4:$A$153,Lists!$O$8)) | S20: =IF(Lists!$O$8="","",INDEX(Stories!$F$4:$F$153,Lists!$O$8)&"")
B21: =IF(Lists!$O$9="","",8) | C21: =IF(Lists!$O$9="","",IF(AND(Lists!$P$9<>"",LEN(Lists!$P$9)<=255),HYPERLINK(Lists!$P$9,Lists!$Q$9),HYPERLINK("#'Stories'!B"&(Lists!$O$9+3),Lists!$Q$9))) | I21: =IF(Lists!$O$9="","",INDEX(Stories!$K$4:$K$153,Lists!$O$9)) | J21: =IF(Lists!$O$9="","",INDEX(Stories!$C$4:$C$153,Lists!$O$9)&"") | M21: =IF(Lists!$O$9="","",INDEX(Stories!$D$4:$D$153,Lists!$O$9)) | N21: =IF(Lists!$O$9="","",INDEX(Stories!$E$4:$E$153,Lists!$O$9)&"") | P21: =IF(Lists!$O$9="","",INDEX(Stories!$J$4:$J$153,Lists!$O$9)&"") | R21: =IF(Lists!$O$9="","",INDEX(Stories!$A$4:$A$153,Lists!$O$9)) | S21: =IF(Lists!$O$9="","",INDEX(Stories!$F$4:$F$153,Lists!$O$9)&"")
B22: =IF(Lists!$O$10="","",9) | C22: =IF(Lists!$O$10="","",IF(AND(Lists!$P$10<>"",LEN(Lists!$P$10)<=255),HYPERLINK(Lists!$P$10,Lists!$Q$10),HYPERLINK("#'Stories'!B"&(Lists!$O$10+3),Lists!$Q$10))) | I22: =IF(Lists!$O$10="","",INDEX(Stories!$K$4:$K$153,Lists!$O$10)) | J22: =IF(Lists!$O$10="","",INDEX(Stories!$C$4:$C$153,Lists!$O$10)&"") | M22: =IF(Lists!$O$10="","",INDEX(Stories!$D$4:$D$153,Lists!$O$10)) | N22: =IF(Lists!$O$10="","",INDEX(Stories!$E$4:$E$153,Lists!$O$10)&"") | P22: =IF(Lists!$O$10="","",INDEX(Stories!$J$4:$J$153,Lists!$O$10)&"") | R22: =IF(Lists!$O$10="","",INDEX(Stories!$A$4:$A$153,Lists!$O$10)) | S22: =IF(Lists!$O$10="","",INDEX(Stories!$F$4:$F$153,Lists!$O$10)&"")
B23: =IF(Lists!$O$11="","",10) | C23: =IF(Lists!$O$11="","",IF(AND(Lists!$P$11<>"",LEN(Lists!$P$11)<=255),HYPERLINK(Lists!$P$11,Lists!$Q$11),HYPERLINK("#'Stories'!B"&(Lists!$O$11+3),Lists!$Q$11))) | I23: =IF(Lists!$O$11="","",INDEX(Stories!$K$4:$K$153,Lists!$O$11)) | J23: =IF(Lists!$O$11="","",INDEX(Stories!$C$4:$C$153,Lists!$O$11)&"") | M23: =IF(Lists!$O$11="","",INDEX(Stories!$D$4:$D$153,Lists!$O$11)) | N23: =IF(Lists!$O$11="","",INDEX(Stories!$E$4:$E$153,Lists!$O$11)&"") | P23: =IF(Lists!$O$11="","",INDEX(Stories!$J$4:$J$153,Lists!$O$11)&"") | R23: =IF(Lists!$O$11="","",INDEX(Stories!$A$4:$A$153,Lists!$O$11)) | S23: =IF(Lists!$O$11="","",INDEX(Stories!$F$4:$F$153,Lists!$O$11)&"")
C24: Ranked by relevance, then keyword score, then newest digest. Find a story in the Stories sheet by its Story No.
B26: Stories by theme
B27: Theme | F27: Stories | G27: Rated 5 | H27: Rated 4 | I27: Feature leads | J27: Share
B28: Sustainability & the Energy Transition | F28: =SUMPRODUCT(Stories!$W$4:$W$153,--(Stories!$C$4:$C$153=$B28)) | G28: =SUMPRODUCT(Stories!$W$4:$W$153,--(Stories!$C$4:$C$153=$B28),--(Stories!$D$4:$D$153=5)) | H28: =SUMPRODUCT(Stories!$W$4:$W$153,--(Stories!$C$4:$C$153=$B28),--(Stories!$D$4:$D$153=4)) | I28: =SUMPRODUCT(Stories!$W$4:$W$153,--(Stories!$C$4:$C$153=$B28),--(Stories!$E$4:$E$153="Feature lead")) | J28: =IF(Lists!$H$6=0,0,F28/Lists!$H$6)
B29: Digital Geotechnics | F29: =SUMPRODUCT(Stories!$W$4:$W$153,--(Stories!$C$4:$C$153=$B29)) | G29: =SUMPRODUCT(Stories!$W$4:$W$153,--(Stories!$C$4:$C$153=$B29),--(Stories!$D$4:$D$153=5)) | H29: =SUMPRODUCT(Stories!$W$4:$W$153,--(Stories!$C$4:$C$153=$B29),--(Stories!$D$4:$D$153=4)) | I29: =SUMPRODUCT(Stories!$W$4:$W$153,--(Stories!$C$4:$C$153=$B29),--(Stories!$E$4:$E$153="Feature lead")) | J29: =IF(Lists!$H$6=0,0,F29/Lists!$H$6)
B30: Hazards & Resilience | F30: =SUMPRODUCT(Stories!$W$4:$W$153,--(Stories!$C$4:$C$153=$B30)) | G30: =SUMPRODUCT(Stories!$W$4:$W$153,--(Stories!$C$4:$C$153=$B30),--(Stories!$D$4:$D$153=5)) | H30: =SUMPRODUCT(Stories!$W$4:$W$153,--(Stories!$C$4:$C$153=$B30),--(Stories!$D$4:$D$153=4)) | I30: =SUMPRODUCT(Stories!$W$4:$W$153,--(Stories!$C$4:$C$153=$B30),--(Stories!$E$4:$E$153="Feature lead")) | J30: =IF(Lists!$H$6=0,0,F30/Lists!$H$6)
B31: Ground Improvement & Innovation | F31: =SUMPRODUCT(Stories!$W$4:$W$153,--(Stories!$C$4:$C$153=$B31)) | G31: =SUMPRODUCT(Stories!$W$4:$W$153,--(Stories!$C$4:$C$153=$B31),--(Stories!$D$4:$D$153=5)) | H31: =SUMPRODUCT(Stories!$W$4:$W$153,--(Stories!$C$4:$C$153=$B31),--(Stories!$D$4:$D$153=4)) | I31: =SUMPRODUCT(Stories!$W$4:$W$153,--(Stories!$C$4:$C$153=$B31),--(Stories!$E$4:$E$153="Feature lead")) | J31: =IF(Lists!$H$6=0,0,F31/Lists!$H$6)
B32: Infrastructure & the Underground City | F32: =SUMPRODUCT(Stories!$W$4:$W$153,--(Stories!$C$4:$C$153=$B32)) | G32: =SUMPRODUCT(Stories!$W$4:$W$153,--(Stories!$C$4:$C$153=$B32),--(Stories!$D$4:$D$153=5)) | H32: =SUMPRODUCT(Stories!$W$4:$W$153,--(Stories!$C$4:$C$153=$B32),--(Stories!$D$4:$D$153=4)) | I32: =SUMPRODUCT(Stories!$W$4:$W$153,--(Stories!$C$4:$C$153=$B32),--(Stories!$E$4:$E$153="Feature lead")) | J32: =IF(Lists!$H$6=0,0,F32/Lists!$H$6)
B33: Offshore, Coasts & Water | F33: =SUMPRODUCT(Stories!$W$4:$W$153,--(Stories!$C$4:$C$153=$B33)) | G33: =SUMPRODUCT(Stories!$W$4:$W$153,--(Stories!$C$4:$C$153=$B33),--(Stories!$D$4:$D$153=5)) | H33: =SUMPRODUCT(Stories!$W$4:$W$153,--(Stories!$C$4:$C$153=$B33),--(Stories!$D$4:$D$153=4)) | I33: =SUMPRODUCT(Stories!$W$4:$W$153,--(Stories!$C$4:$C$153=$B33),--(Stories!$E$4:$E$153="Feature lead")) | J33: =IF(Lists!$H$6=0,0,F33/Lists!$H$6)
B34: Characterisation & Modelling | F34: =SUMPRODUCT(Stories!$W$4:$W$153,--(Stories!$C$4:$C$153=$B34)) | G34: =SUMPRODUCT(Stories!$W$4:$W$153,--(Stories!$C$4:$C$153=$B34),--(Stories!$D$4:$D$153=5)) | H34: =SUMPRODUCT(Stories!$W$4:$W$153,--(Stories!$C$4:$C$153=$B34),--(Stories!$D$4:$D$153=4)) | I34: =SUMPRODUCT(Stories!$W$4:$W$153,--(Stories!$C$4:$C$153=$B34),--(Stories!$E$4:$E$153="Feature lead")) | J34: =IF(Lists!$H$6=0,0,F34/Lists!$H$6)
B35: Geotechnics & Society | F35: =SUMPRODUCT(Stories!$W$4:$W$153,--(Stories!$C$4:$C$153=$B35)) | G35: =SUMPRODUCT(Stories!$W$4:$W$153,--(Stories!$C$4:$C$153=$B35),--(Stories!$D$4:$D$153=5)) | H35: =SUMPRODUCT(Stories!$W$4:$W$153,--(Stories!$C$4:$C$153=$B35),--(Stories!$D$4:$D$153=4)) | I35: =SUMPRODUCT(Stories!$W$4:$W$153,--(Stories!$C$4:$C$153=$B35),--(Stories!$E$4:$E$153="Feature lead")) | J35: =IF(Lists!$H$6=0,0,F35/Lists!$H$6)
B36: General | F36: =SUMPRODUCT(Stories!$W$4:$W$153,--(Stories!$C$4:$C$153=$B36)) | G36: =SUMPRODUCT(Stories!$W$4:$W$153,--(Stories!$C$4:$C$153=$B36),--(Stories!$D$4:$D$153=5)) | H36: =SUMPRODUCT(Stories!$W$4:$W$153,--(Stories!$C$4:$C$153=$B36),--(Stories!$D$4:$D$153=4)) | I36: =SUMPRODUCT(Stories!$W$4:$W$153,--(Stories!$C$4:$C$153=$B36),--(Stories!$E$4:$E$153="Feature lead")) | J36: =IF(Lists!$H$6=0,0,F36/Lists!$H$6)
B38: Suggested editorial use | H38: Geotechnical relevance | N38: Planning status
B39: Use | E39: Stories | F39: Share | H39: Relevance | K39: Stories | L39: Share | N39: Status | Q39: Stories | R39: Share
B40: Feature lead | E40: =SUMPRODUCT(Stories!$W$4:$W$153,--(Stories!$E$4:$E$153=$B40)) | F40: =IF(Lists!$H$6=0,0,E40/Lists!$H$6) | H40: 5 / 5 | K40: =COUNTIFS(Stories!$W$4:$W$153,1,Stories!$D$4:$D$153,5) | L40: =IF(Lists!$H$6=0,0,K40/Lists!$H$6) | N40: To review | Q40: =COUNTIFS(Stories!$W$4:$W$153,1,Stories!$F$4:$F$153,"To review") | R40: =IF(Lists!$H$6=0,0,Q40/Lists!$H$6)
B41: News brief | E41: =SUMPRODUCT(Stories!$W$4:$W$153,--(Stories!$E$4:$E$153=$B41)) | F41: =IF(Lists!$H$6=0,0,E41/Lists!$H$6) | H41: 4 / 5 | K41: =COUNTIFS(Stories!$W$4:$W$153,1,Stories!$D$4:$D$153,4) | L41: =IF(Lists!$H$6=0,0,K41/Lists!$H$6) | N41: Shortlisted | Q41: =COUNTIFS(Stories!$W$4:$W$153,1,Stories!$F$4:$F$153,"Shortlisted") | R41: =IF(Lists!$H$6=0,0,Q41/Lists!$H$6)
B42: Academia-to-Industry topic | E42: =SUMPRODUCT(Stories!$W$4:$W$153,--(Stories!$E$4:$E$153=$B42)) | F42: =IF(Lists!$H$6=0,0,E42/Lists!$H$6) | H42: 3 / 5 | K42: =COUNTIFS(Stories!$W$4:$W$153,1,Stories!$D$4:$D$153,3) | L42: =IF(Lists!$H$6=0,0,K42/Lists!$H$6) | N42: Commissioned | Q42: =COUNTIFS(Stories!$W$4:$W$153,1,Stories!$F$4:$F$153,"Commissioned") | R42: =IF(Lists!$H$6=0,0,Q42/Lists!$H$6)
B43: Regional insight | E43: =SUMPRODUCT(Stories!$W$4:$W$153,--(Stories!$E$4:$E$153=$B43)) | F43: =IF(Lists!$H$6=0,0,E43/Lists!$H$6) | N43: Published | Q43: =COUNTIFS(Stories!$W$4:$W$153,1,Stories!$F$4:$F$153,"Published") | R43: =IF(Lists!$H$6=0,0,Q43/Lists!$H$6)
B44: Watch only | E44: =SUMPRODUCT(Stories!$W$4:$W$153,--(Stories!$E$4:$E$153=$B44)) | F44: =IF(Lists!$H$6=0,0,E44/Lists!$H$6) | N44: Not used | Q44: =COUNTIFS(Stories!$W$4:$W$153,1,Stories!$F$4:$F$153,"Not used") | R44: =IF(Lists!$H$6=0,0,Q44/Lists!$H$6)
B59: Theme × suggested use (heat map for this selection)
B60: Theme | F60: Feature lead | G60: News brief | H60: Academia-to-Industry topic | I60: Regional insight | J60: Watch only | K60: Total
B61: Sustainability & the Energy Transition | F61: =SUMPRODUCT(Stories!$W$4:$W$153,--(Stories!$C$4:$C$153=$B61),--(Stories!$E$4:$E$153=F$60)) | G61: =SUMPRODUCT(Stories!$W$4:$W$153,--(Stories!$C$4:$C$153=$B61),--(Stories!$E$4:$E$153=G$60)) | H61: =SUMPRODUCT(Stories!$W$4:$W$153,--(Stories!$C$4:$C$153=$B61),--(Stories!$E$4:$E$153=H$60)) | I61: =SUMPRODUCT(Stories!$W$4:$W$153,--(Stories!$C$4:$C$153=$B61),--(Stories!$E$4:$E$153=I$60)) | J61: =SUMPRODUCT(Stories!$W$4:$W$153,--(Stories!$C$4:$C$153=$B61),--(Stories!$E$4:$E$153=J$60)) | K61: =SUM(F61:J61)
B62: Digital Geotechnics | F62: =SUMPRODUCT(Stories!$W$4:$W$153,--(Stories!$C$4:$C$153=$B62),--(Stories!$E$4:$E$153=F$60)) | G62: =SUMPRODUCT(Stories!$W$4:$W$153,--(Stories!$C$4:$C$153=$B62),--(Stories!$E$4:$E$153=G$60)) | H62: =SUMPRODUCT(Stories!$W$4:$W$153,--(Stories!$C$4:$C$153=$B62),--(Stories!$E$4:$E$153=H$60)) | I62: =SUMPRODUCT(Stories!$W$4:$W$153,--(Stories!$C$4:$C$153=$B62),--(Stories!$E$4:$E$153=I$60)) | J62: =SUMPRODUCT(Stories!$W$4:$W$153,--(Stories!$C$4:$C$153=$B62),--(Stories!$E$4:$E$153=J$60)) | K62: =SUM(F62:J62)
B63: Hazards & Resilience | F63: =SUMPRODUCT(Stories!$W$4:$W$153,--(Stories!$C$4:$C$153=$B63),--(Stories!$E$4:$E$153=F$60)) | G63: =SUMPRODUCT(Stories!$W$4:$W$153,--(Stories!$C$4:$C$153=$B63),--(Stories!$E$4:$E$153=G$60)) | H63: =SUMPRODUCT(Stories!$W$4:$W$153,--(Stories!$C$4:$C$153=$B63),--(Stories!$E$4:$E$153=H$60)) | I63: =SUMPRODUCT(Stories!$W$4:$W$153,--(Stories!$C$4:$C$153=$B63),--(Stories!$E$4:$E$153=I$60)) | J63: =SUMPRODUCT(Stories!$W$4:$W$153,--(Stories!$C$4:$C$153=$B63),--(Stories!$E$4:$E$153=J$60)) | K63: =SUM(F63:J63)
B64: Ground Improvement & Innovation | F64: =SUMPRODUCT(Stories!$W$4:$W$153,--(Stories!$C$4:$C$153=$B64),--(Stories!$E$4:$E$153=F$60)) | G64: =SUMPRODUCT(Stories!$W$4:$W$153,--(Stories!$C$4:$C$153=$B64),--(Stories!$E$4:$E$153=G$60)) | H64: =SUMPRODUCT(Stories!$W$4:$W$153,--(Stories!$C$4:$C$153=$B64),--(Stories!$E$4:$E$153=H$60)) | I64: =SUMPRODUCT(Stories!$W$4:$W$153,--(Stories!$C$4:$C$153=$B64),--(Stories!$E$4:$E$153=I$60)) | J64: =SUMPRODUCT(Stories!$W$4:$W$153,--(Stories!$C$4:$C$153=$B64),--(Stories!$E$4:$E$153=J$60)) | K64: =SUM(F64:J64)
B65: Infrastructure & the Underground City | F65: =SUMPRODUCT(Stories!$W$4:$W$153,--(Stories!$C$4:$C$153=$B65),--(Stories!$E$4:$E$153=F$60)) | G65: =SUMPRODUCT(Stories!$W$4:$W$153,--(Stories!$C$4:$C$153=$B65),--(Stories!$E$4:$E$153=G$60)) | H65: =SUMPRODUCT(Stories!$W$4:$W$153,--(Stories!$C$4:$C$153=$B65),--(Stories!$E$4:$E$153=H$60)) | I65: =SUMPRODUCT(Stories!$W$4:$W$153,--(Stories!$C$4:$C$153=$B65),--(Stories!$E$4:$E$153=I$60)) | J65: =SUMPRODUCT(Stories!$W$4:$W$153,--(Stories!$C$4:$C$153=$B65),--(Stories!$E$4:$E$153=J$60)) | K65: =SUM(F65:J65)
B66: Offshore, Coasts & Water | F66: =SUMPRODUCT(Stories!$W$4:$W$153,--(Stories!$C$4:$C$153=$B66),--(Stories!$E$4:$E$153=F$60)) | G66: =SUMPRODUCT(Stories!$W$4:$W$153,--(Stories!$C$4:$C$153=$B66),--(Stories!$E$4:$E$153=G$60)) | H66: =SUMPRODUCT(Stories!$W$4:$W$153,--(Stories!$C$4:$C$153=$B66),--(Stories!$E$4:$E$153=H$60)) | I66: =SUMPRODUCT(Stories!$W$4:$W$153,--(Stories!$C$4:$C$153=$B66),--(Stories!$E$4:$E$153=I$60)) | J66: =SUMPRODUCT(Stories!$W$4:$W$153,--(Stories!$C$4:$C$153=$B66),--(Stories!$E$4:$E$153=J$60)) | K66: =SUM(F66:J66)
B67: Characterisation & Modelling | F67: =SUMPRODUCT(Stories!$W$4:$W$153,--(Stories!$C$4:$C$153=$B67),--(Stories!$E$4:$E$153=F$60)) | G67: =SUMPRODUCT(Stories!$W$4:$W$153,--(Stories!$C$4:$C$153=$B67),--(Stories!$E$4:$E$153=G$60)) | H67: =SUMPRODUCT(Stories!$W$4:$W$153,--(Stories!$C$4:$C$153=$B67),--(Stories!$E$4:$E$153=H$60)) | I67: =SUMPRODUCT(Stories!$W$4:$W$153,--(Stories!$C$4:$C$153=$B67),--(Stories!$E$4:$E$153=I$60)) | J67: =SUMPRODUCT(Stories!$W$4:$W$153,--(Stories!$C$4:$C$153=$B67),--(Stories!$E$4:$E$153=J$60)) | K67: =SUM(F67:J67)
B68: Geotechnics & Society | F68: =SUMPRODUCT(Stories!$W$4:$W$153,--(Stories!$C$4:$C$153=$B68),--(Stories!$E$4:$E$153=F$60)) | G68: =SUMPRODUCT(Stories!$W$4:$W$153,--(Stories!$C$4:$C$153=$B68),--(Stories!$E$4:$E$153=G$60)) | H68: =SUMPRODUCT(Stories!$W$4:$W$153,--(Stories!$C$4:$C$153=$B68),--(Stories!$E$4:$E$153=H$60)) | I68: =SUMPRODUCT(Stories!$W$4:$W$153,--(Stories!$C$4:$C$153=$B68),--(Stories!$E$4:$E$153=I$60)) | J68: =SUMPRODUCT(Stories!$W$4:$W$153,--(Stories!$C$4:$C$153=$B68),--(Stories!$E$4:$E$153=J$60)) | K68: =SUM(F68:J68)
B69: General | F69: =SUMPRODUCT(Stories!$W$4:$W$153,--(Stories!$C$4:$C$153=$B69),--(Stories!$E$4:$E$153=F$60)) | G69: =SUMPRODUCT(Stories!$W$4:$W$153,--(Stories!$C$4:$C$153=$B69),--(Stories!$E$4:$E$153=G$60)) | H69: =SUMPRODUCT(Stories!$W$4:$W$153,--(Stories!$C$4:$C$153=$B69),--(Stories!$E$4:$E$153=H$60)) | I69: =SUMPRODUCT(Stories!$W$4:$W$153,--(Stories!$C$4:$C$153=$B69),--(Stories!$E$4:$E$153=I$60)) | J69: =SUMPRODUCT(Stories!$W$4:$W$153,--(Stories!$C$4:$C$153=$B69),--(Stories!$E$4:$E$153=J$60)) | K69: =SUM(F69:J69)
B72: Stories per daily digest
B73: Daily digest | F73: All stories | G73: This selection
B74: 24 Oct 2026 | F74: 60 | G74: =COUNTIFS(Stories!$W$4:$W$153,1,Stories!$K$4:$K$153,DATE(2026,10,24))
B75: 25 Oct 2026 | F75: 47 | G75: =COUNTIFS(Stories!$W$4:$W$153,1,Stories!$K$4:$K$153,DATE(2026,10,25))
B76: 26 Oct 2026 | F76: 43 | G76: =COUNTIFS(Stories!$W$4:$W$153,1,Stories!$K$4:$K$153,DATE(2026,10,26))

Sheet Stories
A1: Stories · 150 in this workbook | C1: ← Dashboard | D1: ↑ Start here | E1: By theme →
C2: Gold columns are yours: choose a Status from its dropdown, and fill in Assigned to and Editor notes. Use ▼ in the header to filter or sort. ✓ in ‘In Dashboard selection’ (far right) marks the stories the Dashboard is showing.
A3: No. | B3: Headline (English or Claude's translation) | C3: Theme | D3: Relevance | E3: Suggested use | F3: Status | G3: Assigned to | H3: Editor notes | I3: Magazine angle | J3: Source | K3: Digest date | L3: Original headline | M3: Primary source to check | N3: Country | O3: Place | P3: Developing story | Q3: Google News edition | R3: Published | S3: Issue window | T3: Keywords | U3: Keyword score | V3: Article URL | W3: In Dashboard selection | X3: Top-10 key (helper)
A4: 1 | B4: Kumamoto earthquake: 96% of liquefaction sites reoccurred | C4: Hazards & Resilience | D4: 5 | E4: Feature lead | F4: To review | I4: Why do the same sites re-liquefy in repeated earthquakes, and which ground improvement or site-specific measures actually stop recurrence? | J4: Yahoo!ニュース | K4: 46321 | L4: 熊本地震 液状化地点の96%で再発 | M4: Kumamoto Prefectural Government and the research team behind the liquefaction survey | N4: Japan | O4: Kumamoto Prefecture | Q4: Japan | R4: 46321 | S4: 2026-Q4 | T4: liquefaction, earthquake | U4: 7 | V4: https://news.google.com/rss/articles/CBMiUEFVX3lxTE9sUlNwdEcwMURBRkNDb3dEd0NfVFIzaG9RTUMtYkQ0dnNpT3ByQjFVWFJPYkhjWDNqOFlXNkVrOFk3VzB6NHB1MGtjU1Bfa0d6?oc=5 | W4: =IF($B4="",0,IF(AND(OR(OR(Dashboard!$B$5="All themes",Dashboard!$B$5=""),$C4=Dashboard!$B$5),OR(OR(Dashboard!$G$5="All uses",Dashboard!$G$5=""),$E4=Dashboard!$G$5),N($D4)>=Lists!$H$2,OR(OR(Dashboard!$N$5="All windows",Dashboard!$N$5=""),$S4=Dashboard!$N$5)),1,0)) | X4: =IF($W4=1,N($D4)*1E14+MIN(MAX(N($U4),0),9999)*1E10+MIN(N($K4),99999)*1E5+99999-MIN(ROW(),99999),"")
A5: 2 | B5: 96% of sites with upper seismic intensity 6 in the Kumamoto earthquake re-liquefied; experts urge advance countermeasures. | C5: Hazards & Resilience | D5: 5 | E5: Watch only | F5: To review | I5: Why do the same sites re-liquefy in repeated earthquakes, and which ground improvement or site-specific measures actually stop recurrence? | J5: 読売新聞 | K5: 46321 | L5: 熊本地震「震度６強」の９６％が再液状化…繰り返される被害、専門家は事前対策訴え | M5: Kumamoto Prefectural Government and the research team behind the liquefaction survey | N5: Japan | O5: Kumamoto Prefecture | Q5: Japan | R5: 46320 | S5: 2026-Q4 | T5: liquefaction, earthquake | U5: 7 | V5: https://news.google.com/rss/articles/CBMiZkFVX3lxTFA3VmNVcVpnS3U1V0ZuanVlb3VQdnhpaDN3NGlETGFPa3h5bURmWGJUUGJsdjh6SENpWGFUUHNGa3pMbUJNd0FndDBkakstVzV2b0U5bjVMOFRFVDFrTS1ob3RwTTZPZw?oc=5 | W5: =IF($B5="",0,IF(AND(OR(OR(Dashboard!$B$5="All themes",Dashboard!$B$5=""),$C5=Dashboard!$B$5),OR(OR(Dashboard!$G$5="All uses",Dashboard!$G$5=""),$E5=Dashboard!$G$5),N($D5)>=Lists!$H$2,OR(OR(Dashboard!$N$5="All windows",Dashboard!$N$5=""),$S5=Dashboard!$N$5)),1,0)) | X5: =IF($W5=1,N($D5)*1E14+MIN(MAX(N($U5),0),9999)*1E10+MIN(N($K5),99999)*1E5+99999-MIN(ROW(),99999),"")
A6: 3 | B6: Ancient Earthquakes Triggered Massive 10,000-Year-Old Landslides In Kashmir Himalaya, New Study Reveals | C6: Hazards & Resilience | D6: 5 | E6: Feature lead | F6: To review | I6: Can dating of ancient landslide deposits be used to infer earthquake recurrence and slope hazard in tectonically active Himalayan terrain? | J6: Kashmir Life | K6: 46321 | M6: the study's lead research institution (check the journal paper) | N6: India | O6: Kashmir Himalaya | Q6: United Kingdom | R6: 46321 | S6: 2026-Q4 | T6: landslide, earthquake | U6: 6 | V6: https://news.google.com/rss/articles/CBMizgFBVV95cUxPeUtDQ05KR3BiV2d5RkNjVUJSb29EZlZaRks5VlJvb1g3STk4dEliaDZ1Smt3Yk53bnFJdndubXJYN0xXZkNGV0ZpT09ZZVdmTWpWUHNpUFo4Z2hiTFFVQkVjaWJ5aEZOYnUzakhPNHVWVmx4U0V0c1ZBU1owYUhRLVNUNy12d1N5U3ZHOVB3bE5kOW5yRndjQXc2am5YUGdMbmJQQ19EVVpGTEJXLUpYTFY0QUpkS0FPZ0wxdDdLejZ1RVBGZkZaOEFQR0lEZw?oc=5 | W6: =IF($B6="",0,IF(AND(OR(OR(Dashboard!$B$5="All themes",Dashboard!$B$5=""),$C6=Dashboard!$B$5),OR(OR(Dashboard!$G$5="All uses",Dashboard!$G$5=""),$E6=Dashboard!$G$5),N($D6)>=Lists!$H$2,OR(OR(Dashboard!$N$5="All windows",Dashboard!$N$5=""),$S6=Dashboard!$N$5)),1,0)) | X6: =IF($W6=1,N($D6)*1E14+MIN(MAX(N($U6),0),9999)*1E10+MIN(N($K6),99999)*1E5+99999-MIN(ROW(),99999),"")
A7: 4 | B7: Niscemi, nine months after the landslide: the town hanging over the void and thirty years of broken promises. | C7: Hazards & Resilience | D7: 5 | E7: Feature lead | F7: To review | I7: Why does a large landslide keep a hilltop town in limbo months later, and what geotechnical monitoring and stabilisation strategy could justify either remaining or relocating residents? | J7: la Repubblica | K7: 46321 | L7: Niscemi, nove mesi dopo la frana: la città sospesa sul vuoto e trent'anni di promesse tradite | M7: Italian Civil Protection Department and Comune di Niscemi | N7: Italy | O7: Niscemi, Sicily | P7: Niscemi landslide, Sicily (Jan 2026) · Update · 2 reports | Q7: Italy | R7: 46321 | S7: 2026-Q4 | T7: landslide | U7: 4 | V7: https://news.google.com/rss/articles/CBMiqwFBVV95cUxQUVljZ2Z4NlVrQkw3RXVnMUxoZ1hCVjRvWjJ4TDlQSVRaaHF3RFRILUxNck1KQXB3RS1wTTlnZEhyMkxlMjBqR25udVNxVXZFLXRhX0IyX2VuUGJDTEl1a1RPUS1tcDRmd3hkWmpEQnQ4UF91dF9MY25OcEZ1czBzaXNlZFVuTjZxVVVCN0JKNVBtSmZtRUlvNV94Q1dzRWxuYlU5UXdGUTdaMzDSAasBQVVfeXFMUFFZY2dmeDZVa0JMN0V1ZzFMaGdYQlY0b1oyeEw5UElUWmhxd0RUSC1MTXJNSkFwd0UtcE05Z2RIcjJMZTIwakdubnVTcVV2RS10YV9CMl9lblBiQ0xJdWtUT1EtbXA0Znd4ZFpqREJ0OFBfdXRfTGNuTnBGdXMwc2lzZWRVbk42cVVVQjdCSjVQbUpmbUVJbzVfeENXc0VsbmJVOVF3RlE3WjMw?oc=5 | W7: =IF($B7="",0,IF(AND(OR(OR(Dashboard!$B$5="All themes",Dashboard!$B$5=""),$C7=Dashboard!$B$5),OR(OR(Dashboard!$G$5="All uses",Dashboard!$G$5=""),$E7=Dashboard!$G$5),N($D7)>=Lists!$H$2,OR(OR(Dashboard!$N$5="All windows",Dashboard!$N$5=""),$S7=Dashboard!$N$5)),1,0)) | X7: =IF($W7=1,N($D7)*1E14+MIN(MAX(N($U7),0),9999)*1E10+MIN(N($K7),99999)*1E5+99999-MIN(ROW(),99999),"")
A8: 5 | B8: Liu Yushui garden earth collapse kills; SAM says it warned repeatedly about hillside development risks | C8: Hazards & Resilience | D8: 5 | E8: Feature lead | F8: To review | I8: How do hillside development practices and repeated unheeded warnings contribute to fatal slope failures, and what geotechnical due diligence should apply to hillside housing? | J8: China Press | K8: 46321 | L8: 刘玉水花园土崩夺命 SAM：已多次警告 山坡发展风险 | M8: Penang state government and the police | N8: Malaysia | P8: Paya Terubong landslide, Penang, Malaysia (Oct 2026) · Investigation & inquiry · 7 reports | Q8: China | R8: 46320 | S8: 2026-Q4 | T8: slope | U8: 2 | V8: https://news.google.com/rss/articles/CBMi2wJBVV95cUxPaUpqb21fRVV2bFlHYU5ud1p3NFVmYVpIMWN4U2Z5S1lOS2lVWGpsb0p4ZnIwZUIxOHQ4OVNXTlhjTWg2Nk9CRTI4cEY1VEJRREV6SmxiQnliUF9pYmh4ekpfQUkwRGxsYW9TOFE1VzdxTDc5bmk2Z2RGbTduX3lIVDVrbFN0eXlualBsSFZ6TzJranBnWi1TSHlKT1FhTDQ5bFpwODI0RVhTVTlOYW9iNjhGc1puZGJkQ1kwUTdZb2IxY1FHTV9DRWFvYnJPd1lWb3ZyOTNxMVNRTGtwd0w0a0RXaFRRMG1WZ1RKUDk0OUJQMHJTN3VjNm5DanhLR3g3eTRmQm8tU1F0bm5EVHJCUkFvR05hejY3NWFPNmhmUkxSZlJFSjFOTVdLRmEyVVY1akMxdWNNSjUzSWhyMmVaTDE5cWhoS2NRWEdrTWVmdE80SUZ6Uldlb0VTZw?oc=5 | W8: =IF($B8="",0,IF(AND(OR(OR(Dashboard!$B$5="All themes",Dashboard!$B$5=""),$C8=Dashboard!$B$5),OR(OR(Dashboard!$G$5="All uses",Dashboard!$G$5=""),$E8=Dashboard!$G$5),N($D8)>=Lists!$H$2,OR(OR(Dashboard!$N$5="All windows",Dashboard!$N$5=""),$S8=Dashboard!$N$5)),1,0)) | X8: =IF($W8=1,N($D8)*1E14+MIN(MAX(N($U8),0),9999)*1E10+MIN(N($K8),99999)*1E5+99999-MIN(ROW(),99999),"")
A9: 6 | B9: Ground crumbles and gas escapes: thousands of dangerous sites identified in Yamal | C9: Sustainability & the Energy Transition | D9: 5 | E9: Feature lead | F9: To review | I9: How is permafrost thaw and gas migration causing ground collapse and craters across Yamal, and what monitoring and foundation strategies can manage thousands of hazardous sites? | J9: Life.ru | K9: 46321 | L9: Грунт рушится, а газ рвётся наружу: На Ямале выявили тысячи опасных участков | M9: Yamal regional authorities and the gas operators | N9: Russia | O9: Yamal | Q9: Russia | R9: 46320 | S9: 2026-Q4 | T9: soil | U9: 1 | V9: https://news.google.com/rss/articles/CBMilgFBVV95cUxNdFl6QWFvMFBRQ3hMOFc2S0hRdkIzNWViQXFZaFB1b2h5eEx5czUwbnhOeFNKX3MybWRfLVhhdlJjb0s0eFUtMDloNFJoUTEtb0dRRElGdllDbFVOejZFS0o4NzUwN2lhNlkyMzdlZzBCR1NpaXhKN1ZSZjZHRG1RV1JFQVpJRFNxQW1xcTBZWUMxWnVxRnc?oc=5 | W9: =IF($B9="",0,IF(AND(OR(OR(Dashboard!$B$5="All themes",Dashboard!$B$5=""),$C9=Dashboard!$B$5),OR(OR(Dashboard!$G$5="All uses",Dashboard!$G$5=""),$E9=Dashboard!$G$5),N($D9)>=Lists!$H$2,OR(OR(Dashboard!$N$5="All windows",Dashboard!$N$5=""),$S9=Dashboard!$N$5)),1,0)) | X9: =IF($W9=1,N($D9)*1E14+MIN(MAX(N($U9),0),9999)*1E10+MIN(N($K9),99999)*1E5+99999-MIN(ROW(),99999),"")
A10: 7 | B10: Silkyara tunnel may open before the upcoming Char Dham yatra, company claims; Yamunotri distance to shrink by 26 km | C10: Infrastructure & the Underground City | D10: 5 | E10: Feature lead | F10: To review | I10: What ground stabilisation and rock mass conditions must be verified before a collapsed Himalayan tunnel can safely reopen, and how credible is the proposed schedule? | J10: Dainik Bhaskar | K10: 46321 | L10: सिलक्यारा टनल आगामी चारधाम यात्रा तक खुल सकती है: कंपनी का दावा; यमुनोत्री धाम की 26 किमी दूरी घटेगी, समय औ... | M10: NHIDCL (the project owner) and the contractor | N10: India | O10: Silkyara tunnel, Uttarkashi | Q10: India | R10: 46320 | S10: 2026-Q4 | U10: 0 | V10: https://news.google.com/rss/articles/CBMi1gFBVV95cUxNYUVkaGtnY09kNFJzUnNQUmFla3RVLUJyMzRiTy1aWGtEWmVrMWNCeFF0YWJBLTd1dHN2VVd2UlFNZGNTNWlFNUZOdU1RbWl0NWloV1MyUWZoOUkxOUhubWZqbl9IQndyY2VLTUFQZjV4RW55bmdWUHE0YmFXNnZDRHlLS0hiQTllQVJxQ1d2Si1VYjhtcWxmR05hZGJ0MzZONmlaX1VpZm41TWs2QXROM2p6a1U4cnViakV1TWRTNklwakJRdkpVZjBlNDJEVFVwLXRzMFVR0gHWAUFVX3lxTE1hRWRoa2djT2Q0UnNSc1BSYWVrdFUtQnIzNGJPLVpYa0RaZWsxY0J4UXRhYkEtN3V0c3ZVV3ZSUU1kY1M1aUU1Rk51TVFtaXQ1aWhXUzJRZmg5STE5SG5tZmpuX0hCd3JjZUtNQVBmNXhFbnluZ1ZQcTRiYVc2dkNEeUtLSGJBOWVBUnFDV3ZKLVViOG1xbGZHTmFkYnQzNk42aVpfVWlmbjVNazZBdE4zanprVThydWJqRXVNZFM2SXBqQlF2SlVmMGU0MkRUVXAtdHMwVVE?oc=5 | W10: =IF($B10="",0,IF(AND(OR(OR(Dashboard!$B$5="All themes",Dashboard!$B$5=""),$C10=Dashboard!$B$5),OR(OR(Dashboard!$G$5="All uses",Dashboard!$G$5=""),$E10=Dashboard!$G$5),N($D10)>=Lists!$H$2,OR(OR(Dashboard!$N$5="All windows",Dashboard!$N$5=""),$S10=Dashboard!$N$5)),1,0)) | X10: =IF($W10=1,N($D10)*1E14+MIN(MAX(N($U10),0),9999)*1E10+MIN(N($K10),99999)*1E5+99999-MIN(ROW(),99999),"")
A11: 8 | B11: Rock blocks over 500 tonnes threaten Turkey–Georgia road; experts demand inspection of 50 km | C11: Hazards & Resilience | D11: 5 | E11: Feature lead | F11: To review | I11: How can rockfall hazard along a mountain highway be assessed for very large blocks, and what slope-scaling and stabilisation approach suits a 50 km stretch? | J11: تركيا عاجل | K11: 46321 | L11: كتل صخرية تتجاوز 500 طن تهدد طريق تركيا-جورجيا.. خبراء يطالبون بفحص 50 كيلومترًا | M11: the General Directorate of Highways (KGM) | N11: Türkiye | O11: Turkey–Georgia road | Q11: Egypt | R11: 46320 | S11: 2026-Q4 | U11: 0 | V11: https://news.google.com/rss/articles/CBMi3wJBVV95cUxPSDh4cHZPcTZteEUtQTEtU2lZdGtHRUZiWDQwV192QUxleXF4TVZCTEY4XzR5Vmc3dmd1TEJxUFAxdy0yZjNBUzJ1cEhtTW9HRHhKUlRJdnp6SF9STE1EVnNRMFJYVVVWaDU2c0hCY00yQU9leVA0ZHpXaGMyMER1LVNuZHZybktTU2E0R0dfTkdMNnJMYjhsenNqT3diVGY5MFowZGNHNFIxVEg4S01LclRER0l0QW5BSUFDb1E4WndWcGtwYTZOX3BIZEZIaXNic2cyTjdGV09QNlJfVnJOcTl1WG5kTXEtZm40MXhJLVpQdktQanlCcThBeXl2VHRDSGxQc1FrZ0hYTkpTRUpmbTNneVdxS0tvaGtxNF9PVWRBaHBPUDZBSEVkTk5qOHdtMzV1a0Zncy1HQ19NQTlDSnRLQ2dtU184WC1obWEyQUFaenoxWVFCRnpFazFCTkk?oc=5 | W11: =IF($B11="",0,IF(AND(OR(OR(Dashboard!$B$5="All themes",Dashboard!$B$5=""),$C11=Dashboard!$B$5),OR(OR(Dashboard!$G$5="All uses",Dashboard!$G$5=""),$E11=Dashboard!$G$5),N($D11)>=Lists!$H$2,OR(OR(Dashboard!$N$5="All windows",Dashboard!$N$5=""),$S11=Dashboard!$N$5)),1,0)) | X11: =IF($W11=1,N($D11)*1E14+MIN(MAX(N($U11),0),9999)*1E10+MIN(N($K11),99999)*1E5+99999-MIN(ROW(),99999),"")
A12: 9 | B12: Longwei earth collapse death: autopsy report released, cause is traumatic asphyxia | C12: Hazards & Resilience | D12: 5 | E12: Feature lead | F12: To review | I12: What does the post-mortem finding of a traumatic death reveal about the safety of hillside collapse rescue and the failure of earlier slope warnings? | J12: China Press | K12: 46321 | L12: 垄尾土崩酿一死｜死者解剖报告出炉 死因是创伤性窒息 | M12: Penang state government and the police | N12: Malaysia | Q12: China | R12: 46321 | S12: 2026-Q4 | U12: 0 | V12: https://news.google.com/rss/articles/CBMi2wJBVV95cUxNSldHQkhacnFXOW9uNFFPVC1kbkdZbW1KcVhfbjZGdGdIZFhBbmd5SjVCeGRtOW5vdllWQmFwZGo2bTdNOThuVmR0dkNDSjNMVHZQYmVSNldnNWhjRlRQR2VCTU0xSmZ4N0hJZ01XUGN0ZGI0dWtTLUpkS0poX3ZxRnVpY3FLLVpYQWZxRVktNFhjeVpwTXU5WWI0RGY3X3NhUG9UVHByNnFLRkpBbmxwYnE2Y3VUaWhZU0duOVlzNDk2YWNrVGsyOXlsREV3V3ZYM0o3ZVZXUk91Z2paQ1hlWE9haGZPemIwbVdvWjZLbTNjNkUzQlJNUmpDeTVQZTQxQzI3enk2UU5RX1lxNmlfa1NudG45WjE5SlotTXlaS3lhdW5MaEtwTDNESnVXajkwak04MUwwYUZiYW5FMHM3S2xSRTZKbGROazZQR0ZzS055aGh1Rl9Nc3pCdw?oc=5 | W12: =IF($B12="",0,IF(AND(OR(OR(Dashboard!$B$5="All themes",Dashboard!$B$5=""),$C12=Dashboard!$B$5),OR(OR(Dashboard!$G$5="All uses",Dashboard!$G$5=""),$E12=Dashboard!$G$5),N($D12)>=Lists!$H$2,OR(OR(Dashboard!$N$5="All windows",Dashboard!$N$5=""),$S12=Dashboard!$N$5)),1,0)) | X12: =IF($W12=1,N($D12)*1E14+MIN(MAX(N($U12),0),9999)*1E10+MIN(N($K12),99999)*1E5+99999-MIN(ROW(),99999),"")
A13: 10 | B13: Deslizamiento de talud afecta sótanos y locales de plaza comercial en Cuajimalpa | C13: Hazards & Resilience | D13: 4 | E13: Feature lead | F13: To review | I13: How should basements and retail excavations beside unstable natural slopes be designed and monitored so that slope movement does not reach occupied spaces? | J13: El Universal | K13: 46321 | M13: Mexico City Protección Civil and the borough's building authority | N13: Mexico | O13: Cuajimalpa, Mexico City | Q13: Spain | R13: 46321 | S13: 2026-Q4 | T13: landslide, retaining wall | U13: 8 | V13: https://news.google.com/rss/articles/CBMi3gFBVV95cUxQS0l6Zm44UzhLZWp1WEhEeDlhUDQ4YkJaaVMtcTVRdUZqV2N0YU9VWmFRb1Q1Q1dfdW12dFBKUTU4aHViU0NKOENyY0JKM3hQM2pxZng4QzlDMG45WVhydDJybkdZQ2tXY2VxUEdnTjRQSGFNZjdubGQ4UFlrYVhhVFhTMTg4SGszQkFMVDlha1lmdFZyVXBSYTJ3cENnN1RvQmtmeU9KZGlGcHgxeERaNC11MjVLeDV4eC13R090RnhHc0RQWFZBalRYNktRdVRpbHFWN19FR2NYeGx4dUHSAfIBQVVfeXFMTVEwQTl0MUFJZ1VtQXlLalgzS3BXTjFzVmJFeUFmU1BqZVZnY09VQWRCeTZTenNtLVBUT2JPbVFfZ2tGSzJyekF5Y0JWRUF6Sk4tdi1wN1FieTZUNEM2U2hJcGZBTFJNdkY1aDNkckc4Q0hFa2JaRFhDWVBMNnkzS3Nya2QzYVJRanVsVXN1MGUtTjJYTjNVNGVNWHR2bml0Q2tUSFhIMmR5c25XTmdlMGZ6TGVCc2ZHUW5XY1N2VXFUSUtzNUZGdlBpZFVGeDVjUl81QzVBTlhMOWd2eFJUNWdUOHhCZEhqR3pOYWtHRFBKVGc?oc=5 | W13: =IF($B13="",0,IF(AND(OR(OR(Dashboard!$B$5="All themes",Dashboard!$B$5=""),$C13=Dashboard!$B$5),OR(OR(Dashboard!$G$5="All uses",Dashboard!$G$5=""),$E13=Dashboard!$G$5),N($D13)>=Lists!$H$2,OR(OR(Dashboard!$N$5="All windows",Dashboard!$N$5=""),$S13=Dashboard!$N$5)),1,0)) | X13: =IF($W13=1,N($D13)*1E14+MIN(MAX(N($U13),0),9999)*1E10+MIN(N($K13),99999)*1E5+99999-MIN(ROW(),99999),"")
A14: 11 | B14: Fuerte deslave en Centro Santa Fe: colapsa talud de 30 metros y afecta locales | C14: Hazards & Resilience | D14: 4 | E14: Feature lead | F14: To review | I14: What failure mechanisms could bring down a 30 m cut slope in a dense urban business district, and what monitoring would have given early warning? | J14: PostaMx | K14: 46321 | M14: Mexico City Protección Civil and the developer's geotechnical consultant | N14: Mexico | O14: Centro Santa Fe, Mexico City | Q14: Spain | R14: 46321 | S14: 2026-Q4 | T14: landslide, retaining wall | U14: 8 | V14: https://news.google.com/rss/articles/CBMiyAFBVV95cUxQd1RPVUlZbTlJeGVMQi1xZjBBU0RZUVZnMkNFRlAtTzZVUTdXd3RWbTVGTDc1b2lnb2haM1YyM0pQQVF2MHBVMFZvdUpEN2hzQ2prQWhVT0hYNmxwZG9yQVNBWlF2SUlPbFpJN1VrdWNYRGRNdkJJejJReEFwZ080WUs0MTh5NHB1a2hJcWdOdWZpYlJscUg1RUhGX3dnRkJDazhMOUZrQ3BVQk1BNVJLZTNfUndUMXJEU05vd1NYSmkwYVpsdGowVdIByAFBVV95cUxQd1RPVUlZbTlJeGVMQi1xZjBBU0RZUVZnMkNFRlAtTzZVUTdXd3RWbTVGTDc1b2lnb2haM1YyM0pQQVF2MHBVMFZvdUpEN2hzQ2prQWhVT0hYNmxwZG9yQVNBWlF2SUlPbFpJN1VrdWNYRGRNdkJJejJReEFwZ080WUs0MTh5NHB1a2hJcWdOdWZpYlJscUg1RUhGX3dnRkJDazhMOUZrQ3BVQk1BNVJLZTNfUndUMXJEU05vd1NYSmkwYVpsdGowVQ?oc=5 | W14: =IF($B14="",0,IF(AND(OR(OR(Dashboard!$B$5="All themes",Dashboard!$B$5=""),$C14=Dashboard!$B$5),OR(OR(Dashboard!$G$5="All uses",Dashboard!$G$5=""),$E14=Dashboard!$G$5),N($D14)>=Lists!$H$2,OR(OR(Dashboard!$N$5="All windows",Dashboard!$N$5=""),$S14=Dashboard!$N$5)),1,0)) | X14: =IF($W14=1,N($D14)*1E14+MIN(MAX(N($U14),0),9999)*1E10+MIN(N($K14),99999)*1E5+99999-MIN(ROW(),99999),"")
A15: 12 | B15: Progress review of dyke and retaining wall packages to prevent landslides along the Tien River. | C15: Hazards & Resilience | D15: 4 | E15: Regional insight | F15: To review | I15: What design and construction sequencing issues arise when riverbank dykes and retaining walls are upgraded in stages along an active erosion-prone river? | J15: Vietnam.vn | K15: 46321 | L15: Meninjau kemajuan paket konstruksi dalam Proyek peningkatan tanggul dan dinding penahan untuk mencegah tanah longsor di sepanjang Sungai Tien. | M15: the provincial project management board for the Tien River dyke works | N15: Vietnam | O15: Tien River, Vietnam | Q15: Indonesia | R15: 46319 | S15: 2026-Q4 | T15: landslide, embankment | U15: 7 | V15: https://news.google.com/rss/articles/CBMiwgFBVV95cUxQMlJUSUZORHF4STQta0JTUE5jbGhUeEU2WjdzTTNtSTZZZEprbEpLX3lzS3ZEMTd4YWZhekVGaUJsVnJWUml5M3lMTjlNS0Z4UjgyMUUxZlpWMlB1R1FCWGt3MEczZDZ0Y2YwOVRhd01GUk9ORlJZZklUR1I0SnhwbmM3eGdod182eEdWZHM2dkQ2V1hLVTlwaTl1eVJ1dE4ycVlxd0pYWUlab2M4VnBVcG5EU0dRZVBZbmc3UHVkMHRrdw?oc=5 | W15: =IF($B15="",0,IF(AND(OR(OR(Dashboard!$B$5="All themes",Dashboard!$B$5=""),$C15=Dashboard!$B$5),OR(OR(Dashboard!$G$5="All uses",Dashboard!$G$5=""),$E15=Dashboard!$G$5),N($D15)>=Lists!$H$2,OR(OR(Dashboard!$N$5="All windows",Dashboard!$N$5=""),$S15=Dashboard!$N$5)),1,0)) | X15: =IF($W15=1,N($D15)*1E14+MIN(MAX(N($U15),0),9999)*1E10+MIN(N($K15),99999)*1E5+99999-MIN(ROW(),99999),"")
A16: 13 | B16: No signs of further slope movement at Paya Terubong landslide site, says MBPP | C16: Hazards & Resilience | D16: 4 | E16: Feature lead | F16: To review | I16: How should a landslide site be judged stable again after movement stops, and what monitoring period is needed before reoccupation? | J16: The Star | K16: 46321 | M16: Penang Municipal Council (MBPP) | N16: Malaysia | O16: Paya Terubong, Penang | P16: Paya Terubong landslide, Penang, Malaysia (Oct 2026) · Response & recovery · 7 reports | Q16: United Kingdom | R16: 46321 | S16: 2026-Q4 | T16: landslide, slope | U16: 6 | V16: https://news.google.com/rss/articles/CBMixAFBVV95cUxPYTBqYjFndGYzaFJ2VUxqdjg5SW5FNXZZczhJcmVKSDBHd3pQWThlXzRJc25mQVQzR0ZMdlg0eENhY1NkX3VTZjZJeGxhblFaRVhQWUd3UnEzTEFXVW5OZWM4QVVtR1k3UEk5bjVkUlNfcW1UTThGbTNBSEFCcEZ3S2Y1eG95dndkeHBlUF9TXzd3U1FSTlhreU1ZZGFtOWNUY1lLWnp5OE5wcUp0cGQ0TTdNWUJaOU1WNnU0cWJnMlBTUzVC?oc=5 | W16: =IF($B16="",0,IF(AND(OR(OR(Dashboard!$B$5="All themes",Dashboard!$B$5=""),$C16=Dashboard!$B$5),OR(OR(Dashboard!$G$5="All uses",Dashboard!$G$5=""),$E16=Dashboard!$G$5),N($D16)>=Lists!$H$2,OR(OR(Dashboard!$N$5="All windows",Dashboard!$N$5=""),$S16=Dashboard!$N$5)),1,0)) | X16: =IF($W16=1,N($D16)*1E14+MIN(MAX(N($U16),0),9999)*1E10+MIN(N($K16),99999)*1E5+99999-MIN(ROW(),99999),"")
A17: 14 | B17: State Govt urged to act on slope safety after landslide kills 73-year-old doctor | C17: Hazards & Resilience | D17: 4 | E17: Feature lead | F17: To review | I17: What would a credible state-wide slope inventory and maintenance regime look like for hill-slope housing in tropical, rain-driven terrain? | J17: The Vibes | K17: 46321 | M17: Penang state government and its slope safety authority | N17: Malaysia | O17: Penang | P17: Paya Terubong landslide, Penang, Malaysia (Oct 2026) · Legal & policy · 7 reports | Q17: Australia | R17: 46320 | S17: 2026-Q4 | T17: landslide, slope | U17: 6 | V17: https://news.google.com/rss/articles/CBMi0gFBVV95cUxQa2swTlk5dXpVVXAyeTNwM3ZqaExYMnhyTVdFOHA2bFhnaGpsYlAyYVlKdWxndHFvNEdrOEF1cFpSaE1wbm42MHd1UUVVNkdwclBzai1hTnNGV1JsdEttRms5SjdhUWtaZ2Z2REtHb09WUUZWZWFuZ2UyRTFzLWk3YjFFRnlXRGFuaGhGenBMekotdU1UM3NWcW5vYWtvRk9fUUw1cXl0alU1S09FZWhfUjRNV3dTZ3cwMlFOYzlYRnpQcXpseWkxQXo2NmJ0ejBJR3c?oc=5 | W17: =IF($B17="",0,IF(AND(OR(OR(Dashboard!$B$5="All themes",Dashboard!$B$5=""),$C17=Dashboard!$B$5),OR(OR(Dashboard!$G$5="All uses",Dashboard!$G$5=""),$E17=Dashboard!$G$5),N($D17)>=Lists!$H$2,OR(OR(Dashboard!$N$5="All windows",Dashboard!$N$5=""),$S17=Dashboard!$N$5)),1,0)) | X17: =IF($W17=1,N($D17)*1E14+MIN(MAX(N($U17),0),9999)*1E10+MIN(N($K17),99999)*1E5+99999-MIN(ROW(),99999),"")
A18: 15 | B18: Four Tourists Injured After Poolside Patio Collapses Into Sinkhole At Cozumel Resort | C18: Infrastructure & the Underground City | D18: 4 | E18: Feature lead | F18: To review | I18: How can shallow cavities in karst limestone be detected under resort paving and foundations before a patio collapses into a sinkhole? | J18: Cancun Sun | K18: 46321 | M18: Quintana Roo state civil protection and the resort's engineering consultant | N18: Mexico | O18: Cozumel, Quintana Roo | P18: Occidental Cozumel hotel sinkhole, Mexico (Oct 2026) · Event · 3 reports | Q18: United Kingdom | R18: 46320 | S18: 2026-Q4 | T18: sinkhole, collapse | U18: 5 | V18: https://news.google.com/rss/articles/CBMirwFBVV95cUxOVGZ5TmMxZlZmTTc2cjhZVXVvUlhHbnQ2VFhzbjFUck9PNkVDY01Lc2dYN3lLZVlXcUVkV0hhTmtOSkl4bnlVblNVZ0dlM1h0dVpia1RIcDV6YU5rRW5icDB2Z2RFRGZucFFRZ2J2UUpWSlB4dEFOTEwtaUtyQXhqQkNZeVNGZmtJV3JORy1VN3ZvV1JzSkdXbk9kNVkzb3FLRkVRdEtOdkYxVThCNmtZ?oc=5 | W18: =IF($B18="",0,IF(AND(OR(OR(Dashboard!$B$5="All themes",Dashboard!$B$5=""),$C18=Dashboard!$B$5),OR(OR(Dashboard!$G$5="All uses",Dashboard!$G$5=""),$E18=Dashboard!$G$5),N($D18)>=Lists!$H$2,OR(OR(Dashboard!$N$5="All windows",Dashboard!$N$5=""),$S18=Dashboard!$N$5)),1,0)) | X18: =IF($W18=1,N($D18)*1E14+MIN(MAX(N($U18),0),9999)*1E10+MIN(N($K18),99999)*1E5+99999-MIN(ROW(),99999),"")
A19: 16 | B19: В Пенанге оползень обрушился на дом, погиб 73-летний мужчина — Channel NewsAsia | C19: Hazards & Resilience | D19: 4 | E19: Watch only | F19: To review | I19: What slope failure mechanisms and early warning gaps are behind landslides that reach occupied homes on hillside sites? | J19: UA.NEWS | K19: 46321 | M19: Penang state authorities and Penang Municipal Council (MBPP) | N19: Malaysia | O19: Penang | P19: Paya Terubong landslide, Penang, Malaysia (Oct 2026) · Event · 7 reports | Q19: Russia | R19: 46321 | S19: 2026-Q4 | T19: landslide, collapse | U19: 5 | V19: https://news.google.com/rss/articles/CBMirwFBVV95cUxNdUtXS3JxY2xtSXRmMkdCNVY0V1lYazB4VlM5aDV5TGRxUTFuR2RZYVB5Z282YVJVSzZIQ3d0VHhOaDBRVU9WZUY0M2VQWEFRb2lfWmNLcEZRZ2U3RTNVOVVDM0NnWVVxc2NEdEpYRll1TDk5d3FkWXltZXVGa0N6Q1N4bEFVelBqY3BGb0xPSzRNMUJGdVRaR1g0bGJyS0paUElYZjBnanFQeTI2aVZN?oc=5 | W19: =IF($B19="",0,IF(AND(OR(OR(Dashboard!$B$5="All themes",Dashboard!$B$5=""),$C19=Dashboard!$B$5),OR(OR(Dashboard!$G$5="All uses",Dashboard!$G$5=""),$E19=Dashboard!$G$5),N($D19)>=Lists!$H$2,OR(OR(Dashboard!$N$5="All windows",Dashboard!$N$5=""),$S19=Dashboard!$N$5)),1,0)) | X19: =IF($W19=1,N($D19)*1E14+MIN(MAX(N($U19),0),9999)*1E10+MIN(N($K19),99999)*1E5+99999-MIN(ROW(),99999),"")
A20: 17 | B20: Fuerte oleaje provoca un socavón y daños en un malecón emblemático de México | C20: Offshore, Coasts & Water | D20: 4 | E20: Feature lead | F20: To review | I20: How do storm waves undermine the backfill behind a seafront promenade wall to create sinkholes, and what coastal protection and geotechnical checks should follow such damage? | J20: TV Azteca Jalisco | K20: 46321 | M20: Mazatlán municipal government and Sinaloa civil protection | N20: Mexico | O20: Mazatlán malecón, Sinaloa | P20: Mazatlán malecón wave sinkhole, Mexico (Oct 2026) · Event · 3 reports | Q20: Colombia | R20: 46319 | S20: 2026-Q4 | T20: sinkhole | U20: 4 | V20: https://news.google.com/rss/articles/CBMiywFBVV95cUxPTmRGcEVybWVjSzRpZ1pvMmZqdzBKQnJQVXR5YUpwNmVzclVUaGdnZVVhUXJlcHBVaGFSR1R0TXhKc3BTSXJuS1Ryc2FabjN1UlQyalJ2XzU3cTd4aTUxS0VOVkNfRnlIZXJFMld6UFNwVlVWVUwzWlRfX2trZk51aDNaUGpLeE9Td0xWYVJURTBFaVZlcm05bGxFWjNQZzJtekJNZFhrNmlfZEIxQmtzQjhndTlHclkxNldIbjBMMHhFMmlSOTNSbmlNdw?oc=5 | W20: =IF($B20="",0,IF(AND(OR(OR(Dashboard!$B$5="All themes",Dashboard!$B$5=""),$C20=Dashboard!$B$5),OR(OR(Dashboard!$G$5="All uses",Dashboard!$G$5=""),$E20=Dashboard!$G$5),N($D20)>=Lists!$H$2,OR(OR(Dashboard!$N$5="All windows",Dashboard!$N$5=""),$S20=Dashboard!$N$5)),1,0)) | X20: =IF($W20=1,N($D20)*1E14+MIN(MAX(N($U20),0),9999)*1E10+MIN(N($K20),99999)*1E5+99999-MIN(ROW(),99999),"")
A21: 18 | B21: Inician reparación de socavón provocado por fuerte oleaje junto al Monumento a la Mujer Mazatleca | C21: Offshore, Coasts & Water | D21: 4 | E21: Regional insight | F21: To review | I21: What repair approach suits a wave-undermined seafront structure, and how should designers balance scour protection, backfill compaction and monument stability at the shoreline? | J21: Los Noticieristas | K21: 46321 | M21: Mazatlán municipal government | N21: Mexico | O21: Monumento a la Mujer Mazatleca, Mazatlán | P21: Mazatlán malecón wave sinkhole, Mexico (Oct 2026) · Repair & reconstruction · 3 reports | Q21: Colombia | R21: 46318 | S21: 2026-Q4 | T21: sinkhole | U21: 4 | V21: https://news.google.com/rss/articles/CBMi5gFBVV95cUxPSnh3ZEx6N0ZTcnlzekRyS05rY2djbEVfZGs3cmttMkwxTU56V3pIbjNsanNsQ2FBdGtoMjZPdlRUcjNVZ2FyUVVrWUFsWGctMGVYQzYwTlBkQ0t0dm9UOEdkRkVSeTlkazBkUVdpNnVlbHRVU3hYNkZqdWRMVENoNWx0YXdybnRhWUttam5kX2FRUlJxMlRPS0ZIc09WUnRhSzNseDdSaWJLSEhrYWUtLWczUkNKZXJGQ2xOVE50OHBWVkZpZWZTdHE5QUVQQmpTcnY1OXVEVms4NXhpRjR5aEhRWDdpZw?oc=5 | W21: =IF($B21="",0,IF(AND(OR(OR(Dashboard!$B$5="All themes",Dashboard!$B$5=""),$C21=Dashboard!$B$5),OR(OR(Dashboard!$G$5="All uses",Dashboard!$G$5=""),$E21=Dashboard!$G$5),N($D21)>=Lists!$H$2,OR(OR(Dashboard!$N$5="All windows",Dashboard!$N$5=""),$S21=Dashboard!$N$5)),1,0)) | X21: =IF($W21=1,N($D21)*1E14+MIN(MAX(N($U21),0),9999)*1E10+MIN(N($K21),99999)*1E5+99999-MIN(ROW(),99999),"")
A22: 19 | B22: Ayuntamiento atiende más de 50 socavones su reparación cuesta hasta 700 mil pesos por punto | C22: Infrastructure & the Underground City | D22: 4 | E22: Feature lead | F22: To review | I22: Why do dozens of urban sinkholes appear in one city, and what are the economics and engineering options for locating leaking buried pipes and rehabilitating ground before repairs become recurrent? | J22: Pulso Diario San Luis | K22: 46321 | M22: San Luis Potosí municipal government | N22: Mexico | O22: San Luis Potosí city | Q22: Colombia | R22: 46320 | S22: 2026-Q4 | T22: sinkhole | U22: 4 | V22: https://news.google.com/rss/articles/CBMipAFBVV95cUxNUnM2My1keW1jZUFFWldaOGdueXdRemVGa21mVnNQU0w2bzRaalVPSWJVVGtCZms2OGkwcnlYTGR3ZzdaWG5UMjVOaXZhN2FSOVNzSVJKbHFBTU4wTEFSOTE5WVctQUhKdTR5bm1FQTQ3NDBJX2RsRWN5d2REVG9wOFJja0FOWUNGS0tvSjJFLUhwQ1BYR2dfMUQ3dzZMTWREVDZ5etIBqgFBVV95cUxOS2xrRXVVVlhvZUZLZkFpS1lWUTBsOVZHNHpyaUFiU2h6aE9Kdk1xeHUtR1ZRS3M0OFdQYzlWVzJwbjV5QTNydXNxT2xDMERONXBqQnVMZEZpSnVXdkFDcTU3ZVVOdXdKeEJVckFFRDlIT2hDaWdLdnZ0M19nNWdVZzhta3V2Mkt6bmt2RG9jRkwyaGVaMmYwZVVNTzNSR0VVNzZ3RGZ0ckl1UQ?oc=5 | W22: =IF($B22="",0,IF(AND(OR(OR(Dashboard!$B$5="All themes",Dashboard!$B$5=""),$C22=Dashboard!$B$5),OR(OR(Dashboard!$G$5="All uses",Dashboard!$G$5=""),$E22=Dashboard!$G$5),N($D22)>=Lists!$H$2,OR(OR(Dashboard!$N$5="All windows",Dashboard!$N$5=""),$S22=Dashboard!$N$5)),1,0)) | X22: =IF($W22=1,N($D22)*1E14+MIN(MAX(N($U22),0),9999)*1E10+MIN(N($K22),99999)*1E5+99999-MIN(ROW(),99999),"")
A23: 20 | B23: Ica: nuevo huaico podría repetir el bloqueo de la Panamericana Sur por falta de puente en Ocucaje | C23: Infrastructure & the Underground City | D23: 4 | E23: Feature lead | F23: To review | I23: How do debris flows crossing desert valleys threaten highway embankments and crossings, and what design choices should guide replacement of a missing bridge on this corridor? | J23: Diario Correo | K23: 46321 | M23: Provías Nacional (MTC) | N23: Peru | O23: Ocucaje, Ica | Q23: Peru | R23: 46320 | S23: 2026-Q4 | T23: debris flow | U23: 4 | V23: https://news.google.com/rss/articles/CBMi5AFBVV95cUxOb3NDdUN3Y3VHbl9BSE5xZUcwQkduTVRNdFQ0dlM1eUN3V0VyRzNYWDQxa0xaZjNUdkZjTmd4dHVBaTRCOXRCNUU3VTdTSnhGcms0X0dTMkZnMndqOEpWdFVDbXpUZWxGc2tJb0NkQ2JNMWV1dnBxR3BWYm5Ga1pRSGxMUDFuTkp1aEFyM1ozSHRkOVFFNkdGajNOZVJTSlp3OTBCT3d0NTFPMWJyemhtaGc4RmMzYWs3MWNvcHpIVHdsOXRuZF9HWnAyUGVLWGRkUW5jV2pPbVVnMzJ0bVRGY3ZDRljSAfgBQVVfeXFMUGk0TVN2aUMxUUhXYnN2SklCSmRvcm41R0pVSUNUV2s5Tkg4b1FEeldzbk13QVZsX3RjcFFobDlld1VrYzF6MnNJWVV6Y292WDhOSGZuMUdfV2E5OTdMamYwcWJTY0pHb2I4VzdsTWw1anBEWGVJanF1ejBpVHZVQnlBYzZOanhQb1lkTzVNYXJHbGttLVNNcG5oZnpzTFA2U2ZZYkNjNnl4MGxGMi11ZEZRUVNwZUpkTV9raVFVZGFHMWY2amVXd1VXRHB3Q0NIR1BCNmhBYmZ6X1VyVXBuNlhhQUFIR0NLd2dMNU11REotX0o3UWlPTlc?oc=5 | W23: =IF($B23="",0,IF(AND(OR(OR(Dashboard!$B$5="All themes",Dashboard!$B$5=""),$C23=Dashboard!$B$5),OR(OR(Dashboard!$G$5="All uses",Dashboard!$G$5=""),$E23=Dashboard!$G$5),N($D23)>=Lists!$H$2,OR(OR(Dashboard!$N$5="All windows",Dashboard!$N$5=""),$S23=Dashboard!$N$5)),1,0)) | X23: =IF($W23=1,N($D23)*1E14+MIN(MAX(N($U23),0),9999)*1E10+MIN(N($K23),99999)*1E5+99999-MIN(ROW(),99999),"")
A24: 21 | B24: Panamá interviene antigua mina de oro tras deslizamiento que amenaza fuentes de agua | C24: Hazards & Resilience | D24: 4 | E24: Feature lead | F24: To review | I24: How should slope and waste-material stability in an abandoned mine be assessed where failure threatens downstream water supplies? | J24: Infobae | K24: 46321 | M24: Panama's environment ministry (MiAmbiente) | N24: Panama | O24: former gold mine, Panama | Q24: Spain | R24: 46320 | S24: 2026-Q4 | T24: landslide | U24: 4 | V24: https://news.google.com/rss/articles/CBMixgFBVV95cUxQaVhsb1NSUXVneU1mZ0s1bXFVUHlEWjJrd0ZFa3FCeW1rYjVLeXBWcGxWSUJyM0VBaS00ZU9naFM4RGxYa1N0MUtGRlJMMExzZEJ2MXRoWnZnd3FCWHFwbFFna0xwUmhST3dab0NGNllRZGxyN1lENkJxVnhpa2RUcEdLWndtZmRySGw4RjlmU25ocmQ0aWJkQ1RUU0ZWSjlhZE9KYmpyUWhkOXdEbU9pc2RZc1dIVWxMQUloOGZCb3dWWDAxZnfSAeABQVVfeXFMUHV0bkZyU0hXY0RQTDdYd3g5M1d4QkxUYklYQlgxOFlGVjQyUTJwVVFVQTE3QUh6NzUtbVpfSkhjVW5kQlA5RW9nemlfNDBWQzJCRE9FY2xfZ19velh4a29NdkNlaEJJdGIwOGV3bW1zY1VCenhhd1VRRncybE9UM1YzU1ZrSzdWY0JTM1hVZVRmTDEySFFWWloxUEptSDV3MTVuOUdHTmFGZF9pRzBfM3E5YTNHSVkwNnRCc1NqMUU4LXl2SWlwMjByRWowN2FIc2lIb3ROWmVNZDRBeXpkY0g?oc=5 | W24: =IF($B24="",0,IF(AND(OR(OR(Dashboard!$B$5="All themes",Dashboard!$B$5=""),$C24=Dashboard!$B$5),OR(OR(Dashboard!$G$5="All uses",Dashboard!$G$5=""),$E24=Dashboard!$G$5),N($D24)>=Lists!$H$2,OR(OR(Dashboard!$N$5="All windows",Dashboard!$N$5=""),$S24=Dashboard!$N$5)),1,0)) | X24: =IF($W24=1,N($D24)*1E14+MIN(MAX(N($U24),0),9999)*1E10+MIN(N($K24),99999)*1E5+99999-MIN(ROW(),99999),"")
A25: 22 | B25: Socavón amenaza con dejar incomunicadas a dos barriadas en Arraiján | C25: Hazards & Resilience | D25: 4 | E25: Feature lead | F25: To review | I25: What causes a sinkhole to threaten access roads serving residential areas, and how should geotechnical investigation and emergency stabilisation be prioritised to keep communities connected? | J25: Telemetro | K25: 46321 | M25: Arraiján municipality and Panama's public works ministry (MOP) | N25: Panama | O25: Arraiján, Panamá Oeste | Q25: Colombia | R25: 46320 | S25: 2026-Q4 | T25: sinkhole | U25: 4 | V25: https://news.google.com/rss/articles/CBMipwFBVV95cUxPWHFDTVg5S1Z4YURHWFE5YjMycWRyYWNObmRLUVRMV0NsN2NGLU0zeUx6REd2NktKajNUOTdNZGxqcjNWWmE1NGk4WWUwck1DTUNvY0pOa2xGNDBIcWc1SURyXzFQZHpCbVQwY1JyMVpNRmVMdzgwd1VpQU53cm96cUNoM2pEQmJkQ2VBRVBtV1hpZkpDSE12aGNLYndSckl4V1ZTOG8tQdIBrAFBVV95cUxOMk93aGFZX1RCd045SlQ5d0gwOW9vOG1Sem5IYW9URVY3YTdOUnExWU80QlVnYU5wUDdaN1Y3SXlvS3pLT0FDcGxWbVc3N2ZPUXExVTU5LTZBNk01bFltYUVSTFQxSEZYMG9seXV3UUx2cXAyRUlFcHBLZTF6bmtIXzJHckt5Nld3TUJRbmJJTzBiTUMwQ1RabnhzR09hUUt6OXBoR3R5ZHY2MFl5?oc=5 | W25: =IF($B25="",0,IF(AND(OR(OR(Dashboard!$B$5="All themes",Dashboard!$B$5=""),$C25=Dashboard!$B$5),OR(OR(Dashboard!$G$5="All uses",Dashboard!$G$5=""),$E25=Dashboard!$G$5),N($D25)>=Lists!$H$2,OR(OR(Dashboard!$N$5="All windows",Dashboard!$N$5=""),$S25=Dashboard!$N$5)),1,0)) | X25: =IF($W25=1,N($D25)*1E14+MIN(MAX(N($U25),0),9999)*1E10+MIN(N($K25),99999)*1E5+99999-MIN(ROW(),99999),"")
A26: 23 | B26: Reportan caída de cuatro huéspedes en socavón de hotel Occidental de Cozumel | C26: Hazards & Resilience | D26: 4 | E26: News brief | F26: To review | I26: What subsurface conditions in coastal limestone, such as cenotes and dissolution cavities, lead to sudden ground collapse beneath resort buildings, and how should such sites be surveyed? | J26: Quinta Fuerza | K26: 46321 | M26: Hotel Occidental Cozumel management and Quintana Roo civil protection | N26: Mexico | O26: Cozumel, Quintana Roo | P26: Occidental Cozumel hotel sinkhole, Mexico (Oct 2026) · Event · 3 reports | Q26: Colombia | R26: 46320 | S26: 2026-Q4 | T26: sinkhole | U26: 4 | V26: https://news.google.com/rss/articles/CBMirwFBVV95cUxPVnhmNG5qb2FXNFprTmtzdnowYkYya3RTZ0I5VlZsWVJ3OTdsMWlkZ0hUcWlOQks1YWEycFhLWUlzZmhaREN3VUQ3REhuUklsX3k4M3J3QzFRbl9JaWduTlRqby1Rem4tYzhqUmtxUFVZU1BOQ25NTUxqZ1BOdzJzX3BYaklQaWV3NS1LbkdTY1ZhNGtSbkZrS2FabmpSWEtpY1BSV0t2S0hSZFYxOWVZ?oc=5 | W26: =IF($B26="",0,IF(AND(OR(OR(Dashboard!$B$5="All themes",Dashboard!$B$5=""),$C26=Dashboard!$B$5),OR(OR(Dashboard!$G$5="All uses",Dashboard!$G$5=""),$E26=Dashboard!$G$5),N($D26)>=Lists!$H$2,OR(OR(Dashboard!$N$5="All windows",Dashboard!$N$5=""),$S26=Dashboard!$N$5)),1,0)) | X26: =IF($W26=1,N($D26)*1E14+MIN(MAX(N($U26),0),9999)*1E10+MIN(N($K26),99999)*1E5+99999-MIN(ROW(),99999),"")
A27: 24 | B27: Alertas SMS, señaléticas y rutas de evacuación: el plan de La Reina ante futuros aluviones | C27: Hazards & Resilience | D27: 4 | E27: Feature lead | F27: To review | I27: Beyond warning systems, what ground-based hazard mapping and debris-flow control measures should a municipality in an Andean foothill commune use to plan evacuation and reduce aluvión exposure? | J27: Cooperativa | K27: 46321 | M27: La Reina municipality and Senapred | N27: Chile | O27: La Reina, Santiago | Q27: Chile | R27: 46319 | S27: 2026-Q4 | T27: debris flow | U27: 4 | V27: https://news.google.com/rss/articles/CBMi-wFBVV95cUxObzhjLXYxeEhDM0hkcVE1YVNRNzhhVGMtQmpuYlBnV0d2Ykk4XzR6QjJKdFR6Y3lsUjZrSlNYSW5fTnlFdHVtN21PT1NQZW5jS3FLMk9obEZ5cUxOLWlkcjlYTjA1VGo3aW9yY1VVaEdyUFVnNmhhZS1vNVdXLU1neDBzdlZYZGtGb3FnelhGZXVOUk56ZnRCQ2hqdmc5VWV0bUFxb1AwTHVRYWhQZ2hJamN1QTgzZExkdU5VdE0xWHp4OWJwQl91YkNDSlFwQ1hITm4xVl96Wm0yeVVEcHdCRXkxM3dVNEZDd19GRlNyUUxmZ0JZM0JLZE9YY9IBjAFBVV95cUxOck1uV2p6RDJ3VXVOVkI5ZVFtYzVuYkt1Tk1QVklFcHZCY3lDZVJ0cm1OWDh6VlpiMGlTaW53dElkUkNyRnE4VVlMYmRtSGR3YXItSTJ0RmZnWmt6UmR4anN5amw0emlSUU5NdHJoWVc2aHd3SU9kTVdjNGZQN29PanZLTk1GVndudnVqVA?oc=5 | W27: =IF($B27="",0,IF(AND(OR(OR(Dashboard!$B$5="All themes",Dashboard!$B$5=""),$C27=Dashboard!$B$5),OR(OR(Dashboard!$G$5="All uses",Dashboard!$G$5=""),$E27=Dashboard!$G$5),N($D27)>=Lists!$H$2,OR(OR(Dashboard!$N$5="All windows",Dashboard!$N$5=""),$S27=Dashboard!$N$5)),1,0)) | X27: =IF($W27=1,N($D27)*1E14+MIN(MAX(N($U27),0),9999)*1E10+MIN(N($K27),99999)*1E5+99999-MIN(ROW(),99999),"")
A28: 25 | B28: ANA instala 12 barreras para reducir el impacto de huaicos en Lima y Huarochirí | C28: Hazards & Resilience | D28: 4 | E28: Feature lead | F28: To review | I28: Can check dams and barrier structures in steep Andean gullies meaningfully reduce debris-flow impacts, and how should their design and maintenance be evaluated? | J28: TVPerú | K28: 46321 | M28: Autoridad Nacional del Agua (ANA) | N28: Peru | O28: Lima and Huarochirí | Q28: Peru | R28: 46320 | S28: 2026-Q4 | T28: debris flow | U28: 4 | V28: https://news.google.com/rss/articles/CBMiwwFBVV95cUxNWFA0THhERThMM2RnZS1WTWRDUVZOVUxEN254WUFHdEs5a0dfZGtINWtuOHAxM1I3TXRPak1xRDd0ZnZybEVWbF9BVnFaQVltSThXb3NHelk1ZVozMTAwcXJVMXF5cGZEREpPN2c3Z2gwNHNxSHVhZmlLNzluWGk1bERUTGlGVlJGejRLZVVIRDhfZ3VvSm9HaU41U1RZYkFLX2pJUlZoSE0yY0wtQ2FfdzMweXVIb29iWVJFUV9jclpNM3M?oc=5 | W28: =IF($B28="",0,IF(AND(OR(OR(Dashboard!$B$5="All themes",Dashboard!$B$5=""),$C28=Dashboard!$B$5),OR(OR(Dashboard!$G$5="All uses",Dashboard!$G$5=""),$E28=Dashboard!$G$5),N($D28)>=Lists!$H$2,OR(OR(Dashboard!$N$5="All windows",Dashboard!$N$5=""),$S28=Dashboard!$N$5)),1,0)) | X28: =IF($W28=1,N($D28)*1E14+MIN(MAX(N($U28),0),9999)*1E10+MIN(N($K28),99999)*1E5+99999-MIN(ROW(),99999),"")
A29: 26 | B29: Zero cycle: how Setl Group creates 3D excavation models for residential buildings using nanoCAD GeoniCS | C29: Digital Geotechnics | D29: 4 | E29: Feature lead | F29: To review | I29: How reliable are 3D excavation models built from site investigation data for deep pits in dense urban sites, and how should their accuracy be verified before construction? | J29: ComNews.ru | K29: 46321 | L29: Нулевой цикл: как в Setl Group создают 3D модели котлованов жилых зданий при помощи nanoCAD GeoniCS | M29: Setl Group (developer) and the nanoCAD GeoniCS software vendor | N29: Russia | Q29: Russia | R29: 46320 | S29: 2026-Q4 | T29: excavation | U29: 2 | V29: https://news.google.com/rss/articles/CBMi9wFBVV95cUxNb2RuOGhRdXFVMFdkZGFBRy0tQVZUWlMtODhEZzJpMzJicUFacnBWTXpkeEZ5YTdTMmxmbFNoUDRaWFdKVmdJZFJtbnJtc2p1ejBxbWR6OUs0ZkNSMlJhX0g4NEplZHdndFFITWVjeEF5bnNpZkNlTlBPWEFRN1FRNktCZXcyU1Fha1l4dXc3VHo0TVBsU3l0R2hob0NNYWtIeVM5YUNhVTNHWnAzUHozc0dsNmxLZUgtYzhpR2VubDdJMnF0aHNwdi0zd3JpXzI1Wk5hbDdyNnVmUERYQkFYSUV4UWRnR01GZXFIRVNENzZYTWpJSkFv?oc=5 | W29: =IF($B29="",0,IF(AND(OR(OR(Dashboard!$B$5="All themes",Dashboard!$B$5=""),$C29=Dashboard!$B$5),OR(OR(Dashboard!$G$5="All uses",Dashboard!$G$5=""),$E29=Dashboard!$G$5),N($D29)>=Lists!$H$2,OR(OR(Dashboard!$N$5="All windows",Dashboard!$N$5=""),$S29=Dashboard!$N$5)),1,0)) | X29: =IF($W29=1,N($D29)*1E14+MIN(MAX(N($U29),0),9999)*1E10+MIN(N($K29),99999)*1E5+99999-MIN(ROW(),99999),"")
A30: 27 | B30: Anuncia Ayuntamiento de Cuernavaca cierre temporal de Avenida Universidad por revisión de hundimiento | C30: Infrastructure & the Underground City | D30: 4 | E30: News brief | F30: To review | I30: What ground or utility causes are behind the subsidence on Avenida Universidad, and what investigation should determine whether the road can safely reopen? | J30: La Jornada Morelos | K30: 46321 | M30: the Cuernavaca city council | N30: Mexico | O30: Avenida Universidad, Cuernavaca | Q30: Argentina | R30: 46319 | S30: 2026-Q4 | U30: 0 | V30: https://news.google.com/rss/articles/CBMi2wFBVV95cUxPMTNJeGdhN2Y2Q0lMTlZlU2UzUHNVTW9udUMwWEZXZEJiYThReDRFODE5NmRlZE1vTXFfOU5zV1FwcFVYVV9pRGFmT29SWDZ0Ulk0R0ZEbWZDdlB5RTBuSXRHSndyMDA3QlliNmNRajRoUjBscGdWVFRRVFdNRFdvTVBvSUZlMjVYSWV4NkhnTFkyeG5wRmdZVmgweGV6LUp3X045OVJsZ3F2ajRRa2ZUeWFMdEFGX0szZlBnel9ZUkNrdkRYcWRzbUZUZ0t4WTZBTUVnLWpBRjVrcG8?oc=5 | W30: =IF($B30="",0,IF(AND(OR(OR(Dashboard!$B$5="All themes",Dashboard!$B$5=""),$C30=Dashboard!$B$5),OR(OR(Dashboard!$G$5="All uses",Dashboard!$G$5=""),$E30=Dashboard!$G$5),N($D30)>=Lists!$H$2,OR(OR(Dashboard!$N$5="All windows",Dashboard!$N$5=""),$S30=Dashboard!$N$5)),1,0)) | X30: =IF($W30=1,N($D30)*1E14+MIN(MAX(N($U30),0),9999)*1E10+MIN(N($K30),99999)*1E5+99999-MIN(ROW(),99999),"")
A31: 28 | B31: India's first bullet train: station to be built 100 feet underground, high-speed train to pass beneath the sea | C31: Infrastructure & the Underground City | D31: 4 | E31: Feature lead | F31: To review | I31: What ground conditions and deep excavation methods are needed for a 30 m deep station and an undersea tunnel on India's first bullet train route? | J31: Inh News | K31: 46321 | L31: भारत की पहली बुलेट ट्रेन: 100 फीट नीचे बनेगा स्टेशन, समुद्र के नीचे से गुजरेगी हाई-स्पीड ट्रेन | M31: NHSRCL (National High Speed Rail Corporation) | N31: India | O31: Mumbai–Ahmedabad bullet train corridor | Q31: India | R31: 46320 | S31: 2026-Q4 | U31: 0 | V31: https://news.google.com/rss/articles/CBMijwFBVV95cUxOZGhPdS0zY1BmbHVzOUNQZWR0dkZCZ1VuRVh3NV9mbF8wdGY5aVEwTjhNdkIzdTlnM2cyWmZCUDdIdzVab1hFd3ZNZjdsUWlVc0I1Z2xyVHhEbHFGRUtNTWp2dVZIREx6aG5ZaHlXQ3hwdC1lb29YYllJbzNxZ29LX1ppUFN6a2w2WHdZaTlkY9IBlAFBVV95cUxNakMwc3pUZG5mUlZjWVZPa1VyNG5UN3U2NTkzRGRENXZpNUJSZThYZ1lJNGVjUnZvLU90Zm5rdVpEa2tLMmtVUlB1bUhSSjhtalpjZlhXQ0phYnFCdWRLOFo3cmJtZWtKVDRETlhYSWVaRzBRTEZiNHhvNUxVZDUwTGo0MlNvVVlLeW5oY3R6aVF6bldL?oc=5 | W31: =IF($B31="",0,IF(AND(OR(OR(Dashboard!$B$5="All themes",Dashboard!$B$5=""),$C31=Dashboard!$B$5),OR(OR(Dashboard!$G$5="All uses",Dashboard!$G$5=""),$E31=Dashboard!$G$5),N($D31)>=Lists!$H$2,OR(OR(Dashboard!$N$5="All windows",Dashboard!$N$5=""),$S31=Dashboard!$N$5)),1,0)) | X31: =IF($W31=1,N($D31)*1E14+MIN(MAX(N($U31),0),9999)*1E10+MIN(N($K31),99999)*1E5+99999-MIN(ROW(),99999),"")
A32: 29 | B32: Disaster R&D to prevent sinkhole and ageing elevated structure collapses using veteran field technology. | C32: Infrastructure & the Underground City | D32: 3 | E32: Academia-to-Industry topic | F32: To review | I32: Which field-proven ground investigation techniques could detect cavities and deteriorating foundations before sinkholes or elevated structure collapses occur? | J32: 한국일보 | K32: 46321 | L32: 싱크홀·노후 고가 붕괴 사고 막는다... 현장 베테랑 기술력 접목해 재난재해 해결 R&D | M32: the government ministry funding the disaster R&D programme | N32: South Korea | Q32: South Korea | R32: 46321 | S32: 2026-Q4 | T32: sinkhole, collapse | U32: 5 | V32: https://news.google.com/rss/articles/CBMibkFVX3lxTE5lR29sc1VXZDNMZjlCTmhhNUxXVW95WURmdk9VVVV5WC1xazJDUnl0dzEyRGI4cURWUTVJWnNrZzg4NEQ5NGcyLUMyeHNreU5MdlIybTNjTzRYaHR5SDlaNzdESzVLeXBWeTMwNU9R0gFzQVVfeXFMTkZ6a1ZKdVo4Zkx2Z1kxR2ZpODdUQ0xvWXBUbWZFa0FZMVA5UF8zSUFQM0VKRDE1emx2dWR4TElPNXd5ekhCY3hzdWhnc1l6YWh3cUFZTTA4bklaN2ZPWW1HdXVHZmthS05XUExZdzhNdVR5UQ?oc=5 | W32: =IF($B32="",0,IF(AND(OR(OR(Dashboard!$B$5="All themes",Dashboard!$B$5=""),$C32=Dashboard!$B$5),OR(OR(Dashboard!$G$5="All uses",Dashboard!$G$5=""),$E32=Dashboard!$G$5),N($D32)>=Lists!$H$2,OR(OR(Dashboard!$N$5="All windows",Dashboard!$N$5=""),$S32=Dashboard!$N$5)),1,0)) | X32: =IF($W32=1,N($D32)*1E14+MIN(MAX(N($U32),0),9999)*1E10+MIN(N($K32),99999)*1E5+99999-MIN(ROW(),99999),"")
A33: 30 | B33: Concentrer les ressources sur le relogement des personnes vivant dans les zones à risque de glissements de terrain. | C33: Geotechnics & Society | D33: 3 | E33: Feature lead | F33: To review | I33: How should relocation programmes for households in landslide-prone zones be prioritised using ground hazard evidence? | J33: Vietnam.vn | K33: 46321 | M33: Vietnam's ministry responsible for disaster prevention | N33: Vietnam | Q33: France | R33: 46321 | S33: 2026-Q4 | T33: landslide | U33: 4 | V33: https://news.google.com/rss/articles/CBMilAFBVV95cUxNSHZ2QXBIZEZ6bnJfNURvNG8xZ01rMkdnY3UwSGY4cjB4ZXpCcmRBSVZtQUprTExRNVlmdnE4Q0pPcllIZmlhYjN1WV9qejJVYzhIWC10QTFzcjdQc0gwbDJsamIzMVdxZVBiWjhLVDY5X0tOZEFqQnBITF84M2hyNkZmUmY4czZIMDIzRjgyaVBVQXBJ?oc=5 | W33: =IF($B33="",0,IF(AND(OR(OR(Dashboard!$B$5="All themes",Dashboard!$B$5=""),$C33=Dashboard!$B$5),OR(OR(Dashboard!$G$5="All uses",Dashboard!$G$5=""),$E33=Dashboard!$G$5),N($D33)>=Lists!$H$2,OR(OR(Dashboard!$N$5="All windows",Dashboard!$N$5=""),$S33=Dashboard!$N$5)),1,0)) | X33: =IF($W33=1,N($D33)*1E14+MIN(MAX(N($U33),0),9999)*1E10+MIN(N($K33),99999)*1E5+99999-MIN(ROW(),99999),"")
A34: 31 | B34: Using AI to detect landslide risks early. | C34: Digital Geotechnics | D34: 3 | E34: Academia-to-Industry topic | F34: To review | I34: Can machine learning on rainfall and monitoring data reliably predict landslide initiation, and what validation would engineers need? | J34: Vietnam.vn | K34: 46321 | L34: Utiliser l'IA pour détecter précocement les risques de glissements de terrain. | N34: Vietnam | P34: AI landslide early warning, Vietnam · Update · 3 reports | Q34: France | R34: 46319 | S34: 2026-Q4 | T34: landslide | U34: 4 | V34: https://news.google.com/rss/articles/CBMibkFVX3lxTE9QQVZhX29ySmV5Wk9oVElzYXZVaUdkc3NkcERtSm5RZEVEZDNWN0pFUml2aC03WFNHRWJRRUk4YXY3bExHLU5iajZoV1V3Tm1xVVRBVmRWZklRN0thMDNfUUJTaFZLZ2NXWXRwRE9R?oc=5 | W34: =IF($B34="",0,IF(AND(OR(OR(Dashboard!$B$5="All themes",Dashboard!$B$5=""),$C34=Dashboard!$B$5),OR(OR(Dashboard!$G$5="All uses",Dashboard!$G$5=""),$E34=Dashboard!$G$5),N($D34)>=Lists!$H$2,OR(OR(Dashboard!$N$5="All windows",Dashboard!$N$5=""),$S34=Dashboard!$N$5)),1,0)) | X34: =IF($W34=1,N($D34)*1E14+MIN(MAX(N($U34),0),9999)*1E10+MIN(N($K34),99999)*1E5+99999-MIN(ROW(),99999),"")
A35: 32 | B35: Using artificial intelligence to provide early warnings of landslide risk. | C35: Digital Geotechnics | D35: 3 | E35: Watch only | F35: To review | I35: Can machine learning on rainfall and monitoring data reliably predict landslide initiation, and what validation would engineers need? | J35: Vietnam.vn | K35: 46321 | L35: Utilizar la inteligencia artificial para proporcionar alertas tempranas sobre riesgos de deslizamientos de tierra. | N35: Vietnam | P35: AI landslide early warning, Vietnam · Update · 3 reports | Q35: Spain | R35: 46319 | S35: 2026-Q4 | T35: landslide | U35: 4 | V35: https://news.google.com/rss/articles/CBMibkFVX3lxTE1WQ0c3RjRvbm50dlNYYi1UcTNoTDRQbllDZzJ0X0d5NVVkbHdMdmNNeGNxZmJPelQ0T1V0Y291aVF0Tmt2bDFEbDZyeWgtZXEwZ1NRQ0oxVF9pN0tTbnZYWVhDdFVBbE9obFRhSHNn?oc=5 | W35: =IF($B35="",0,IF(AND(OR(OR(Dashboard!$B$5="All themes",Dashboard!$B$5=""),$C35=Dashboard!$B$5),OR(OR(Dashboard!$G$5="All uses",Dashboard!$G$5=""),$E35=Dashboard!$G$5),N($D35)>=Lists!$H$2,OR(OR(Dashboard!$N$5="All windows",Dashboard!$N$5=""),$S35=Dashboard!$N$5)),1,0)) | X35: =IF($W35=1,N($D35)*1E14+MIN(MAX(N($U35),0),9999)*1E10+MIN(N($K35),99999)*1E5+99999-MIN(ROW(),99999),"")
A36: 33 | B36: Earthworks begin on second section of damaged collector in Voronezh | C36: Infrastructure & the Underground City | D36: 3 | E36: News brief | F36: To review | I36: What ground conditions and excavation support measures govern safe repair of a buried collector in soft urban soils? | J36: Новости Воронежа интернет-газета | K36: 46321 | L36: В Воронеже начали земляные работы на втором участке поврежденного коллектора | M36: Voronezh city water utility (Voronezhvodokanal) | N36: Russia | O36: Voronezh | P36: Voronezh Moskovsky Avenue collector repair, Russia · Repair & reconstruction · 2 reports | Q36: Russia | R36: 46320 | S36: 2026-Q4 | T36: earthworks | U36: 4 | V36: https://news.google.com/rss/articles/CBMiWEFVX3lxTE40bjhiX3RGaTgxc0h6UU1ENDdRSGFlNkRMOTdvakVpalctY3B2bW4wYjNNcno2UHNrNVItVmJGZHB4aTdOX1ljNjNJUnJVbk5DV1ltRl8tN3o?oc=5 | W36: =IF($B36="",0,IF(AND(OR(OR(Dashboard!$B$5="All themes",Dashboard!$B$5=""),$C36=Dashboard!$B$5),OR(OR(Dashboard!$G$5="All uses",Dashboard!$G$5=""),$E36=Dashboard!$G$5),N($D36)>=Lists!$H$2,OR(OR(Dashboard!$N$5="All windows",Dashboard!$N$5=""),$S36=Dashboard!$N$5)),1,0)) | X36: =IF($W36=1,N($D36)*1E14+MIN(MAX(N($U36),0),9999)*1E10+MIN(N($K36),99999)*1E5+99999-MIN(ROW(),99999),"")
A37: 34 | B37: Vía Alóag-Santo Domingo tiene paso controlado tras deslizamiento en el km 35 | C37: Infrastructure & the Underground City | D37: 3 | E37: News brief | F37: To review | I37: What slope monitoring and remediation are needed on a major highway section where slides repeatedly force controlled traffic? | J37: El Comercio | K37: 46321 | M37: Ecuador's transport ministry (MTOP) | N37: Ecuador | O37: Alóag-Santo Domingo road, km 35 | Q37: Spain | R37: 46321 | S37: 2026-Q4 | T37: landslide | U37: 4 | V37: https://news.google.com/rss/articles/CBMisAFBVV95cUxNc3VaQmhHTlhIY2tzZWlvdlE2ZjhlZjUxSkstajdvbjR1dmh1Y0VKRUZMQlc1M015SlVGSkpmWERfakdzVk1sbjlUc201TVdoMWhxbGM1WmxPZXotRXk5WWpraEJKRUM0a3hlN1hxNnVfcVRYU0tZMFR3RXd0OURHLTBLRGlISmVHUURaZm9TRmlXUzBaRDRDc1BaRnMwSnhlOVM0SEJZckE3T2ZrWGVDZw?oc=5 | W37: =IF($B37="",0,IF(AND(OR(OR(Dashboard!$B$5="All themes",Dashboard!$B$5=""),$C37=Dashboard!$B$5),OR(OR(Dashboard!$G$5="All uses",Dashboard!$G$5=""),$E37=Dashboard!$G$5),N($D37)>=Lists!$H$2,OR(OR(Dashboard!$N$5="All windows",Dashboard!$N$5=""),$S37=Dashboard!$N$5)),1,0)) | X37: =IF($W37=1,N($D37)*1E14+MIN(MAX(N($U37),0),9999)*1E10+MIN(N($K37),99999)*1E5+99999-MIN(ROW(),99999),"")
A38: 35 | B38: Vía Riobamba–Penipe–Baños fue habilitada tras deslizamiento | C38: Infrastructure & the Underground City | D38: 3 | E38: News brief | F38: To review | I38: How should a mountain road reopened after a slide be assessed for residual hazard and re-failure risk? | J38: diariolosandes.com.ec | K38: 46321 | M38: Chimborazo provincial road authority (MTOP) | N38: Ecuador | O38: Riobamba–Penipe–Baños road | Q38: Spain | R38: 46320 | S38: 2026-Q4 | T38: landslide | U38: 4 | V38: https://news.google.com/rss/articles/CBMilAFBVV95cUxPcnRNQzY0bndiRjZuWTR4SzEtdjFNZEtFOGxBVVI0dml6X3NTVE1Fa0xLSTg5X3ZkNUQxQ1lMNjR5cExKcDd3RU51WHFVMGhfNndZZFhLSk5XTjNodVFqYy1Bb2ctXzl6NTV3VDEzSXZ0VnZHWWhnSHNTenRoNEt0TmxtMnZ5bDZnZGJnbXBUbzY0d1pF?oc=5 | W38: =IF($B38="",0,IF(AND(OR(OR(Dashboard!$B$5="All themes",Dashboard!$B$5=""),$C38=Dashboard!$B$5),OR(OR(Dashboard!$G$5="All uses",Dashboard!$G$5=""),$E38=Dashboard!$G$5),N($D38)>=Lists!$H$2,OR(OR(Dashboard!$N$5="All windows",Dashboard!$N$5=""),$S38=Dashboard!$N$5)),1,0)) | X38: =IF($W38=1,N($D38)*1E14+MIN(MAX(N($U38),0),9999)*1E10+MIN(N($K38),99999)*1E5+99999-MIN(ROW(),99999),"")
A39: 36 | B39: Áncash: deslizamiento de tierra dañó 15 metros de vía vecinal en Shupluy - | C39: Infrastructure & the Underground City | D39: 3 | E39: News brief | F39: To review | I39: What drainage and slope protection would keep a rural access road operational during Andean rainy seasons? | J39: luminanoticias.pe | K39: 46321 | M39: Áncash regional government road authority | N39: Peru | O39: Shupluy, Áncash | Q39: Spain | R39: 46320 | S39: 2026-Q4 | T39: landslide | U39: 4 | V39: https://news.google.com/rss/articles/CBMiqwFBVV95cUxQc0lQODA0QjMzSXAwS2psWC1SN2Nld0pVODkxZzhrcEZHQUU0aTkxd1ljM2p5MVdoUnhMaGY4bzBmVlpZQlNtZlUtelJXb0ZFcmV3ZndyNUEtZUJiMzBqRC04ZjZabThfWVdwd0VfLWFBMjQyZnhkRGlRUEY4OGVPbm9MZGRleFNDcU9xYzVmeEpSZmRJb1FtbDk5TFU0dUN5MWJVTl9vd0wyZTQ?oc=5 | W39: =IF($B39="",0,IF(AND(OR(OR(Dashboard!$B$5="All themes",Dashboard!$B$5=""),$C39=Dashboard!$B$5),OR(OR(Dashboard!$G$5="All uses",Dashboard!$G$5=""),$E39=Dashboard!$G$5),N($D39)>=Lists!$H$2,OR(OR(Dashboard!$N$5="All windows",Dashboard!$N$5=""),$S39=Dashboard!$N$5)),1,0)) | X39: =IF($W39=1,N($D39)*1E14+MIN(MAX(N($U39),0),9999)*1E10+MIN(N($K39),99999)*1E5+99999-MIN(ROW(),99999),"")
A40: 37 | B40: Camioneta varada en socavón de la colonia Fronteriza en Juárez | C40: Infrastructure & the Underground City | D40: 3 | E40: News brief | F40: To review | I40: What failure mechanisms allow a road surface to collapse under a vehicle in a neighbourhood with poor drainage, and what subsurface survey would identify such voids before vehicles are trapped? | J40: Netnoticias.mx | K40: 46321 | M40: Ciudad Juárez municipal government | N40: Mexico | O40: Colonia Fronteriza, Ciudad Juárez | Q40: Colombia | R40: 46320 | S40: 2026-Q4 | T40: sinkhole | U40: 4 | V40: https://news.google.com/rss/articles/CBMilAFBVV95cUxPNEV1bllwT1R4cXk3NlhndEdqZm5YWXAxRXl5LThrb0dzbEdqdTJXRVB4VDMxN2NzSGtzSHR1RmxhYUdsTHVHaEJLNmZ5NTNWajhVT2VabHhRMGNCUTZDZVZRZVNmRThEckdaNVdWbEJPM3FYS0NVVDhKTlhTUE9HODdHWFE0SUpCQnE4d3N4Y0E4cldj?oc=5 | W40: =IF($B40="",0,IF(AND(OR(OR(Dashboard!$B$5="All themes",Dashboard!$B$5=""),$C40=Dashboard!$B$5),OR(OR(Dashboard!$G$5="All uses",Dashboard!$G$5=""),$E40=Dashboard!$G$5),N($D40)>=Lists!$H$2,OR(OR(Dashboard!$N$5="All windows",Dashboard!$N$5=""),$S40=Dashboard!$N$5)),1,0)) | X40: =IF($W40=1,N($D40)*1E14+MIN(MAX(N($U40),0),9999)*1E10+MIN(N($K40),99999)*1E5+99999-MIN(ROW(),99999),"")
A41: 38 | B41: Mañana inicia la reparación del socavón en el puente Terrazas del Valle | C41: Infrastructure & the Underground City | D41: 3 | E41: News brief | F41: To review | I41: What causes a sinkhole to form at a bridge abutment or approach, and what foundation and backfill investigation should precede a repair to prevent recurrence? | J41: Punto Norte | K41: 46321 | M41: municipal public works department | N41: Mexico | O41: Terrazas del Valle bridge | P41: Terrazas del Valle bridge sinkhole, Tijuana, Mexico · Repair & reconstruction · 2 reports | Q41: Colombia | R41: 46318 | S41: 2026-Q4 | T41: sinkhole | U41: 4 | V41: https://news.google.com/rss/articles/CBMiqwFBVV95cUxNNk1QTEtuRDhRclJYR2xZaU9jT0J1VkIzbmhhZlZJS3RzaXBXbTdwS2I5WU1LaTdSSFdUbGZVWUpkRm9vRm9yQ2xIem9kbXExVDRkLVVrZ0J4R1dwaXZScWtpNHJhaU5oTW5iQkFyRmhkd2pmYXdMUHhIUWYwM05YNnRWdS1DZUhlNGJUWWdjN2M3amVXbXQ5VGgxMXczbzhVUFg5YWt1RnAyb3c?oc=5 | W41: =IF($B41="",0,IF(AND(OR(OR(Dashboard!$B$5="All themes",Dashboard!$B$5=""),$C41=Dashboard!$B$5),OR(OR(Dashboard!$G$5="All uses",Dashboard!$G$5=""),$E41=Dashboard!$G$5),N($D41)>=Lists!$H$2,OR(OR(Dashboard!$N$5="All windows",Dashboard!$N$5=""),$S41=Dashboard!$N$5)),1,0)) | X41: =IF($W41=1,N($D41)*1E14+MIN(MAX(N($U41),0),9999)*1E10+MIN(N($K41),99999)*1E5+99999-MIN(ROW(),99999),"")
A42: 39 | B42: Fortes chuvas provocam deslizamento de terra em acesso da SP-294 em Garça | C42: Infrastructure & the Underground City | D42: 3 | E42: News brief | F42: To review | I42: What causes a cut or embankment on a state highway access road to fail under heavy rain, and what stabilisation is appropriate for such slopes? | J42: Marília Notícia | K42: 46321 | M42: DER-SP (São Paulo state roads department) | N42: Brazil | O42: Garça, SP-294 access road | Q42: Brazil | R42: 46320 | S42: 2026-Q4 | T42: landslide | U42: 4 | V42: https://news.google.com/rss/articles/CBMirwFBVV95cUxQd216OXIzbVp3NEZ5M2ozejBVWktPYmoyd29wVVFEQmRLbUU1RWZ1Yi0zUGR4bUJCZV9xYmxDWTdqemFNcmM3WTdmUlA5M3RHcGtwLUQwYkxDUXNWUFdUbXo1SVZpMDJQTllFYjJBVG0wTF9iTkZrWVFLaXRNdU9qRjBuaWlWYUlBMUhNZ0xtMzlFNURQT2cxblRyRV9HYlBob2JQLWVmbkR1Z2MwSEJj?oc=5 | W42: =IF($B42="",0,IF(AND(OR(OR(Dashboard!$B$5="All themes",Dashboard!$B$5=""),$C42=Dashboard!$B$5),OR(OR(Dashboard!$G$5="All uses",Dashboard!$G$5=""),$E42=Dashboard!$G$5),N($D42)>=Lists!$H$2,OR(OR(Dashboard!$N$5="All windows",Dashboard!$N$5=""),$S42=Dashboard!$N$5)),1,0)) | X42: =IF($W42=1,N($D42)*1E14+MIN(MAX(N($U42),0),9999)*1E10+MIN(N($K42),99999)*1E5+99999-MIN(ROW(),99999),"")
A43: 40 | B43: Deslizamento de terra e árvores bloqueia rodovia entre Tatuí e Boituva | C43: Infrastructure & the Underground City | D43: 3 | E43: News brief | F43: To review | I43: What triggered a slope to shed soil and vegetation onto a regional highway, and what slope inspection would prevent repeated closures on this route? | J43: G1 | K43: 46321 | M43: DER-SP (São Paulo state roads department) | N43: Brazil | O43: Tatuí–Boituva road, São Paulo | Q43: Brazil | R43: 46320 | S43: 2026-Q4 | T43: landslide | U43: 4 | V43: https://news.google.com/rss/articles/CBMi1gFBVV95cUxNa1J5Qm5WUEhnak5mVkZhS1RabHBudEcyUkE4LUJESjgxRFg0T1U5emFhZVh2LXpZZFQ5eXR5S0Q2TFV5TFpuMWJHNGt6azN1R2plbVkxdTNnbzVRWTdVSDBHNk1La1FweTQ4dkxhb1BjaTllVmRFT0t4dzdEbzZXZjBYWnlJSWQxVXp6ZFhsWmVabk9KZmtlTEtuQmwza3pDQ0tpWTBzVkxKbTNtRWtoMlR4b01VUDVoMDhrNC13RGhqbnRVT3lVekdNV1NpRWk3cDNzSWNB0gHkAUFVX3lxTE40VE5KUjc5OGJtZk42dG1aVzEybU9fZ2N3NFFLTE9ab3pocGdScGh5S1otd1htVUIzaThZODV0Tk1ISHkzaE95T2I0M3lFMDQ5X2Utdnh1YTVYU2phMEhiNmJfZkhMX1dPZVBIRDZwdG5sRG82Sy1KWERDemVVUklWOE1sM3RNQzJoTjlrTW5QQUpDSUxTVmxGcGJtak80NHBFYjhwaF9na0Z6b2dENVdZUGNfc2dkdlBZcVhZZlBQTThlUjI2WlZGcDFOdWtfTGV5SlhJYWo1QndYSnFwLTFqSjYtQQ?oc=5 | W43: =IF($B43="",0,IF(AND(OR(OR(Dashboard!$B$5="All themes",Dashboard!$B$5=""),$C43=Dashboard!$B$5),OR(OR(Dashboard!$G$5="All uses",Dashboard!$G$5=""),$E43=Dashboard!$G$5),N($D43)>=Lists!$H$2,OR(OR(Dashboard!$N$5="All windows",Dashboard!$N$5=""),$S43=Dashboard!$N$5)),1,0)) | X43: =IF($W43=1,N($D43)*1E14+MIN(MAX(N($U43),0),9999)*1E10+MIN(N($K43),99999)*1E5+99999-MIN(ROW(),99999),"")
A44: 41 | B44: Deslizamento de terra interdita rodovia entre Realeza e Planalto | C44: Infrastructure & the Underground City | D44: 3 | E44: News brief | F44: To review | I44: Why do rural highway cuts in this region fail during rain, and what slope stability assessment would inform repair and prevent future interdictions? | J44: Jornal Novo Tempo | K44: 46321 | M44: DER-PR (Paraná state roads department) | N44: Brazil | O44: Realeza–Planalto road, Paraná | Q44: Brazil | R44: 46320 | S44: 2026-Q4 | T44: landslide | U44: 4 | V44: https://news.google.com/rss/articles/CBMiuAFBVV95cUxOS3ZyVDhPWjk5Z1J4dkdFbndrWTBBZXd6UUVHM3lxUTVMQkZOSjk0N2VuSlJCZ2hJSWd5cW8wOGN3VWZSTzlqTnBWV0RZbTFSNWNxaWtEUXhhTkZzSGNZcTVSUnNDQ1VGNHRnelFZblZwbTZtSjl2UUhLMEdwN1k5WlZaVWdtcTVkdnpIRE41eTBfZjhqV3d1MTNLeldNZGg5ekxTMjRORGZOajBPRng5cTJ1QUxMSEhB?oc=5 | W44: =IF($B44="",0,IF(AND(OR(OR(Dashboard!$B$5="All themes",Dashboard!$B$5=""),$C44=Dashboard!$B$5),OR(OR(Dashboard!$G$5="All uses",Dashboard!$G$5=""),$E44=Dashboard!$G$5),N($D44)>=Lists!$H$2,OR(OR(Dashboard!$N$5="All windows",Dashboard!$N$5=""),$S44=Dashboard!$N$5)),1,0)) | X44: =IF($W44=1,N($D44)*1E14+MIN(MAX(N($U44),0),9999)*1E10+MIN(N($K44),99999)*1E5+99999-MIN(ROW(),99999),"")
A45: 42 | B45: BR-277 é liberada após deslizamento de terra na Serra da Esperança, em Guarapuava | C45: Infrastructure & the Underground City | D45: 3 | E45: News brief | F45: To review | I45: What triggered the mountain slope failure on this highway, and what monitoring and remediation would reduce the time the route is closed after storms? | J45: Catve | K45: 46321 | M45: DNIT and the BR-277 concessionaire | N45: Brazil | O45: Serra da Esperança, Guarapuava | Q45: Brazil | R45: 46319 | S45: 2026-Q4 | T45: landslide | U45: 4 | V45: https://news.google.com/rss/articles/CBMiR0FVX3lxTE94OUJCMW4zNWdhYkRhdHNyanpLUDRXZ0gtZERXYjNCdnM0X3Z0WnV3QlVaX09kem5CMko5Vy0wamJTUnZkWjRB?oc=5 | W45: =IF($B45="",0,IF(AND(OR(OR(Dashboard!$B$5="All themes",Dashboard!$B$5=""),$C45=Dashboard!$B$5),OR(OR(Dashboard!$G$5="All uses",Dashboard!$G$5=""),$E45=Dashboard!$G$5),N($D45)>=Lists!$H$2,OR(OR(Dashboard!$N$5="All windows",Dashboard!$N$5=""),$S45=Dashboard!$N$5)),1,0)) | X45: =IF($W45=1,N($D45)*1E14+MIN(MAX(N($U45),0),9999)*1E10+MIN(N($K45),99999)*1E5+99999-MIN(ROW(),99999),"")
A46: 43 | B46: Deslizamento de terra no Km 43, em Cajamar, coloca motoristas em alerta | C46: Infrastructure & the Underground City | D46: 3 | E46: News brief | F46: To review | I46: What caused soil to slide onto this highway cut, and what slope inspection and drainage check should follow before traffic is fully normal? | J46: JORNAL DA REGIÃO | K46: 46321 | M46: DER-SP and the road concessionaire | N46: Brazil | O46: Cajamar, São Paulo | Q46: Brazil | R46: 46320 | S46: 2026-Q4 | T46: landslide | U46: 4 | V46: https://news.google.com/rss/articles/CBMioAFBVV95cUxNcE1vSTkzcnVFZHlScldIbU1rdk51ZlN2WHZhNVRUWjdETmhvYmJyNVdKTjRBdENnNk83d29TZTVEWngweEs5LUlKeFZLRFBrQWFIMWk0MWJtVjdFVkhJX3FfRGdzckVFdnBISVhmb2hiUmFNaDM2WURmUE9tUmNiUFNjM3FhYW9NSmNteTZRUmJMV2VPekk3SFlIaWU3X3JH?oc=5 | W46: =IF($B46="",0,IF(AND(OR(OR(Dashboard!$B$5="All themes",Dashboard!$B$5=""),$C46=Dashboard!$B$5),OR(OR(Dashboard!$G$5="All uses",Dashboard!$G$5=""),$E46=Dashboard!$G$5),N($D46)>=Lists!$H$2,OR(OR(Dashboard!$N$5="All windows",Dashboard!$N$5=""),$S46=Dashboard!$N$5)),1,0)) | X46: =IF($W46=1,N($D46)*1E14+MIN(MAX(N($U46),0),9999)*1E10+MIN(N($K46),99999)*1E5+99999-MIN(ROW(),99999),"")
A47: 44 | B47: More than 100 days after Kalladi landslip, twin-tunnel road project awaits safety reports | C47: Hazards & Resilience | D47: 5 | E47: Feature lead | F47: To review | I47: How should twin-tunnel road projects be geotechnically assessed and safety-verified in landslide-prone hill terrain after a major slope failure? | J47: Onmanorama | K47: 46320 | N47: India | O47: Kalladi, Kerala | Q47: South Africa | R47: 46319 | S47: 2026-Q4 | T47: landslip, tunnel | U47: 6 | V47: https://news.google.com/rss/articles/CBMi2wFBVV95cUxQYlB1TFpreUsyaGpXMjRFOFRPSFBBR1R5QmxiMkxzMS1vbW1vNklPRk1kTUFtekZFOGt0aEdKc1c1ajRDN20yLTl0Ym1JUXBNanctbXF3OVlMUi1iOVo3WDRMeUR6a3RuQnZXNWgxa01JQThSaGZoUlFvZ19fZXM0MEo4ekJMbmpSRlVLZGtmaGczbEFOZ0tYdzNBNDZsUFJZVTFIV2tKY3FUY1pHdXBoRnREeGdZem1qRjNnMkxYZjRvMGtiSmx5ZHp1MGdGTXBRd00wRTFSWVREMUE?oc=5 | W47: =IF($B47="",0,IF(AND(OR(OR(Dashboard!$B$5="All themes",Dashboard!$B$5=""),$C47=Dashboard!$B$5),OR(OR(Dashboard!$G$5="All uses",Dashboard!$G$5=""),$E47=Dashboard!$G$5),N($D47)>=Lists!$H$2,OR(OR(Dashboard!$N$5="All windows",Dashboard!$N$5=""),$S47=Dashboard!$N$5)),1,0)) | X47: =IF($W47=1,N($D47)*1E14+MIN(MAX(N($U47),0),9999)*1E10+MIN(N($K47),99999)*1E5+99999-MIN(ROW(),99999),"")
A48: 45 | B48: Fragility of port disaster prevention exposed: liquefaction halts logistics at Yatsushiro | C48: Hazards & Resilience | D48: 5 | E48: Feature lead | F48: To review | I48: Why do reclaimed port areas liquefy during earthquakes, and how can quay and yard design reduce the risk of losing logistics function after shaking? | J48: 山陽新聞 | K48: 46320 | L48: 港湾防災のもろさ露呈 八代、液状化で物流停止 | N48: Japan | O48: Yatsushiro port, Kumamoto | Q48: Japan | R48: 46318 | S48: 2026-Q4 | T48: liquefaction | U48: 5 | V48: https://news.google.com/rss/articles/CBMiZ0FVX3lxTE5leHlqNFI1UXh5aXh5dU5RMVFSUmI5Y2VCOFkzTzhla0Rwa25XbDk5ZlBNblFrdEw2UDc2ZTA4VWtaWmJuN25hLWlBdjNpRDJEU045aldfR3dLbzhzdGZmN3ltV3lxQ3M?oc=5 | W48: =IF($B48="",0,IF(AND(OR(OR(Dashboard!$B$5="All themes",Dashboard!$B$5=""),$C48=Dashboard!$B$5),OR(OR(Dashboard!$G$5="All uses",Dashboard!$G$5=""),$E48=Dashboard!$G$5),N($D48)>=Lists!$H$2,OR(OR(Dashboard!$N$5="All windows",Dashboard!$N$5=""),$S48=Dashboard!$N$5)),1,0)) | X48: =IF($W48=1,N($D48)*1E14+MIN(MAX(N($U48),0),9999)*1E10+MIN(N($K48),99999)*1E5+99999-MIN(ROW(),99999),"")
A49: 46 | B49: Arauco sinkhole: government acknowledges earlier warnings about unstable land and keeps 152 families evacuated | C49: Hazards & Resilience | D49: 5 | E49: Feature lead | F49: To review | I49: How should authorities act on prior geotechnical warnings about unstable ground, and what criteria should govern long-term evacuation and land reuse? | J49: Publimicro | K49: 46320 | L49: Socavón de Arauco: Gobierno reconoce advertencias previas sobre terrenos inestables y mantiene evacuación de 152 familias | N49: Chile | O49: Arauco | P49: Arauco sinkhole, Chile (Oct 2026) · Response & recovery · 2 reports | Q49: Colombia | R49: 46320 | S49: 2026-Q4 | T49: sinkhole | U49: 4 | V49: https://news.google.com/rss/articles/CBMi2wFBVV95cUxPbEItcVZCOEZqYkozMmZkelZyb2JPaWRsOHl5M0dHNUQyWE1tVnRYbXk4eHZBbWJudE8zUFJGSWNUdlNZZE5pS2FDWDhnY19OM0FGSUVDb1FaN044VHU0X04zUnFhREE0M0kyRW83czIwZVlwZnRnNnBaU2VwUUotZWZXZWl2WHNnV01LaXV5Nzk5dklNSE9zZHlXZG41SGg3WlUwQlk4N1BhX3VlSGNKa2pyX2VBMzBVMWFzdEwtejR2TlNYb29DNmtxYURuaHl2YWlIRzk4dktYMzA?oc=5 | W49: =IF($B49="",0,IF(AND(OR(OR(Dashboard!$B$5="All themes",Dashboard!$B$5=""),$C49=Dashboard!$B$5),OR(OR(Dashboard!$G$5="All uses",Dashboard!$G$5=""),$E49=Dashboard!$G$5),N($D49)>=Lists!$H$2,OR(OR(Dashboard!$N$5="All windows",Dashboard!$N$5=""),$S49=Dashboard!$N$5)),1,0)) | X49: =IF($W49=1,N($D49)*1E14+MIN(MAX(N($U49),0),9999)*1E10+MIN(N($K49),99999)*1E5+99999-MIN(ROW(),99999),"")
A50: 47 | B50: Up to 1.20 metres of ground moved during the 7.5 earthquake that shook Panama | C50: Hazards & Resilience | D50: 5 | E50: Feature lead | F50: To review | I50: What mechanisms produced metre-scale ground displacement during this magnitude 7.5 earthquake, and what do they imply for fault-zone hazard assessment in Panama? | J50: Infobae | K50: 46320 | L50: Hasta 1.20 metros se desplazó el suelo durante el terremoto de 7.5 que sacudió Panamá | N50: Panama | O50: Panama | Q50: Argentina | R50: 46317 | S50: 2026-Q4 | T50: earthquake, soil | U50: 3 | V50: https://news.google.com/rss/articles/CBMixAFBVV95cUxNb1N4SjlJaXNrelJVZzRFNWxVeXJ3T1VBNHVRa25mZzF3amp0Rk4yWG8yZHJYOVpoaFlrWHNuLUlEcVBPUTl5MVpyTVUtemtxSHMzN3NsbDFfZXZkT0x2V1Q4Wm1McXJxRFg3TFZmWTBLbURMM3ZDZ2d6cEJMNzlaUTdFM3k3YWFLLXlkcFo0UERKUWFQalM1X0F0Qk52ckUwbXZRM3VTa1RVMTd4SmlrYzR5LU9iUXdCbk9SQmZaYlViNVBF0gHfAUFVX3lxTE9pU0JMMnVDa2FFQ3RzdEgweE1mYVJIandLaTdZTk5YOVl6Ri1uUnVMS3Jsc25qMDNzVjk0QUhqYzNCMFFWQkFycGRDZklpSmg1ZE00M2V5TDRJRXR1NnhyMWxhb3lVdUoyaEhWVy14Q1FuUmQzc2hHbVBhRXdMQTlKYVdYT25Id1owZ2FiUy1Vczl3WG5sMVhuM1RIS05xekVTOGF5eEJ5TjYwTjdQVTRyWmVnb1QwTm5yOXVfalJfcFNpNERRc3VqYmtCTjVOMnhNV3o4VTdYYy0wQnVXdmM?oc=5 | W50: =IF($B50="",0,IF(AND(OR(OR(Dashboard!$B$5="All themes",Dashboard!$B$5=""),$C50=Dashboard!$B$5),OR(OR(Dashboard!$G$5="All uses",Dashboard!$G$5=""),$E50=Dashboard!$G$5),N($D50)>=Lists!$H$2,OR(OR(Dashboard!$N$5="All windows",Dashboard!$N$5=""),$S50=Dashboard!$N$5)),1,0)) | X50: =IF($W50=1,N($D50)*1E14+MIN(MAX(N($U50),0),9999)*1E10+MIN(N($K50),99999)*1E5+99999-MIN(ROW(),99999),"")
A51: 48 | B51: Zaruma sits on old gold galleries: where is the sinkhole risk concentrated? | C51: Hazards & Resilience | D51: 5 | E51: Feature lead | F51: To review | I51: How do abandoned shallow gold mine galleries affect ground stability beneath an urban area, and how can the sinkhole risk be mapped and managed? | J51: Revista Digital Minera REDIMIN | K51: 46320 | L51: Zaruma está sobre antiguas galerías de oro: ¿Dónde se concentra el riesgo de hundimiento? | N51: Ecuador | O51: Zaruma | Q51: Argentina | R51: 46319 | S51: 2026-Q4 | U51: 0 | V51: https://news.google.com/rss/articles/CBMirgFBVV95cUxOMUhXcnpZRTdoS0lYX2pGQ25VSzB1Y3NXNzRVajdqTzVLdWZHcU5MVEpWMHRmTVdIaXJZbGtSNWpCX2tOamV6Qk5HenVWRmxBNXJkbXhLVExlYWIzNHp5T2x4dGJmVElvaTMxU2hDYUpFRkVNS0JUR3dsdG41WnV2UkVqSlBMYWpwbjMxbmc2ejFjM21EQTlnVDk5MmdPZGF4alFpT3ROYTRkWkM5cVE?oc=5 | W51: =IF($B51="",0,IF(AND(OR(OR(Dashboard!$B$5="All themes",Dashboard!$B$5=""),$C51=Dashboard!$B$5),OR(OR(Dashboard!$G$5="All uses",Dashboard!$G$5=""),$E51=Dashboard!$G$5),N($D51)>=Lists!$H$2,OR(OR(Dashboard!$N$5="All windows",Dashboard!$N$5=""),$S51=Dashboard!$N$5)),1,0)) | X51: =IF($W51=1,N($D51)*1E14+MIN(MAX(N($U51),0),9999)*1E10+MIN(N($K51),99999)*1E5+99999-MIN(ROW(),99999),"")
A52: 49 | B52: Rockfall and landslide on the mountain of the Noah's Ark legend captured on camera; climbers escape unhurt | C52: Hazards & Resilience | D52: 4 | E52: News brief | F52: To review | I52: What triggers rockfall and debris slides on steep volcanic-sedimentary mountain slopes, and how should hazard zoning account for such events near visitor routes? | J52: FNNプライムオンライン | K52: 46320 | L52: 「ノアの箱舟」伝説の山で落石・土砂崩れ 「来るぞ！走れ！逃げろ！」カメラが捉えた発生の瞬間 “間一髪”の登山者らけがなし トルコ | N52: Türkiye | O52: Mount Ararat, Ağrı | Q52: Japan | R52: 46318 | S52: 2026-Q4 | T52: landslide, rockfall | U52: 8 | V52: https://news.google.com/rss/articles/CBMiTkFVX3lxTE1uZEw5RnB3UEJsWjd6MFZFRXhhUkV0d0QwMURpMVNQVjhUR3BIdHNrRWZ4OFFJWS12Z3JIcEthQkFhOU9WeC1fVHdiM3hLQQ?oc=5 | W52: =IF($B52="",0,IF(AND(OR(OR(Dashboard!$B$5="All themes",Dashboard!$B$5=""),$C52=Dashboard!$B$5),OR(OR(Dashboard!$G$5="All uses",Dashboard!$G$5=""),$E52=Dashboard!$G$5),N($D52)>=Lists!$H$2,OR(OR(Dashboard!$N$5="All windows",Dashboard!$N$5=""),$S52=Dashboard!$N$5)),1,0)) | X52: =IF($W52=1,N($D52)*1E14+MIN(MAX(N($U52),0),9999)*1E10+MIN(N($K52),99999)*1E5+99999-MIN(ROW(),99999),"")
A53: 50 | B53: Nghe An: urgent measures needed for landslide on the seaside road embankment | C53: Offshore, Coasts & Water | D53: 4 | E53: News brief | F53: To review | I53: Why do coastal road embankments fail by landslide, and what emergency stabilisation and monitoring are appropriate for dyke slopes exposed to waves and rainfall? | J53: Vietnam.vn | K53: 46320 | L53: 응에안성: 해안 도로 제방의 산사태 발생에 대한 긴급 조치가 필요합니다. | N53: Vietnam | O53: Nghe An coastal road | P53: Nghe An coastal road embankment landslide, Vietnam (Oct 2026) · Response & recovery · 2 reports | Q53: South Korea | R53: 46318 | S53: 2026-Q4 | T53: landslide, embankment | U53: 7 | V53: https://news.google.com/rss/articles/CBMilwFBVV95cUxPVWtrMThoQUYxQjFSLS1VQ01fYmEzUW8tamxpSHVxS3hnaWV4YWl2MV9oRUw1ekE0SG01SHJxZTM2c1p6aXMzNWh2Q2M0bXhyYjFjQm9zRGlJUUJ2TWE5VE5TYW41ZTFqSV9vaG9ZRjAyNEJNYkVrU1BrRlN3QTFQZjlUQndtZE94WWpaVXQ4RTRCZmM1enNJ?oc=5 | W53: =IF($B53="",0,IF(AND(OR(OR(Dashboard!$B$5="All themes",Dashboard!$B$5=""),$C53=Dashboard!$B$5),OR(OR(Dashboard!$G$5="All uses",Dashboard!$G$5=""),$E53=Dashboard!$G$5),N($D53)>=Lists!$H$2,OR(OR(Dashboard!$N$5="All windows",Dashboard!$N$5=""),$S53=Dashboard!$N$5)),1,0)) | X53: =IF($W53=1,N($D53)*1E14+MIN(MAX(N($U53),0),9999)*1E10+MIN(N($K53),99999)*1E5+99999-MIN(ROW(),99999),"")
A54: 51 | B54: Quang Tri: severe coastal erosion threatens dykes, embankments and residents' lives. | C54: Offshore, Coasts & Water | D54: 4 | E54: Feature lead | F54: To review | I54: How can coastal erosion monitoring and erosion-resistant embankment design protect dykes and communities when shoreline retreat accelerates? | J54: Vietnam.vn | K54: 46320 | L54: 꽝찌: 심각한 해안 침식으로 인해 제방과 둑, 그리고 주민들의 생명이 위협받고 있습니다. | N54: Vietnam | O54: Quang Tri province | P54: Quang Tri coastal erosion threatening dykes, Vietnam (Oct 2026) · Event · 2 reports | Q54: South Korea | R54: 46318 | S54: 2026-Q4 | T54: embankment, erosion | U54: 5 | V54: https://news.google.com/rss/articles/CBMingFBVV95cUxOMW5DMERmVlE2dVl1LU4zMFhMTlpPLVBHblZweXJjYXJIV0ZHVVR6Sk50eW1xVm1MS3VTYTJtUjBoZkVfTm1hWFlmTGlOS0JZX2lOSTJCYkoxbm1TODNFSURESTIxbm5YRjJXcVkxOGp6bmdnMmJmdjBqRnNzXzFDdzdHaXVBYXlaVzFiZW5kSlpJdEIyemJVeDVWZWlsdw?oc=5 | W54: =IF($B54="",0,IF(AND(OR(OR(Dashboard!$B$5="All themes",Dashboard!$B$5=""),$C54=Dashboard!$B$5),OR(OR(Dashboard!$G$5="All uses",Dashboard!$G$5=""),$E54=Dashboard!$G$5),N($D54)>=Lists!$H$2,OR(OR(Dashboard!$N$5="All windows",Dashboard!$N$5=""),$S54=Dashboard!$N$5)),1,0)) | X54: =IF($W54=1,N($D54)*1E14+MIN(MAX(N($U54),0),9999)*1E10+MIN(N($K54),99999)*1E5+99999-MIN(ROW(),99999),"")
A55: 52 | B55: Survived against the odds: home destroyed in typhoon No. 25 landslide in Kamogawa; Iimura Hiroshi says fear comes with consciousness | C55: Hazards & Resilience | D55: 4 | E55: News brief | F55: To review | I55: What slope and saturation conditions cause houses on hillsides to be destroyed by debris slides during typhoon rainfall, and how can early warning address them? | J55: 千葉日報オンライン | K55: 46320 | L55: 自宅崩壊“九死に一生” 台風２５号 鴨川で土砂崩れ多発 生き埋めから生還 飯村浩さん 意識あるからこそ恐怖 | N55: Japan | O55: Kamogawa, Chiba | P55: Typhoon 25 landslides, Bōsō Peninsula, Japan (Oct 2026) · Event · 2 reports | Q55: Japan | R55: 46319 | S55: 2026-Q4 | T55: landslide, collapse | U55: 5 | V55: https://news.google.com/rss/articles/CBMiWEFVX3lxTFBTQ25tOTZGZzZsUWdHamNXa3hxMGdGTG8ySno0dWhQSzl1SnVtZHBuSUtrM3d3VTJPekZvbFZXRDY0TWhFZ1NDWDllM3RSeDI5SUZkRWZtQzU?oc=5 | W55: =IF($B55="",0,IF(AND(OR(OR(Dashboard!$B$5="All themes",Dashboard!$B$5=""),$C55=Dashboard!$B$5),OR(OR(Dashboard!$G$5="All uses",Dashboard!$G$5=""),$E55=Dashboard!$G$5),N($D55)>=Lists!$H$2,OR(OR(Dashboard!$N$5="All windows",Dashboard!$N$5=""),$S55=Dashboard!$N$5)),1,0)) | X55: =IF($W55=1,N($D55)*1E14+MIN(MAX(N($U55),0),9999)*1E10+MIN(N($K55),99999)*1E5+99999-MIN(ROW(),99999),"")
A56: 53 | B56: Four guests fall into sinkhole at Occidental Cozumel hotel | C56: Infrastructure & the Underground City | D56: 4 | E56: News brief | F56: To review | I56: How do karst cavities and dissolution features in coastal limestone create sudden collapses beneath hotel and tourist structures? | J56: Quintana Roo Hoy | K56: 46320 | L56: Cuatro huéspedes caen en socavón del hotel Occidental Cozumel | N56: Mexico | O56: Cozumel, Quintana Roo | P56: Occidental Cozumel hotel sinkhole, Mexico (Oct 2026) · Event · 3 reports | Q56: Colombia | R56: 46319 | S56: 2026-Q4 | T56: sinkhole | U56: 4 | V56: https://news.google.com/rss/articles/CBMipAFBVV95cUxNSjZ6bXhiX2dfbkViZ2dUOVpjOFYyblBpYW81WjVHdkRwYkNGb1hjbF96R1lBaUpxemx0V2FYQVVXM2hiNFF4YzlNSzBOUWtvRldwNjE2VS1wRVpxbzlBdERnUWttZU1abXg1VlNiZER5d3g3V0ZoWTl2dnNNd2Q3RlhHWFM0Q0dranBKbTRUb0w4LWdWWGF6UWhZczREOGQ4WnhfNg?oc=5 | W56: =IF($B56="",0,IF(AND(OR(OR(Dashboard!$B$5="All themes",Dashboard!$B$5=""),$C56=Dashboard!$B$5),OR(OR(Dashboard!$G$5="All uses",Dashboard!$G$5=""),$E56=Dashboard!$G$5),N($D56)>=Lists!$H$2,OR(OR(Dashboard!$N$5="All windows",Dashboard!$N$5=""),$S56=Dashboard!$N$5)),1,0)) | X56: =IF($W56=1,N($D56)*1E14+MIN(MAX(N($U56),0),9999)*1E10+MIN(N($K56),99999)*1E5+99999-MIN(ROW(),99999),"")
A57: 54 | B57: Close-up of giant 120 m deep sinkhole just discovered in Phong Nha-Ke Bang | C57: Characterisation & Modelling | D57: 4 | E57: Feature lead | F57: To review | I57: How are very deep karst sinkholes investigated, and what does their formation reveal about hazards around cave systems? | J57: Laodong.vn | K57: 46320 | L57: 퐁냐케방에서 방금 발견된 깊이 120m의 거대한 싱크홀 근접 촬영 | N57: Vietnam | O57: Phong Nha-Ke Bang | P57: Phong Nha-Ke Bang 120 m sinkhole discovery, Vietnam · Update · 4 reports | Q57: South Korea | R57: 46320 | S57: 2026-Q4 | T57: sinkhole | U57: 4 | V57: https://news.google.com/rss/articles/CBMisgFBVV95cUxQdURwNUowWTYydWgxelNON0NTNUozZXdjMFUxM3AtSHBQRTBfWWZlT0tWQ0VkaDdNa0lOanpPSk05SVRyZVhOODJteTJzUGo4UWlYUFRBb3dLMnB2R2Z5NjZ0XzRVdHQyS3hYUlRPMl9rZmw4SnZjdXJGT2dhZ18wNzFsOFNvOGg0Tmh4c1ViaDR3Y3lPQUhnMnNkYzNnSkRjOG9xWXpHcFJYYW1rZ01zcGhB?oc=5 | W57: =IF($B57="",0,IF(AND(OR(OR(Dashboard!$B$5="All themes",Dashboard!$B$5=""),$C57=Dashboard!$B$5),OR(OR(Dashboard!$G$5="All uses",Dashboard!$G$5=""),$E57=Dashboard!$G$5),N($D57)>=Lists!$H$2,OR(OR(Dashboard!$N$5="All windows",Dashboard!$N$5=""),$S57=Dashboard!$N$5)),1,0)) | X57: =IF($W57=1,N($D57)*1E14+MIN(MAX(N($U57),0),9999)*1E10+MIN(N($K57),99999)*1E5+99999-MIN(ROW(),99999),"")
A58: 55 | B58: Using AI to provide early warning of landslide risks. | C58: Digital Geotechnics | D58: 4 | E58: Feature lead | F58: To review | I58: How reliable are AI-based landslide early-warning models when trained on sparse ground monitoring data? | J58: Vietnam.vn | K58: 46320 | P58: AI landslide early warning, Vietnam · Event · 3 reports | Q58: United Kingdom | R58: 46319 | S58: 2026-Q4 | T58: landslide | U58: 4 | V58: https://news.google.com/rss/articles/CBMibkFVX3lxTFBHcTd0RXlKUzRRSnNZS2RrSFdQSTlnajJrcWxrUWt4S2E5cDNqSkhzRDNiRl84eW1Obll6MDJiLTUxSURzUG5GVWtnOVR3TlhyMUpPMzNHYW1XNlNyRFNweHlQMDA1RjNqQS1KZnRn?oc=5 | W58: =IF($B58="",0,IF(AND(OR(OR(Dashboard!$B$5="All themes",Dashboard!$B$5=""),$C58=Dashboard!$B$5),OR(OR(Dashboard!$G$5="All uses",Dashboard!$G$5=""),$E58=Dashboard!$G$5),N($D58)>=Lists!$H$2,OR(OR(Dashboard!$N$5="All windows",Dashboard!$N$5=""),$S58=Dashboard!$N$5)),1,0)) | X58: =IF($W58=1,N($D58)*1E14+MIN(MAX(N($U58),0),9999)*1E10+MIN(N($K58),99999)*1E5+99999-MIN(ROW(),99999),"")
A59: 56 | B59: Reconstruction of the Terrazas del Valle bridge begins after sinkhole | C59: Infrastructure & the Underground City | D59: 4 | E59: News brief | F59: To review | I59: What investigation and foundation design are needed to rebuild a bridge whose support ground has collapsed into a sinkhole? | J59: NDT Noticias de Tijuana | K59: 46320 | L59: Inician reconstrucción del puente de Terrazas del Valle tras socavón | N59: Mexico | O59: Terrazas del Valle bridge, Tijuana | P59: Terrazas del Valle bridge sinkhole, Tijuana, Mexico · Event · 2 reports | Q59: Colombia | R59: 46319 | S59: 2026-Q4 | T59: sinkhole | U59: 4 | V59: https://news.google.com/rss/articles/CBMikgFBVV95cUxOTnI4emxtUmVodDFQV3Z1REstXzUyWWxvdHg5SGoxeXdNUmdPRUppY2hOZ090aElnMGpLWUZ5TEVvUVNJbVVYcDh3VjNEbWNsekVpXzNKNHFEbVRUZTVaazZ3TlpzMGNHU3A3S2g1WkgxWkdEaUo4dE5WRXB6UkQ0QjdneVMyOUZfODViZHBJZlpvQQ?oc=5 | W59: =IF($B59="",0,IF(AND(OR(OR(Dashboard!$B$5="All themes",Dashboard!$B$5=""),$C59=Dashboard!$B$5),OR(OR(Dashboard!$G$5="All uses",Dashboard!$G$5=""),$E59=Dashboard!$G$5),N($D59)>=Lists!$H$2,OR(OR(Dashboard!$N$5="All windows",Dashboard!$N$5=""),$S59=Dashboard!$N$5)),1,0)) | X59: =IF($W59=1,N($D59)*1E14+MIN(MAX(N($U59),0),9999)*1E10+MIN(N($K59),99999)*1E5+99999-MIN(ROW(),99999),"")
A60: 57 | B60: 120 m deep sinkhole containing primeval forest discovered in Phong Nha-Ke Bang area | C60: Characterisation & Modelling | D60: 4 | E60: Feature lead | F60: To review | I60: How are very deep karst sinkholes investigated, and what does their formation reveal about hazards around cave systems? | J60: Vietnam.vn | K60: 46320 | L60: 퐁냐-케방 지역에서 원시림이 포함된 깊이 120미터의 싱크홀이 발견되었습니다. | N60: Vietnam | O60: Phong Nha-Ke Bang | P60: Phong Nha-Ke Bang 120 m sinkhole discovery, Vietnam · Update · 4 reports | Q60: South Korea | R60: 46317 | S60: 2026-Q4 | T60: sinkhole | U60: 4 | V60: https://news.google.com/rss/articles/CBMilgFBVV95cUxOaWxCcjZNMEJuSVgyc2QwRzY3ZzZMblFuNWxLV0NvSl9yRnFQLWY3NG9pRTRuVU5fdHB0YUVSd0w3V2VDSVdaLXdDYWJOUlVyM0VhWVpLQ0E1SjJxOHVMUG9pTC1JcWpKUGVNZDF6c25nZlRoZ3hwOVZPSEtqbzRIREJpTUR6UjBjbVdPckE3eTBCWU43S0E?oc=5 | W60: =IF($B60="",0,IF(AND(OR(OR(Dashboard!$B$5="All themes",Dashboard!$B$5=""),$C60=Dashboard!$B$5),OR(OR(Dashboard!$G$5="All uses",Dashboard!$G$5=""),$E60=Dashboard!$G$5),N($D60)>=Lists!$H$2,OR(OR(Dashboard!$N$5="All windows",Dashboard!$N$5=""),$S60=Dashboard!$N$5)),1,0)) | X60: =IF($W60=1,N($D60)*1E14+MIN(MAX(N($U60),0),9999)*1E10+MIN(N($K60),99999)*1E5+99999-MIN(ROW(),99999),"")
A61: 58 | B61: Can Tho to invest over 500 billion dong in dykes against erosion at Cu Lao Dung | C61: Offshore, Coasts & Water | D61: 4 | E61: Feature lead | F61: To review | I61: How should dyke and bank protection balance erosion control against settlement and stability on soft deltaic soils? | J61: Báo Nhân Dân điện tử | K61: 46320 | L61: Cần Thơ đầu tư hơn 500 tỷ đồng xây dựng đê phòng, chống sạt lở ở Cù Lao Dung | N61: Vietnam | O61: Cu Lao Dung, Can Tho | Q61: Vietnam | R61: 46319 | S61: 2026-Q4 | T61: landslide | U61: 4 | V61: https://news.google.com/rss/articles/CBMirwFBVV95cUxOWUlBRk5ZaXZkRzhyQ3BQalNsY2xOM2pzQUNMeVI4UEFXQkdBNTdkd2d4Rno5TWNjb0VEeEFwWkhEb2k4S2J3cEtaTGpDM3NMNkR2WEQ2dGtzdWowQTVwa3ZSTEV6ZVdCRl9fRC1Zanc5VXljcllHTlZJZHRTNllxVElOR2hIUmlqWDF2LUFxTzhYU1UtdU5VWFJlWWYzbS1wRmV6cHluMkdDc1RQUkFv?oc=5 | W61: =IF($B61="",0,IF(AND(OR(OR(Dashboard!$B$5="All themes",Dashboard!$B$5=""),$C61=Dashboard!$B$5),OR(OR(Dashboard!$G$5="All uses",Dashboard!$G$5=""),$E61=Dashboard!$G$5),N($D61)>=Lists!$H$2,OR(OR(Dashboard!$N$5="All windows",Dashboard!$N$5=""),$S61=Dashboard!$N$5)),1,0)) | X61: =IF($W61=1,N($D61)*1E14+MIN(MAX(N($U61),0),9999)*1E10+MIN(N($K61),99999)*1E5+99999-MIN(ROW(),99999),"")
A62: 59 | B62: Krong No river erosion in Lam Dong threatens irrigation works and farmland | C62: Offshore, Coasts & Water | D62: 4 | E62: Feature lead | F62: To review | I62: How can riverbank erosion be assessed and countered to protect irrigation infrastructure and farmland? | J62: tin.skydoor.net | K62: 46320 | L62: Sạt lở sông Krông Nô tại Lâm Đồng đe dọa công trình thủy lợi và đất canh tác | N62: Vietnam | O62: Krong No River, Lam Dong | Q62: Vietnam | R62: 46319 | S62: 2026-Q4 | T62: landslide | U62: 4 | V62: https://news.google.com/rss/articles/CBMihAFBVV95cUxPVlNqT093MU81eURKNm9vZDdtTTNRdkRYZ0J2SXdSeHZqQXV1QUZCbEtiVVplNy1MTGdxbkk1a2hkN0toZ0NPakFvOENXYkRnT2JWQWczUVVLOGpYZ0dtZ1NweXUzb1NxM29TWmhUcUdOVXZfT1dBV3ZuZU5uVXhvaWpXR3Q?oc=5 | W62: =IF($B62="",0,IF(AND(OR(OR(Dashboard!$B$5="All themes",Dashboard!$B$5=""),$C62=Dashboard!$B$5),OR(OR(Dashboard!$G$5="All uses",Dashboard!$G$5=""),$E62=Dashboard!$G$5),N($D62)>=Lists!$H$2,OR(OR(Dashboard!$N$5="All windows",Dashboard!$N$5=""),$S62=Dashboard!$N$5)),1,0)) | X62: =IF($W62=1,N($D62)*1E14+MIN(MAX(N($U62),0),9999)*1E10+MIN(N($K62),99999)*1E5+99999-MIN(ROW(),99999),"")
A63: 60 | B63: Accelerating clean-up work after landslides on Provincial Road 160 along the Chay River. | C63: Hazards & Resilience | D63: 4 | E63: News brief | F63: To review | I63: What slope stabilisation and post-failure assessment methods are suited to repeated landslides along a road built beside a river valley? | J63: Vietnam.vn | K63: 46320 | L63: Agilizar las labores de saneamiento tras los deslizamientos de tierra ocurridos en la carretera provincial 160 a lo largo del río Chay. | N63: Vietnam | O63: Provincial Road 160, Chay River | P63: Provincial Road 160 Chay River landslides, Vietnam (Oct 2026) · Response & recovery · 2 reports | Q63: Spain | R63: 46320 | S63: 2026-Q4 | T63: landslide | U63: 4 | V63: https://news.google.com/rss/articles/CBMiiwFBVV95cUxQTnhUTTY5LUVOY0tLRGhBb1lubjROLVg5c0FETHFDbFdpNFlBNFl6Z1hhTzg2VDZTZVUtdDQxSDdhbENHdnc3bGhBTUVHaHc5R0hEMDdxYlN4QV9vMVBkOTA5czhjYlpsU2gzcEZyTnhPT01pMnVPLTFoSzBJT2E1eHpiamtUSjdhYWxB?oc=5 | W63: =IF($B63="",0,IF(AND(OR(OR(Dashboard!$B$5="All themes",Dashboard!$B$5=""),$C63=Dashboard!$B$5),OR(OR(Dashboard!$G$5="All uses",Dashboard!$G$5=""),$E63=Dashboard!$G$5),N($D63)>=Lists!$H$2,OR(OR(Dashboard!$N$5="All windows",Dashboard!$N$5=""),$S63=Dashboard!$N$5)),1,0)) | X63: =IF($W63=1,N($D63)*1E14+MIN(MAX(N($U63),0),9999)*1E10+MIN(N($K63),99999)*1E5+99999-MIN(ROW(),99999),"")
A64: 61 | B64: Tragedy in Tecate: a worker dies after being buried by an earth slope on 23 October. | C64: Hazards & Resilience | D64: 4 | E64: Feature lead | F64: To review | I64: What failure mechanisms and excavation safety controls would have prevented a worker being buried by an earth slope during construction? | J64: El Congresista | K64: 46320 | L64: Tragedia en Tecate: un trabajador muere tras ser sepultado por un talud de tierra el 23 de octubre. | N64: Mexico | O64: Tecate, Baja California | Q64: Spain | R64: 46320 | S64: 2026-Q4 | T64: retaining wall | U64: 4 | V64: https://news.google.com/rss/articles/CBMikwFBVV95cUxQZF9LM09jNm4yMjFEYUYwRWpsb2pDcVdwZ2hGMU45UGdHcUpNamhkRjhnUzEyM3NNck9TeEhjbXhqWDVTOUxWWTRROWVUdlNPRGI3QzZlM3VxeWcxVUMydjMyS3dnSDVEenFoNXpSQklwdmczQURyZXY5U2JPZV9LUzFwcGZWZkF2MnRpTVZkbHpuWUE?oc=5 | W64: =IF($B64="",0,IF(AND(OR(OR(Dashboard!$B$5="All themes",Dashboard!$B$5=""),$C64=Dashboard!$B$5),OR(OR(Dashboard!$G$5="All uses",Dashboard!$G$5=""),$E64=Dashboard!$G$5),N($D64)>=Lists!$H$2,OR(OR(Dashboard!$N$5="All windows",Dashboard!$N$5=""),$S64=Dashboard!$N$5)),1,0)) | X64: =IF($W64=1,N($D64)*1E14+MIN(MAX(N($U64),0),9999)*1E10+MIN(N($K64),99999)*1E5+99999-MIN(ROW(),99999),"")
A65: 62 | B65: Three homes destroyed after landslide in rural area of Moniquirá. | C65: Hazards & Resilience | D65: 4 | E65: News brief | F65: To review | I65: What triggering conditions and hazard mapping would identify rural slopes at risk of landslides destroying housing? | J65: Noticias Caracol | K65: 46320 | L65: Tres viviendas quedaron destruidas tras deslizamiento en zona rural de Moniquirá | N65: Colombia | O65: Moniquirá, Boyacá | Q65: Mexico | R65: 46318 | S65: 2026-Q4 | T65: landslide | U65: 4 | V65: https://news.google.com/rss/articles/CBMixAFBVV95cUxQVk9lWVVIM3k4YXMxWFczeW5KbU5lUHZJcGdfVkxTTEVnTXlOTC1OczhZcEdyY1VrZVVtYUhQNVU0VDYtUDlIZGkwelZRdEFCM2pBOEZBS0k1dGtxSVAtTnM3ZGJhczlnTy0xeXp0bjV0dDg0WHBLTUJkOXhic1BiY3BhWHM2R0diUXJ6ZzVfaG5wOUp6SXNkRlloYnZiN1l0LWlxSGp0LVlaZEVtUklVYVFQbUk2UjZ4X2FHT0FUQkFIZWxf0gHSAUFVX3lxTE5yanRPUFRBaFRNUmlMYmhrcHJBUm9FcHRiMVpKZllOUlhaVkR6WXFpRjlqb1FkaDNSMzZ1MlZrOTR3cHJVYURvNVZwX1c1a0Ywai1PaUI4b3NILS1XQk5scWFHMU15QzU5SGpDZjJYdWRTOElwdllxNUpuOVk1NEhNb2NTRVJfUTFCWFpubDVscjdDaHEtcURUOV9Sakw0MFB0RjdCdll6bGxCSllPRFZ4emw1Nno1eEo0dnBzdTFUN0ZNd2hGWS1CZFVqRWd3dlJjZw?oc=5 | W65: =IF($B65="",0,IF(AND(OR(OR(Dashboard!$B$5="All themes",Dashboard!$B$5=""),$C65=Dashboard!$B$5),OR(OR(Dashboard!$G$5="All uses",Dashboard!$G$5=""),$E65=Dashboard!$G$5),N($D65)>=Lists!$H$2,OR(OR(Dashboard!$N$5="All windows",Dashboard!$N$5=""),$S65=Dashboard!$N$5)),1,0)) | X65: =IF($W65=1,N($D65)*1E14+MIN(MAX(N($U65),0),9999)*1E10+MIN(N($K65),99999)*1E5+99999-MIN(ROW(),99999),"")
A66: 63 | B66: Large landslide on Tofana di Dentro. No hikers involved. | C66: Hazards & Resilience | D66: 4 | E66: Feature lead | F66: To review | I66: What controls rock slope instability in Dolomite mountains, and how can monitoring reduce risk to hikers from large rockfalls? | J66: Giornale Nord Est | K66: 46320 | L66: Frana di grandi dimensioni sulla Tofana di Dentro. Nessun escursionista coinvolto | N66: Italy | O66: Tofana di Dentro, Dolomites | Q66: Italy | R66: 46319 | S66: 2026-Q4 | T66: landslide | U66: 4 | V66: https://news.google.com/rss/articles/CBMiiAFBVV95cUxQMGVMSVUxdDNvS2xIRTB5RS0tT1RVUEVZUERpNjZLYkVMellJS1lVbnhGZ0NJLUdHOGk4ek5md29MWVJZSGxMYWp4b0lWTmJjQ0h5cV9vRjVsbkpoZ3NtQUxCOWxacDZhVkdHbDBHdG1TeENnZ09PdnF4cVpZLUplbk4tQlVaYUdY?oc=5 | W66: =IF($B66="",0,IF(AND(OR(OR(Dashboard!$B$5="All themes",Dashboard!$B$5=""),$C66=Dashboard!$B$5),OR(OR(Dashboard!$G$5="All uses",Dashboard!$G$5=""),$E66=Dashboard!$G$5),N($D66)>=Lists!$H$2,OR(OR(Dashboard!$N$5="All windows",Dashboard!$N$5=""),$S66=Dashboard!$N$5)),1,0)) | X66: =IF($W66=1,N($D66)*1E14+MIN(MAX(N($U66),0),9999)*1E10+MIN(N($K66),99999)*1E5+99999-MIN(ROW(),99999),"")
A67: 64 | B67: Sicily, from the Niscemi landslide to Cyclone Harry: the Army rewards the Engineer Sappers. | C67: Hazards & Resilience | D67: 4 | E67: Feature lead | F67: To review | I67: What lessons do the Niscemi landslide and Cyclone Harry offer about slope instability and engineering response in Sicily? | J67: StrettoWeb | K67: 46320 | L67: Sicilia, dalla frana di Niscemi al ciclone Harry: l’Esercito premia il Genio Guastatori | N67: Italy | O67: Niscemi, Sicily | P67: Niscemi landslide, Sicily (Jan 2026) · Event · 2 reports | Q67: Italy | R67: 46318 | S67: 2026-Q4 | T67: landslide | U67: 4 | V67: https://news.google.com/rss/articles/CBMizAFBVV95cUxPYnZBdDEtcFlXaXFFRmhkdEgxWXNNZDRKbi1TYVRoSjJUTTJlZlIzckh1amJDM2FuYVAwaDRGbFNnZk84Mm85TngzVlEydEFaNGhCVGJWVjJ1RnBtdUtXM2ZnRWdvMHZmczBoTGRsN0g3QkpIbTE3c3U1NHc5LWJoX2YzNVc3Si1oeExVQi1jS2NlQXBIUlRUQlRDUEJXVGZIQmFVTWlGcVFtMjQ0LVZsLTFIdEpZQ3NKZXhKWGFYVDZwZVpRWDkwUG0xTEnSAcwBQVVfeXFMT2J2QXQxLXBZV2lxRUZoZHRIMVlzTWQ0Sm4tU2FUaEoyVE0yZWZSM3JIdWpiQzNhbmFQMGg0RmxTZ2ZPODJvOU54M1ZRMnRBWjRoQlRiVlYydUZwbXVLVzNmZ0VnbzB2ZnMwaExkbDdIN0JKSG0xN3N1NTR3OS1iaF9mMzVXN0otaHhMVUItY0tjZUFwSFJUVEJUQ1BCV1RmSEJhVU1pRnFRbTI0NC1WbC0xSHRKWUNzSmV4SlhhWFQ2cGVaUVg5MFBtMUxJ?oc=5 | W67: =IF($B67="",0,IF(AND(OR(OR(Dashboard!$B$5="All themes",Dashboard!$B$5=""),$C67=Dashboard!$B$5),OR(OR(Dashboard!$G$5="All uses",Dashboard!$G$5=""),$E67=Dashboard!$G$5),N($D67)>=Lists!$H$2,OR(OR(Dashboard!$N$5="All windows",Dashboard!$N$5=""),$S67=Dashboard!$N$5)),1,0)) | X67: =IF($W67=1,N($D67)*1E14+MIN(MAX(N($U67),0),9999)*1E10+MIN(N($K67),99999)*1E5+99999-MIN(ROW(),99999),"")
A68: 65 | B68: Rapidly advancing clean-up work for landslides on Provincial Road 160 along the Chay River. | C68: Hazards & Resilience | D68: 4 | E68: Watch only | F68: To review | I68: Duplicate of the Chay River road landslide clean-up story; monitor for follow-up on repair methods. | J68: Vietnam.vn | K68: 46320 | L68: チャイ川沿いの州道160号線における土砂崩れの復旧作業を迅速に進める。 | N68: Vietnam | O68: Provincial Road 160, Chay River | P68: Provincial Road 160 Chay River landslides, Vietnam (Oct 2026) · Response & recovery · 2 reports | Q68: Japan | R68: 46320 | S68: 2026-Q4 | T68: landslide | U68: 4 | V68: https://news.google.com/rss/articles/CBMiiwFBVV95cUxQN1M1UUFnNFVScGV6VVBTbjZJSEFHOFpBQzNsNHNJTVhScXFfNGs5dVFkTkRHX2VsN3BtUk5LLWtoeHFGTWRicWtVa2wwOFpnV1o2ZkVqbC03Y09hdWVBdDlrV09PZHRtdG9NdS1DZmp6aWtGaXY1ekxpekVKbzRMa295Q19vSDlCYkk0?oc=5 | W68: =IF($B68="",0,IF(AND(OR(OR(Dashboard!$B$5="All themes",Dashboard!$B$5=""),$C68=Dashboard!$B$5),OR(OR(Dashboard!$G$5="All uses",Dashboard!$G$5=""),$E68=Dashboard!$G$5),N($D68)>=Lists!$H$2,OR(OR(Dashboard!$N$5="All windows",Dashboard!$N$5=""),$S68=Dashboard!$N$5)),1,0)) | X68: =IF($W68=1,N($D68)*1E14+MIN(MAX(N($U68),0),9999)*1E10+MIN(N($K68),99999)*1E5+99999-MIN(ROW(),99999),"")
A69: 66 | B69: Special feature: landslides frequent after Typhoon 25; hidden danger in Chiba's Bōsō Peninsula terrain, 'high valley density'. | C69: Hazards & Resilience | D69: 4 | E69: Feature lead | F69: To review | I69: Why does valley density in the Bōsō Peninsula terrain increase landslide hazard during typhoon rainfall, and how should it be mapped? | J69: Yahoo!ニュース | K69: 46320 | L69: 【特集】台風25号で土砂崩れ多発 千葉・房総半島の地形に潜む危険 「谷密度が高い」 (チバテレ) | N69: Japan | O69: Bōsō Peninsula, Chiba | P69: Typhoon 25 landslides, Bōsō Peninsula, Japan (Oct 2026) · Investigation & inquiry · 2 reports | Q69: Japan | R69: 46318 | S69: 2026-Q4 | T69: landslide | U69: 4 | V69: https://news.google.com/rss/articles/CBMijgFBVV95cUxPejNsdUVrN2NfZVROYjRBSV9BN0lGMU8tRDdVcHRMV1lkamdqQWU0b3JVb0d2aWJIb0haUWlLMVR5MGoxb1VQdXc3OU5IZG9NdGNRclg3QkZCQ2gtQldzRl9RS0J6R3hZYTFzMWpKQTBzd3RLVWdDWVlWRE5rOGRoQnRUbzFCVlU2anlxSG1B?oc=5 | W69: =IF($B69="",0,IF(AND(OR(OR(Dashboard!$B$5="All themes",Dashboard!$B$5=""),$C69=Dashboard!$B$5),OR(OR(Dashboard!$G$5="All uses",Dashboard!$G$5=""),$E69=Dashboard!$G$5),N($D69)>=Lists!$H$2,OR(OR(Dashboard!$N$5="All windows",Dashboard!$N$5=""),$S69=Dashboard!$N$5)),1,0)) | X69: =IF($W69=1,N($D69)*1E14+MIN(MAX(N($U69),0),9999)*1E10+MIN(N($K69),99999)*1E5+99999-MIN(ROW(),99999),"")
A70: 67 | B70: Forestry expert with 20 years' experience: newly found sinkhole in Pong Nha–Ke Bang is a 'difficult problem to solve'. | C70: Hazards & Resilience | D70: 4 | E70: Feature lead | F70: To review | I70: Why are sinkholes in karst or soluble terrain so difficult to resolve, and what investigation methods identify them early? | J70: Vietnam.vn | K70: 46320 | L70: 20년 경력의 산림 전문가: 퐁냐-케방에서 새로 발견된 싱크홀은 "해결하기 어려운 문제"다. | N70: Vietnam | O70: Phong Nha–Ke Bang | P70: Phong Nha-Ke Bang 120 m sinkhole discovery, Vietnam · Update · 4 reports | Q70: South Korea | R70: 46320 | S70: 2026-Q4 | T70: sinkhole | U70: 4 | V70: https://news.google.com/rss/articles/CBMisgFBVV95cUxQN0dPclBLZGZXUXh2c2ZNc1NUTXptSzZPaS15QmlMcFRmcl9BczJRaTItenB2ZW9XM0xUWTBBclBjb1gyWmVJX3BpSlRfZGR6LURsWEZFVTRPVVNTMkJmOGdWS3hPMzN0cUlnMGt1WVB3aERyTWtibHNyV3ZNQmNiY1cyd1pJTXNiX1NrSGdLazMxcTZSaXFZcDEyUVc0MndWYTdmM2VtTUUtdm1BbFAyQVpB?oc=5 | W70: =IF($B70="",0,IF(AND(OR(OR(Dashboard!$B$5="All themes",Dashboard!$B$5=""),$C70=Dashboard!$B$5),OR(OR(Dashboard!$G$5="All uses",Dashboard!$G$5=""),$E70=Dashboard!$G$5),N($D70)>=Lists!$H$2,OR(OR(Dashboard!$N$5="All windows",Dashboard!$N$5=""),$S70=Dashboard!$N$5)),1,0)) | X70: =IF($W70=1,N($D70)*1E14+MIN(MAX(N($U70),0),9999)*1E10+MIN(N($K70),99999)*1E5+99999-MIN(ROW(),99999),"")
A71: 68 | B71: Body of doctor pulled from rubble, residents evacuated after Paya Terubong landslide | C71: Hazards & Resilience | D71: 4 | E71: Feature lead | F71: To review | I71: What triggered the fatal Paya Terubong hillside failure, and how should residential slopes be assessed before evacuation and recovery? | J71: Malay Mail | K71: 46320 | N71: Malaysia | O71: Paya Terubong, Penang | P71: Paya Terubong landslide, Penang, Malaysia (Oct 2026) · Response & recovery · 7 reports | Q71: United Kingdom | R71: 46320 | S71: 2026-Q4 | T71: landslide | U71: 4 | V71: https://news.google.com/rss/articles/CBMi2AFBVV95cUxOaDJwYmR0RlVHc3JzcUNhNTFxNEcyNFNacldnWVhuTUZTcVRVTXdrNFJzNUFqZlRNUXBfaW5YdnFTUTN4cHlUUmdVbGFDT3lBNFRMVUlUYll5QXhHWjd6d0JYUkJKbkstekJpNnhhV1IxMVVxSWQySzNKSFJUZ0RiLThJVmdsY25YTnM3bHFGNG56dG41Wjl4Y2libF9DQkhXNnJCNWtUNWhjRlhtMWF4NHhNWjVrQXVaMmZxd0JqRWNyZGQyT1d6d3VzVEtoS1l4dk1jd3U0VXbSAd4BQVVfeXFMTUxUakFhNFBzWVh5REdLY3A1WlFoS25oTmRoWUtPMWk5YmxfSDAzemx3d0dudllQMFVfYXVFVzlQd2U5MGJLUThRRGlyM2dQYk5kOTBKQXdtTXdMVUhfUDZjZTVOT2ZUX3FYcmRQWDdMNTliMmpQX284c1JVeXBDTHpBQzFubkVRZ1VvVFVIcm9pUGNfYXBUd0NweFllZVJySVpVMWd3Vks4VzJ5aHNLenNGMHplZS1SOVNmVExPR0t4Sk5PdjROV2p2WmhCTE9zOGwxaUFjT2dhTTZBUV93?oc=5 | W71: =IF($B71="",0,IF(AND(OR(OR(Dashboard!$B$5="All themes",Dashboard!$B$5=""),$C71=Dashboard!$B$5),OR(OR(Dashboard!$G$5="All uses",Dashboard!$G$5=""),$E71=Dashboard!$G$5),N($D71)>=Lists!$H$2,OR(OR(Dashboard!$N$5="All windows",Dashboard!$N$5=""),$S71=Dashboard!$N$5)),1,0)) | X71: =IF($W71=1,N($D71)*1E14+MIN(MAX(N($U71),0),9999)*1E10+MIN(N($K71),99999)*1E5+99999-MIN(ROW(),99999),"")
A72: 69 | B72: Penang council halts hillside construction, roadworks after fatal landslide | C72: Hazards & Resilience | D72: 4 | E72: Feature lead | F72: To review | I72: Should hillside development be halted after a fatal landslide, and what slope stability criteria should govern such construction? | J72: The Sun Malaysia | K72: 46320 | N72: Malaysia | O72: Penang hillside | P72: Paya Terubong landslide, Penang, Malaysia (Oct 2026) · Legal & policy · 7 reports | Q72: United Kingdom | R72: 46320 | S72: 2026-Q4 | T72: landslide | U72: 4 | V72: https://news.google.com/rss/articles/CBMinwFBVV95cUxObGc2ZnNTTDk0cTRlMW5fY24wN3B2TS1SZndJUlMwVWR3d2pKbXVVS055T1B6UWZROXZ6bVNIZmQ5R0haMHhtLU50SlJHUHNhR0FJUm1VVGtSTTVDb19VbE11RG9SMk1UTXlWQ19HT3BRbE5wdmQza3d0NHQzRlRLblFGVXBCdGxlNTZQZ21xRnFJSTRjQk1rUFJyYW1fR0E?oc=5 | W72: =IF($B72="",0,IF(AND(OR(OR(Dashboard!$B$5="All themes",Dashboard!$B$5=""),$C72=Dashboard!$B$5),OR(OR(Dashboard!$G$5="All uses",Dashboard!$G$5=""),$E72=Dashboard!$G$5),N($D72)>=Lists!$H$2,OR(OR(Dashboard!$N$5="All windows",Dashboard!$N$5=""),$S72=Dashboard!$N$5)),1,0)) | X72: =IF($W72=1,N($D72)*1E14+MIN(MAX(N($U72),0),9999)*1E10+MIN(N($K72),99999)*1E5+99999-MIN(ROW(),99999),"")
A73: 70 | B73: Rain batters Nilgiris; landslide buries government bus, driver loses life | C73: Hazards & Resilience | D73: 4 | E73: News brief | F73: To review | I73: How can landslide risk on hill-road corridors be managed when a government bus is buried during heavy rain? | J73: The New Indian Express | K73: 46320 | N73: India | O73: Nilgiris, Tamil Nadu | Q73: United Kingdom | R73: 46320 | S73: 2026-Q4 | T73: landslide | U73: 4 | V73: https://news.google.com/rss/articles/CBMi3AFBVV95cUxNNnpWbUlLQnpNS3d1NElEaDNGUmdGUmhzN0w4YVMwYTFDZExnbThRQjZaSnU1MTVOR3JwcU9aeFkza2ZJOFBVOTJXVmYzb09NZ3hoTF9PRjM3dWhuaE4tekRTVjBXYklodEVfTFN2YnA2cUhMZXBpLXFBUjI1SmFoRW9JZHpJeGJTOWNfNjdqMk1hcEUtWW9JZnU3dDNBOWFlUTZUUGpaR0lNWkI5WTlPc05DY2owcnl1SlFEaEIwSU55dWdJSHlZcUNCdkcyTS1pd3FHMGxia1V1aE9X0gHcAUFVX3lxTE02elZtSUtCek1Ld3U0SURoM0ZSZ0ZSaHM3TDhhUzBhMUNkTGdtOFFCNlpKdTUxNU5HcnBxT1p4WTNrZkk4UFU5MldWZjNvT01neGhMX09GMzd1aG5oTi16RFNWMFdiSWh0RV9MU3ZicDZxSExlcGktcUFSMjVKYWhFb0lkekl4YlM5Y182N2oyTWFwRS1Zb0lmdTd0M0E5YWVRNlRQalpHSU1aQjlZOU9zTkNjajByeXVKUURoQjBJTnl1Z0lIeVlxQ0J2RzJNLWl3cUcwbGJrVXVoT1c?oc=5 | W73: =IF($B73="",0,IF(AND(OR(OR(Dashboard!$B$5="All themes",Dashboard!$B$5=""),$C73=Dashboard!$B$5),OR(OR(Dashboard!$G$5="All uses",Dashboard!$G$5=""),$E73=Dashboard!$G$5),N($D73)>=Lists!$H$2,OR(OR(Dashboard!$N$5="All windows",Dashboard!$N$5=""),$S73=Dashboard!$N$5)),1,0)) | X73: =IF($W73=1,N($D73)*1E14+MIN(MAX(N($U73),0),9999)*1E10+MIN(N($K73),99999)*1E5+99999-MIN(ROW(),99999),"")
A74: 71 | B74: [Land disappearing beneath the sea] Double attack of climate-driven sea-level rise and ground subsidence; global lands vanishing from maps. | C74: Offshore, Coasts & Water | D74: 4 | E74: Feature lead | F74: To review | I74: How do sea-level rise and land subsidence combine to lower coastal ground, and what engineering responses can slow the loss of land? | J74: AI넷 | K74: 46320 | L74: [국토가 바닷속으로 사라진다] 기후변화 발 해수면 상승·지반 침하의 이중 습격, 지도에서 지워지는 지구촌 | Q74: South Korea | R74: 46320 | S74: 2026-Q4 | T74: subsidence | U74: 3 | V74: https://news.google.com/rss/articles/CBMiQEFVX3lxTE5xNDZoRUVLVUFyUVB6d3duejJIdUpLZjlKZ21qRXJtLWsycEZCU2RuWWtvblNOVHFJc1JpSW1HMkk?oc=5 | W74: =IF($B74="",0,IF(AND(OR(OR(Dashboard!$B$5="All themes",Dashboard!$B$5=""),$C74=Dashboard!$B$5),OR(OR(Dashboard!$G$5="All uses",Dashboard!$G$5=""),$E74=Dashboard!$G$5),N($D74)>=Lists!$H$2,OR(OR(Dashboard!$N$5="All windows",Dashboard!$N$5=""),$S74=Dashboard!$N$5)),1,0)) | X74: =IF($W74=1,N($D74)*1E14+MIN(MAX(N($U74),0),9999)*1E10+MIN(N($K74),99999)*1E5+99999-MIN(ROW(),99999),"")
A75: 72 | B75: Shield 'Nadezhda' completes tunnelling to future metro stations in Primorsky district | C75: Infrastructure & the Underground City | D75: 4 | E75: News brief | F75: To review | I75: How did the shield tunnelling through the local soils, with groundwater and face-stability conditions, shape the progress of the St Petersburg metro extension? | J75: Piter.tv | K75: 46320 | L75: Щит "Надежда" завершил проходку тоннеля к будущим станциям метро Приморского района | N75: Russia | O75: Primorsky district, St Petersburg | Q75: Russia | R75: 46318 | S75: 2026-Q4 | T75: tunnel, metro line | U75: 2 | V75: https://news.google.com/rss/articles/CBMitAFBVV95cUxOelFNVWZTNzk5YWhMZmZQNVBaOUdDcTVPZ2d6QTVxZVl5aUFjSElxNUw4VXI4dzl3NXY2TDhGNTl4MDlpbS0zcWFvOU8wdU9GRF9MbXJiTWg0NUtHZlNpX3NYZEVsd2JZcDVpSldQUkNjMjZsaUNMeGlYSy1fTmUxYS1FOGdVY2NyWWNFYmlQa2w4YmxwNmtpMlloQ0F1Q01nUFFlcUlSdkxMeUpIZjNYb3pmRHM?oc=5 | W75: =IF($B75="",0,IF(AND(OR(OR(Dashboard!$B$5="All themes",Dashboard!$B$5=""),$C75=Dashboard!$B$5),OR(OR(Dashboard!$G$5="All uses",Dashboard!$G$5=""),$E75=Dashboard!$G$5),N($D75)>=Lists!$H$2,OR(OR(Dashboard!$N$5="All windows",Dashboard!$N$5=""),$S75=Dashboard!$N$5)),1,0)) | X75: =IF($W75=1,N($D75)*1E14+MIN(MAX(N($U75),0),9999)*1E10+MIN(N($K75),99999)*1E5+99999-MIN(ROW(),99999),"")
A76: 73 | B76: Experts comment on the plan to level Mot mountain in Quy Nhon | C76: Infrastructure & the Underground City | D76: 4 | E76: Feature lead | F76: To review | I76: What are the slope stability, rock-cutting and environmental trade-offs in levelling a granite mountain inside an urban area, and how should experts weigh them? | J76: Vietnam.vn | K76: 46320 | L76: Des experts s'expriment sur le projet de rasage du mont Mot à Quy Nhon. | N76: Vietnam | O76: Mot Mountain, Quy Nhon | P76: Mot Mountain levelling proposal, Quy Nhon, Vietnam · Update · 2 reports | Q76: France | R76: 46318 | S76: 2026-Q4 | U76: 0 | V76: https://news.google.com/rss/articles/CBMijwFBVV95cUxNVGtiZ0lmT1lzdnltdVZfN1RsaGl0c3g2Sll0bDJUMHd6UDdFQXN3VlJteWJjTTNHZ1R1TXVJcVBZTl94UDFaczBDUjdObXpScmpZeFZPVkpHRjBUSXFteDJ2dlhFeWxPdVgzamFWaFFRQ1lhSG55VFJKQnRWV1pkNE5TcEs1WWlIT25qbUxVbw?oc=5 | W76: =IF($B76="",0,IF(AND(OR(OR(Dashboard!$B$5="All themes",Dashboard!$B$5=""),$C76=Dashboard!$B$5),OR(OR(Dashboard!$G$5="All uses",Dashboard!$G$5=""),$E76=Dashboard!$G$5),N($D76)>=Lists!$H$2,OR(OR(Dashboard!$N$5="All windows",Dashboard!$N$5=""),$S76=Dashboard!$N$5)),1,0)) | X76: =IF($W76=1,N($D76)*1E14+MIN(MAX(N($U76),0),9999)*1E10+MIN(N($K76),99999)*1E5+99999-MIN(ROW(),99999),"")
A77: 74 | B77: Imperial advances planning of block caving method at Red Chris mine | C77: Infrastructure & the Underground City | D77: 4 | E77: Academia-to-Industry topic | F77: To review | I77: What geomechanical data and rock mass characterisation are needed to plan block caving sequences safely in a large porphyry copper mine? | J77: MarketScreener España | K77: 46320 | L77: Imperial avanza en la planificación del método de hundimiento por bloques en la mina Red Chris | N77: Canada | O77: Red Chris mine | Q77: Argentina | R77: 46318 | S77: 2026-Q4 | U77: 0 | V77: https://news.google.com/rss/articles/CBMi5AFBVV95cUxNRTBGLWpXeXZMNjFSNWFJUXlBSkJ5MVpoamwwUDhYSU9BSzY0dHYxbUxONUxfUTBhLVVoSU5jMjgwQTdKSUsycnVKSzNNYkdkdlNpRWlyVWZrWkxIdm1KYUduYl9lRDd4M04xeURNMTBCd3FRaGpwQnR2UXZscTRaYmU2a3huekdQUEJ1SUZEMWkwZlg1TkkyUFFaLUt3bm9GOGxIZFZEMDFKUVNYcWdTNXNmYjVud3R5UHVlOXBBV3c1cUwtV3FZeGY2NFRTX2ZQclNrNmdXeGlPOEFQcFZ5NW42OFg?oc=5 | W77: =IF($B77="",0,IF(AND(OR(OR(Dashboard!$B$5="All themes",Dashboard!$B$5=""),$C77=Dashboard!$B$5),OR(OR(Dashboard!$G$5="All uses",Dashboard!$G$5=""),$E77=Dashboard!$G$5),N($D77)>=Lists!$H$2,OR(OR(Dashboard!$N$5="All windows",Dashboard!$N$5=""),$S77=Dashboard!$N$5)),1,0)) | X77: =IF($W77=1,N($D77)*1E14+MIN(MAX(N($U77),0),9999)*1E10+MIN(N($K77),99999)*1E5+99999-MIN(ROW(),99999),"")
A78: 75 | B78: SAM demands answers over fatal Penang landslide which killed doctor | C78: Geotechnics & Society | D78: 3 | E78: News brief | F78: To review | I78: What accountability and slope regulation gaps are revealed after a fatal landslide in a hillside urban area? | J78: NST Online | K78: 46320 | N78: Malaysia | O78: Penang | P78: Paya Terubong landslide, Penang, Malaysia (Oct 2026) · Legal & policy · 7 reports | Q78: United Kingdom | R78: 46320 | S78: 2026-Q4 | T78: landslide | U78: 4 | V78: https://news.google.com/rss/articles/CBMiugFBVV95cUxOT2dPd2U1SUVOOTEyc1laYjlVWl9QOUhsTGNrOTNCSFF3LUozTzhWT1RiZHJoejIwdEo5TzRMd3BXNXVON2Y0NUkyejlWTUZ2d3dvQ204NkczQV8zeVVhTFEtalZzM243V3ZXY1dMcDBlaXdZampuWHJrWjRzTUhLRmZENlFvaS1qT2FWRlFjLThUWl9XZklTWWstaTdhY0pFMzM2SDRNSVc0WU5YMnRwU0pOenhWUE10b2fSAb8BQVVfeXFMUHZ6YndId1lQYkVCa3lVeG9seXo5SS03MjlpUy0zYWxNekh4T0FJb2thc1hwV1BCUGxXeXUtZjU4MHg0OE1KTTJXdWNSY3h6Y2J6d1cyejNHNmpiazVyLTFYNGpRUWNCekxRNkVhaGU0LUJGMDNpVklramRteDRYLU9FbWhscm1yWVBBblpYbXpKdEVzN3pWUFg0Q09kM0NHYW1Cd2lYZFIweElSa2lTMnp4NzJBWWlmNlU1eFRoWmM?oc=5 | W78: =IF($B78="",0,IF(AND(OR(OR(Dashboard!$B$5="All themes",Dashboard!$B$5=""),$C78=Dashboard!$B$5),OR(OR(Dashboard!$G$5="All uses",Dashboard!$G$5=""),$E78=Dashboard!$G$5),N($D78)>=Lists!$H$2,OR(OR(Dashboard!$N$5="All windows",Dashboard!$N$5=""),$S78=Dashboard!$N$5)),1,0)) | X78: =IF($W78=1,N($D78)*1E14+MIN(MAX(N($U78),0),9999)*1E10+MIN(N($K78),99999)*1E5+99999-MIN(ROW(),99999),"")
A79: 76 | B79: 'The 1956 Landslide and the Church of San Pietro': photographic exhibition extended | C79: Geotechnics & Society | D79: 3 | E79: Watch only | F79: To review | I79: How did the 1956 landslide shape settlement decisions and church site safety, and what does that history teach about landslide memory? | J79: Trigno.net | K79: 46320 | L79: "La Frana del 1956 e la Chiesa di San Pietro", prorogata la mostra fotografica | N79: Italy | Q79: Italy | R79: 46319 | S79: 2026-Q4 | T79: landslide | U79: 4 | V79: https://news.google.com/rss/articles/CBMivwFBVV95cUxPTWZlVmRYaUZXbGhlRkFNMHdvRXRoSzRlMGUwOWZMWVpIN3p5TzdPZC1JbWZnNlN5ZUxjSkdza2hDYUdPWGpBR05qRTV6dkRVWTVXbGdFc1k5bVlUUEhBMTlZdzZXZFFiM3pNbmx1MjgwNjBsTlRJV2dadlQ1RUpPNTVZa2s5cTBhVXI4Rm1ucy12UWVDWlZIRk1oMHZrWmdWRmRhenp4cFlWQmRfVDFaZHd1Y1BQSjBreVNrZ25aNA?oc=5 | W79: =IF($B79="",0,IF(AND(OR(OR(Dashboard!$B$5="All themes",Dashboard!$B$5=""),$C79=Dashboard!$B$5),OR(OR(Dashboard!$G$5="All uses",Dashboard!$G$5=""),$E79=Dashboard!$G$5),N($D79)>=Lists!$H$2,OR(OR(Dashboard!$N$5="All windows",Dashboard!$N$5=""),$S79=Dashboard!$N$5)),1,0)) | X79: =IF($W79=1,N($D79)*1E14+MIN(MAX(N($U79),0),9999)*1E10+MIN(N($K79),99999)*1E5+99999-MIN(ROW(),99999),"")
A80: 77 | B80: Exploring Phong Nha-Ke Bang’s famous sinkholes | C80: Characterisation & Modelling | D80: 3 | E80: Regional insight | F80: To review | I80: How can karst cave systems and sinkhole susceptibility be mapped and characterised in tropical limestone terrain for tourism and infrastructure? | J80: DTiNews | K80: 46320 | N80: Vietnam | O80: Phong Nha-Ke Bang | Q80: United Kingdom | R80: 46320 | S80: 2026-Q4 | T80: sinkhole | U80: 4 | V80: https://news.google.com/rss/articles/CBMiqwFBVV95cUxPTC1MZGtiV3l3dXRoeE5NZVBwWjdUY1kxOHRrTVMyYTZ1VzVNVXMtbVktb2JVUEVFdnJseGVDaVVrR2tZWXpoT0tMWEZnY2dnZGptUnhfTHJqT1d1M1hoazVuMFZ3aUxZLVhaT2pHN1NBM19ERnF4Z0ZDYVFNZ1BNVmZweTd5ZjhQbGhIdHhXRkNoOW5ycm1TOVhuUUMyTkdmMEFsNzFhUDVqdlk?oc=5 | W80: =IF($B80="",0,IF(AND(OR(OR(Dashboard!$B$5="All themes",Dashboard!$B$5=""),$C80=Dashboard!$B$5),OR(OR(Dashboard!$G$5="All uses",Dashboard!$G$5=""),$E80=Dashboard!$G$5),N($D80)>=Lists!$H$2,OR(OR(Dashboard!$N$5="All windows",Dashboard!$N$5=""),$S80=Dashboard!$N$5)),1,0)) | X80: =IF($W80=1,N($D80)*1E14+MIN(MAX(N($U80),0),9999)*1E10+MIN(N($K80),99999)*1E5+99999-MIN(ROW(),99999),"")
A81: 78 | B81: Dong Thap province spends 330 billion dong to tackle landslide-hit areas | C81: Offshore, Coasts & Water | D81: 3 | E81: Regional insight | F81: To review | I81: How does riverbank failure in the Mekong delta drive the cost and design choice between revetments and managed retreat? | J81: Vietnam.vn | K81: 46320 | L81: La provincia di Dong Thap spende 330 miliardi di dong vietnamiti per affrontare le zone colpite dalle frane. | N81: Vietnam | O81: Dong Thap province | Q81: Italy | R81: 46318 | S81: 2026-Q4 | T81: landslide | U81: 4 | V81: https://news.google.com/rss/articles/CBMifkFVX3lxTE1VN2xaNDhXeTdHWkRoTGZuYXhscnI4SnFCeDFqTVdEWHl1anViQ0hlemlUN1FIN1RaSTl0RjRJUlJ2Y2NmWVZuajROZzdULVVZWTRKV2gyeElnWkZ0MUNILXdPeWEwUlNyMldoZkU4MFJEODZSY3dYYnlFOXZ4dw?oc=5 | W81: =IF($B81="",0,IF(AND(OR(OR(Dashboard!$B$5="All themes",Dashboard!$B$5=""),$C81=Dashboard!$B$5),OR(OR(Dashboard!$G$5="All uses",Dashboard!$G$5=""),$E81=Dashboard!$G$5),N($D81)>=Lists!$H$2,OR(OR(Dashboard!$N$5="All windows",Dashboard!$N$5=""),$S81=Dashboard!$N$5)),1,0)) | X81: =IF($W81=1,N($D81)*1E14+MIN(MAX(N($U81),0),9999)*1E10+MIN(N($K81),99999)*1E5+99999-MIN(ROW(),99999),"")
A82: 79 | B82: Un socavón en Cerro se llena de agua y amenaza a peatones y conductores tras las lluvias | C82: Infrastructure & the Underground City | D82: 3 | E82: News brief | F82: To review | I82: What causes water-filled sinkholes to form in urban ground after rainfall, and how should pedestrian and traffic exclusion zones be set? | J82: Infobae | K82: 46320 | O82: Cerro | Q82: Colombia | R82: 46319 | S82: 2026-Q4 | T82: sinkhole | U82: 4 | V82: https://news.google.com/rss/articles/CBMiyAFBVV95cUxQS0RIdEFTRXdlQUh1YkZCTkpIT01XcmNPQ0xlbDl0NjlDYTFqLVItd2J6ZFhqcjBEM2EyOHlodlBuLVU2MkZmcGgxZWN6MzFKN0VPYmc5Z3I1eHJVcS1JbTNtd1h0UGp0YUFHT1dybTdVRVMwQUE4R2htSExDNW9VZmd5SHVZbVFsMHdWNXFrelJ0ZVlLSEgxdlJDN3ZVeTFFcDVqcEVMWkt4czJpUG5jdFJvMTQ3TVcxLUx2Q0cyUlNSWUdKUjVHRtIB4wFBVV95cUxQeGRmeTUwQmI1dzkwNWtLT2p1WDZmSVFXcjJPS3Z5SGVSZVNIaHRxNFJ4RVl4cUJndGRfZDlKaVFkR2lhRHkyQUNMU1hROElpUm1ib241ek1BeWU1OGE2ZWZGUXlhMnQ1UE5uc0ZHTGh3SFNpcUF5dEp4aEVxSkd0MWpid2xQT1JhbkUxZjFIbk5mT0xjQTVRMTd4aTEyUmFiYWhCVlQzVDV6b3Ywb1NyTmtEMGRxUF9TUWhaT1lQWUFMX0pDNVhvbEFpYnBkM1B6OFN2MHg1Vm1kREZFeE9QTFVYWQ?oc=5 | W82: =IF($B82="",0,IF(AND(OR(OR(Dashboard!$B$5="All themes",Dashboard!$B$5=""),$C82=Dashboard!$B$5),OR(OR(Dashboard!$G$5="All uses",Dashboard!$G$5=""),$E82=Dashboard!$G$5),N($D82)>=Lists!$H$2,OR(OR(Dashboard!$N$5="All windows",Dashboard!$N$5=""),$S82=Dashboard!$N$5)),1,0)) | X82: =IF($W82=1,N($D82)*1E14+MIN(MAX(N($U82),0),9999)*1E10+MIN(N($K82),99999)*1E5+99999-MIN(ROW(),99999),"")
A83: 80 | B83: A sinkhole trapped an ambulance transporting a patient | C83: Infrastructure & the Underground City | D83: 3 | E83: News brief | F83: To review | I83: What ground investigation is needed to explain sudden road sinkholes that trap emergency vehicles on mountain-road pavements? | J83: Diario 7 lagos | K83: 46320 | L83: Un socavón dejó atrapada a una ambulancia que trasladaba a una paciente | N83: Argentina | O83: Siete Lagos, Patagonia | P83: Aucapán road sinkhole traps ambulance, Argentina (Oct 2026) · Event · 2 reports | Q83: Colombia | R83: 46319 | S83: 2026-Q4 | T83: sinkhole | U83: 4 | V83: https://news.google.com/rss/articles/CBMiyAFBVV95cUxOMklFazYzYnQwVFVUTnprTDNRMUVqZGFyYTJBUlMzbDl0anAwWFpCY2dob0xPOC1VVjFIRUxxUllFbmdhUE9RWWxheC1ocWlCaDdzdHBXMnNBaXZrRWZNVFJhend0aEYxbTJqTzRnTFV1SldRM0loQm5xVklCc3E3eVZxbVR4YWd3QldWVDdOU3ZJdDZNcWc5SDJLc2o2TTBacW9sOTdLMGpuS3Z6RUlVd2hnVF9YLTVHNUR4Z0VfVG5QNGY0TUgya9IBzgFBVV95cUxOSmZUVEtyNnhYMHJBYU9IbWVRd3o4MGZxN1lCd3FjbF9JaXJlbnJscmtXaXJQMl9HOHJoNG1SY3N0NU94dW05c21ZbVJjcGFrbTlHdldjWURQSG9FcDBwdmU2d2traG9uZVc0UEs1eERrQ1ZnR25xRVIwN3RvM21SU2E5MVRYeUlPYnJIcEE5aEQyZU1GV0xYeXF3SklreExfNVRxVnRSaWN3MTNRYURBOVVFNU45bGhybFJiWDFGYmxWVm5Ub3lHM2h0TUc1Zw?oc=5 | W83: =IF($B83="",0,IF(AND(OR(OR(Dashboard!$B$5="All themes",Dashboard!$B$5=""),$C83=Dashboard!$B$5),OR(OR(Dashboard!$G$5="All uses",Dashboard!$G$5=""),$E83=Dashboard!$G$5),N($D83)>=Lists!$H$2,OR(OR(Dashboard!$N$5="All windows",Dashboard!$N$5=""),$S83=Dashboard!$N$5)),1,0)) | X83: =IF($W83=1,N($D83)*1E14+MIN(MAX(N($U83),0),9999)*1E10+MIN(N($K83),99999)*1E5+99999-MIN(ROW(),99999),"")
A84: 81 | B84: Sinkhole endangers motorists and pedestrians in the 21 de Marzo neighbourhood | C84: Infrastructure & the Underground City | D84: 3 | E84: News brief | F84: To review | I84: What are the likely causes of urban road sinkholes, such as leaking pipes or subsurface erosion, and how should they be detected early? | J84: El Sol de México | K84: 46320 | L84: Socavón pone en riesgo a automovilistas y peatones en la colonia 21 de Marzo | N84: Mexico | O84: Colonia 21 de Marzo | Q84: Colombia | R84: 46320 | S84: 2026-Q4 | T84: sinkhole | U84: 4 | V84: https://news.google.com/rss/articles/CBMiwwFBVV95cUxPNURGNTBXWEl0UmFPYlFOdHJNSUpoZGliNFdlOUdYT1BqUGo3NmNXUXNzNEd1ZGdHdzZNZkFYMGV0S2RETlV0aEFCNzE0cVFDN2cxYTNvMkFzZkJjZWoxSFhVT25USUU4VkJNM0Vma0pXdFRlUzhDUl9nSmNpaFpxTGlMX3ltbU9yQjUtVk1pMmJMUldmN2lmWHRQZW0xa2I3T1JaTVRyd3NHUE9VbUg3UDhkWDZmdUJDS3BiNU5hUHZHSFE?oc=5 | W84: =IF($B84="",0,IF(AND(OR(OR(Dashboard!$B$5="All themes",Dashboard!$B$5=""),$C84=Dashboard!$B$5),OR(OR(Dashboard!$G$5="All uses",Dashboard!$G$5=""),$E84=Dashboard!$G$5),N($D84)>=Lists!$H$2,OR(OR(Dashboard!$N$5="All windows",Dashboard!$N$5=""),$S84=Dashboard!$N$5)),1,0)) | X84: =IF($W84=1,N($D84)*1E14+MIN(MAX(N($U84),0),9999)*1E10+MIN(N($K84),99999)*1E5+99999-MIN(ROW(),99999),"")
A85: 82 | B85: Government abandons community with an enormous sinkhole | C85: Infrastructure & the Underground City | D85: 3 | E85: Watch only | F85: To review | I85: Large community sinkhole left without official remediation; the geotechnical cause and responsibility for investigation remain open. | J85: emsavalles.com | K85: 46320 | L85: Gobierno abandona comunidad con un enorme socavón | Q85: Colombia | R85: 46319 | S85: 2026-Q4 | T85: sinkhole | U85: 4 | V85: https://news.google.com/rss/articles/CBMiiAFBVV95cUxOM3hmcTdXVUJhd1hTblR3RXJ5ZzRQbm80a1dYa21RTlo0T1VmWVUwN1htemlUYnlUbWlxcFZzbjZsQWo2UzZsbGozVHNXRG1MNndqdkJRb1BSVW1GcWFQd1BNdzF0NWNJZGxpWGF0Q3hGNkl3R3E2QnhidTZ1SElMUDFFMm9Ib1lf?oc=5 | W85: =IF($B85="",0,IF(AND(OR(OR(Dashboard!$B$5="All themes",Dashboard!$B$5=""),$C85=Dashboard!$B$5),OR(OR(Dashboard!$G$5="All uses",Dashboard!$G$5=""),$E85=Dashboard!$G$5),N($D85)>=Lists!$H$2,OR(OR(Dashboard!$N$5="All windows",Dashboard!$N$5=""),$S85=Dashboard!$N$5)),1,0)) | X85: =IF($W85=1,N($D85)*1E14+MIN(MAX(N($U85),0),9999)*1E10+MIN(N($K85),99999)*1E5+99999-MIN(ROW(),99999),"")
A86: 83 | B86: Sinkhole repair will close Route 241 in Lebanon County for a week | C86: Infrastructure & the Underground City | D86: 3 | E86: News brief | F86: To review | I86: What causes sinkholes under pavement in karst or mined ground, and which investigation methods would have identified the void before the road failed? | J86: ABC27 | K86: 46320 | N86: United States | O86: Route 241, Lebanon County | Q86: United Kingdom | R86: 46319 | S86: 2026-Q4 | T86: sinkhole | U86: 4 | V86: https://news.google.com/rss/articles/CBMiowFBVV95cUxPSW16TFNndGdxVGNIaVpybmFPR0ZITXoybEsyX2hJM0czSzdzZmRhSjJkS0MwQzdpXzhEa0VsT0dGQi1oTGFjZ01BLVBMcHRUeHVybVdyT0phb0hKRUpobGJKZjBOQmpEbW5Wb0hib2RST0gxZDlmSlRlbE5VNlZmYmxFV2FnVXVpaHhyOVJHNUZLX2tnZ2JxcXljNU1iU3FJSlJJ0gGoAUFVX3lxTE1mMVVBRWZBamF4Y2NEQVBJZFNVTUZDcDkwTERtZllWT29ZQm50T3owSHU4U0s3elcwQnVBaFdvTjdnWGV4UmJxSVoxdWU1TnZQUkhoS2pDSnJmUS1wTWFGYUdmRElaQzV5bUltT040dTk5LU8yRTJLdlVIdUg2LVg3eFc4OUFtNXNBUFF3UzYtTmFBalA5QW1MNFdIZnRpSGRIb0s0WGpHag?oc=5 | W86: =IF($B86="",0,IF(AND(OR(OR(Dashboard!$B$5="All themes",Dashboard!$B$5=""),$C86=Dashboard!$B$5),OR(OR(Dashboard!$G$5="All uses",Dashboard!$G$5=""),$E86=Dashboard!$G$5),N($D86)>=Lists!$H$2,OR(OR(Dashboard!$N$5="All windows",Dashboard!$N$5=""),$S86=Dashboard!$N$5)),1,0)) | X86: =IF($W86=1,N($D86)*1E14+MIN(MAX(N($U86),0),9999)*1E10+MIN(N($K86),99999)*1E5+99999-MIN(ROW(),99999),"")
A87: 84 | B87: TBMs to be produced under Aatmanirbhar Bharat, says Ashwini Vaishnaw | C87: Infrastructure & the Underground City | D87: 3 | E87: News brief | F87: To review | I87: How does local manufacturing of tunnel boring machines affect the technical adaptation of TBMs to varied ground conditions in India's tunnelling projects? | J87: The Hindu | K87: 46320 | N87: India | Q87: United Kingdom | R87: 46318 | S87: 2026-Q4 | T87: tbm | U87: 3 | V87: https://news.google.com/rss/articles/CBMi0wFBVV95cUxOc1QyY1hjNjZvMUFScExlUUNDdjdqVHF1VExXUjlHR3BndTludGR6Y1dPTm9rRkVDdGlsY1hDX0RNYnRNblphYkpFdU5yV2IwMU0yRjhIMUdRMlg5YlRpdE95a08tTDM0aHFVZmtYcFdfbU9ORGc3NnBSWndCTFEtWFVVajlxc0N1ZEpnNDFuMWhwc2dTTEZ6cVI1OFlzOGhBY1hOcUt2Q3BHV1dyLWEtM29TWmRyakRUdVRCUEZzZXNJN0lKZGJ2bmg1amdON1BGdXZn0gHTAUFVX3lxTE5zVDJjWGM2Nm8xQVJwTGVRQ0N2N2pUcXVUTFdSOUdHcGd1OW50ZHpjV09Ob2tGRUN0aWxjWENfRE1idE1uWmFiSkV1TnJXYjAxTTJGOEgxR1EyWDliVGl0T3lrTy1MMzRocVVma1hwV19tT05EZzc2cFJad0JMUS1YVVVqOXFzQ3VkSmc0MW4xaHBzZ1NMRnpxUjU4WXM4aEFjWE5xS3ZDcEdXV3ItYS0zb1NaZHJqRFR1VEJQRnNlc0k3SUpkYnZuaDVqZ043UEZ1dmc?oc=5 | W87: =IF($B87="",0,IF(AND(OR(OR(Dashboard!$B$5="All themes",Dashboard!$B$5=""),$C87=Dashboard!$B$5),OR(OR(Dashboard!$G$5="All uses",Dashboard!$G$5=""),$E87=Dashboard!$G$5),N($D87)>=Lists!$H$2,OR(OR(Dashboard!$N$5="All windows",Dashboard!$N$5=""),$S87=Dashboard!$N$5)),1,0)) | X87: =IF($W87=1,N($D87)*1E14+MIN(MAX(N($U87),0),9999)*1E10+MIN(N($K87),99999)*1E5+99999-MIN(ROW(),99999),"")
A88: 85 | B88: A section of the Esquina waterfront promenade closed due to subsidence | C88: Offshore, Coasts & Water | D88: 3 | E88: News brief | F88: To review | I88: What causes subsidence along a riverfront promenade, and what ground investigation would identify the weak or eroded soils behind it? | J88: Diario 1588 | K88: 46320 | L88: Cerraron un sector de la costanera de Esquina por hundimiento | N88: Argentina | O88: Esquina costanera | P88: Esquina riverfront promenade subsidence, Argentina (Oct 2026) · Event · 2 reports | Q88: Argentina | R88: 46317 | S88: 2026-Q4 | U88: 0 | V88: https://news.google.com/rss/articles/CBMiR0FVX3lxTE5mbFg4a3ZhOWpyZElUSEpyVUR4NllITUlLeGFWV1B2V2JUQng0WUltSk9ENGNmQk1EWVdhM0tjejVqWjJvb0tF0gFHQVVfeXFMTmZsWDhrdmE5anJkSVRISnJVRHg2WUhNSUt4YVZXUHZXYlRCeDRZSW1KT0Q0Y2ZCTURZV2EzS2N6NWpaMm9vS0U?oc=5 | W88: =IF($B88="",0,IF(AND(OR(OR(Dashboard!$B$5="All themes",Dashboard!$B$5=""),$C88=Dashboard!$B$5),OR(OR(Dashboard!$G$5="All uses",Dashboard!$G$5=""),$E88=Dashboard!$G$5),N($D88)>=Lists!$H$2,OR(OR(Dashboard!$N$5="All windows",Dashboard!$N$5=""),$S88=Dashboard!$N$5)),1,0)) | X88: =IF($W88=1,N($D88)*1E14+MIN(MAX(N($U88),0),9999)*1E10+MIN(N($K88),99999)*1E5+99999-MIN(ROW(),99999),"")
A89: 86 | B89: Experts from Hong Kong propose solutions to counter sea-level rise in Vietnam | C89: Offshore, Coasts & Water | D89: 3 | E89: Regional insight | F89: To review | I89: Which ground-engineering measures, such as seawalls and soft-soil improvement, best protect low-lying deltas and coasts facing sea-level rise and subsidence? | J89: Vietnam.vn | K89: 46320 | L89: 来自中国香港的专家为应对越南海平面上升提出了解决方案。 | N89: Vietnam | O89: Vietnam coast | Q89: China | R89: 46319 | S89: 2026-Q4 | U89: 0 | V89: https://news.google.com/rss/articles/CBMiugFBVV95cUxORExmLUpkcGVQbHNvYWduSVhobDZrLW9DNlotVWVaUDgtNlRqcnluTmU3eE45QVRyXzhsYU90U1VlbVl2bnBNUVRyb3IwVUJmS0VZcEhjWHdsM183TldTbmZPTDRyVlI0R1kzUW5mNUVxc0M5MzgzaUdpX0g2WEpmNTcyQmh6V1FTbDVLaDNIdTRuUV9lc3VNR0dvbWM3OTRaSlFlc2FYY0ZMSUZnUkhwOEdqa3RkaktlcFE?oc=5 | W89: =IF($B89="",0,IF(AND(OR(OR(Dashboard!$B$5="All themes",Dashboard!$B$5=""),$C89=Dashboard!$B$5),OR(OR(Dashboard!$G$5="All uses",Dashboard!$G$5=""),$E89=Dashboard!$G$5),N($D89)>=Lists!$H$2,OR(OR(Dashboard!$N$5="All windows",Dashboard!$N$5=""),$S89=Dashboard!$N$5)),1,0)) | X89: =IF($W89=1,N($D89)*1E14+MIN(MAX(N($U89),0),9999)*1E10+MIN(N($K89),99999)*1E5+99999-MIN(ROW(),99999),"")
A90: 87 | B90: Paving train rehabilitated Prolongación Moctezuma, but a sinkhole remained in front of a private road and vehicles block sidewalks | C90: Infrastructure & the Underground City | D90: 3 | E90: News brief | F90: To review | I90: Why did the newly paved street develop a subsidence in front of a private road, and how could trench backfill and compaction have prevented it? | J90: El Portal de Chicoloapan | K90: 46320 | L90: Con el tren de pavimentación rehabilitaron Prolongación Moctezuma, sin embargo quedó un hundimiento frente a la privada y vehículos bloqueando las banquetas | N90: Mexico | O90: Prolongación Moctezuma, Chicoloapan | Q90: Argentina | R90: 46320 | S90: 2026-Q4 | U90: 0 | V90: https://news.google.com/rss/articles/CBMirAJBVV95cUxOMjNzZzJPUUlBTEF6Nmoyakl5Rl9Jc1YwT3h4RW12LVB3cnBYcW1kS2RELXV3MkM4NFctRnBDWjF2WXdOMTVwYUtndVVsRjl0N1BPcEdndkw1dFhFTlZpOWI5MHRsaDZUY25iMkVqLWYwNVpNRzRWenNLeFQ5X2U3QjQweVRpdDlXQlVyZTZicTktQVYwMF92VEI3ZW9PUFZXWEllOVFHa1g2OHhoSzlVdmgtN1Y4dkczVlVnc1FndUpsOG1ybjZpZzlCNkxVNjlUaHdsbVNQMWhVRjhQbFZuRGxkZGZYWGxrX1NYaFVnc1otYVdIaDUxQXlGSEdpMFFWR2JjOFJLZXJsNk9wZDZnekdueFBFSllaWlF6Zy1mVWpONXEyVW1YWjNGZkU?oc=5 | W90: =IF($B90="",0,IF(AND(OR(OR(Dashboard!$B$5="All themes",Dashboard!$B$5=""),$C90=Dashboard!$B$5),OR(OR(Dashboard!$G$5="All uses",Dashboard!$G$5=""),$E90=Dashboard!$G$5),N($D90)>=Lists!$H$2,OR(OR(Dashboard!$N$5="All windows",Dashboard!$N$5=""),$S90=Dashboard!$N$5)),1,0)) | X90: =IF($W90=1,N($D90)*1E14+MIN(MAX(N($U90),0),9999)*1E10+MIN(N($K90),99999)*1E5+99999-MIN(ROW(),99999),"")
A91: 88 | B91: Experts comment on the plan to level Mot Mountain in Quy Nhon | C91: Infrastructure & the Underground City | D91: 3 | E91: Feature lead | F91: To review | I91: What geotechnical challenges arise in levelling a hill in Quy Nhon, including slope stability, cut volumes, and the reuse of excavated soil? | J91: Vietnam.vn | K91: 46320 | L91: 전문가들이 꾸이년의 못산을 평탄화하려는 계획에 대해 의견을 밝혔다. | N91: Vietnam | O91: Quy Nhon, Binh Dinh | P91: Mot Mountain levelling proposal, Quy Nhon, Vietnam · Update · 2 reports | Q91: South Korea | R91: 46318 | S91: 2026-Q4 | U91: 0 | V91: https://news.google.com/rss/articles/CBMijwFBVV95cUxOVjhkZVg1Qms4dWZyT3MxQ2FrSmFPVE1Vak9PNnEwS1RjOTl5dHAxQkZ5WWZkTFlKdHV3U256bU9tZ2syWGFaSnM3YklHNnV2aWVoa1p3SFpnMFBMN1NEVFlVd2laNlhROVh6NFBzX1hxQklRRGk2dGJ3SWhyS2RKYVFOdDRRaHFkR2hueEJqRQ?oc=5 | W91: =IF($B91="",0,IF(AND(OR(OR(Dashboard!$B$5="All themes",Dashboard!$B$5=""),$C91=Dashboard!$B$5),OR(OR(Dashboard!$G$5="All uses",Dashboard!$G$5=""),$E91=Dashboard!$G$5),N($D91)>=Lists!$H$2,OR(OR(Dashboard!$N$5="All windows",Dashboard!$N$5=""),$S91=Dashboard!$N$5)),1,0)) | X91: =IF($W91=1,N($D91)*1E14+MIN(MAX(N($U91),0),9999)*1E10+MIN(N($K91),99999)*1E5+99999-MIN(ROW(),99999),"")
A92: 89 | B92: Voronezh replaces another six metres of damaged collector on Moskovsky Avenue | C92: Infrastructure & the Underground City | D92: 3 | E92: News brief | F92: To review | I92: How do ground movements or soil conditions around urban collector pipes cause damage, and what should guide repair and reinstatement works? | J92: Новости Воронежа интернет-газета | K92: 46320 | L92: В Воронеже заменили еще шесть метров поврежденного коллектора на Московском проспекте | N92: Russia | O92: Moskovsky Avenue, Voronezh | P92: Voronezh Moskovsky Avenue collector repair, Russia · Event · 2 reports | Q92: Russia | R92: 46319 | S92: 2026-Q4 | U92: 0 | V92: https://news.google.com/rss/articles/CBMiWEFVX3lxTE43cWdqNnRTM1lrNU1sbElSd09YdDFzdGJhdFBFdldKb3V6R2taUV9IbUtjM3ZUUm5jNkU0QnJvcGdMTUVfR3k4UVNGeTRER2oycE1fZEFGeXE?oc=5 | W92: =IF($B92="",0,IF(AND(OR(OR(Dashboard!$B$5="All themes",Dashboard!$B$5=""),$C92=Dashboard!$B$5),OR(OR(Dashboard!$G$5="All uses",Dashboard!$G$5=""),$E92=Dashboard!$G$5),N($D92)>=Lists!$H$2,OR(OR(Dashboard!$N$5="All windows",Dashboard!$N$5=""),$S92=Dashboard!$N$5)),1,0)) | X92: =IF($W92=1,N($D92)*1E14+MIN(MAX(N($U92),0),9999)*1E10+MIN(N($K92),99999)*1E5+99999-MIN(ROW(),99999),"")
A93: 90 | B93: Experts weigh in on proposal to level Mot Mountain in Quy Nhon | C93: Infrastructure & the Underground City | D93: 3 | E93: Regional insight | F93: To review | I93: How can slope stability, rock cutting and geohazard risks be assessed when a coastal hill is proposed for levelling in an urban area? | J93: Vietnam.vn | K93: 46320 | L93: Para ahli angkat bicara tentang usulan untuk meratakan Gunung Mot di Quy Nhon. | N93: Vietnam | O93: Mot Mountain, Quy Nhon | P93: Mot Mountain levelling proposal, Quy Nhon, Vietnam · Event · 2 reports | Q93: Indonesia | R93: 46319 | S93: 2026-Q4 | U93: 0 | V93: https://news.google.com/rss/articles/CBMijwFBVV95cUxQbVc4RlhHZWJTeHV3YlBWTjYzSURERHpMLTJuWHUwU3lpdWdvcS04WlZBYUNwY01aNEVkQmJpZzBqYXhQRXlTWEVpMHlPcUhjb3lvM3h1YWhNQXVJSWhqTEFYVmRkMGpmRTlkN0FPRW5SZzM1YW4xVXRmMVFpYzlkMk5YMUhabnk2eURnN0NJNA?oc=5 | W93: =IF($B93="",0,IF(AND(OR(OR(Dashboard!$B$5="All themes",Dashboard!$B$5=""),$C93=Dashboard!$B$5),OR(OR(Dashboard!$G$5="All uses",Dashboard!$G$5=""),$E93=Dashboard!$G$5),N($D93)>=Lists!$H$2,OR(OR(Dashboard!$N$5="All windows",Dashboard!$N$5=""),$S93=Dashboard!$N$5)),1,0)) | X93: =IF($W93=1,N($D93)*1E14+MIN(MAX(N($U93),0),9999)*1E10+MIN(N($K93),99999)*1E5+99999-MIN(ROW(),99999),"")
A94: 91 | B94: Behavior of Square-Round Shaft Combination Helical Piles and Anchors | C94: Ground Improvement & Innovation | D94: 5 | E94: Academia-to-Industry topic | F94: To review | I94: How do square-round shaft combination helical piles and anchors behave under load, and how can their capacity be predicted reliably? | J94: Geoengineer.org | K94: 46319 | Q94: United States | R94: 46318 | S94: 2026-Q4 | T94: pile, shaft | U94: 7 | V94: https://news.google.com/rss/articles/CBMiowFBVV95cUxNbDZHMUZRd0NyUDliQlNXWEZ4bUdaWFJJbk1NRHZIdUlpRzFObmV2bzBkUVpKbzhuUmkxZHI1U0JENHktOGIxOGlvbEtwS3RScWJ0SWhGR0gtNU9lWWNSc1RoMmtsWjJIT3F2ZzByazhRVUViN2FLa3RqSGt5VkxKZUM3WjdrT2NGc2tYeWJWQmR2RmxEZzlYUmczNFBjMlpXVVNB?oc=5 | W94: =IF($B94="",0,IF(AND(OR(OR(Dashboard!$B$5="All themes",Dashboard!$B$5=""),$C94=Dashboard!$B$5),OR(OR(Dashboard!$G$5="All uses",Dashboard!$G$5=""),$E94=Dashboard!$G$5),N($D94)>=Lists!$H$2,OR(OR(Dashboard!$N$5="All windows",Dashboard!$N$5=""),$S94=Dashboard!$N$5)),1,0)) | X94: =IF($W94=1,N($D94)*1E14+MIN(MAX(N($U94),0),9999)*1E10+MIN(N($K94),99999)*1E5+99999-MIN(ROW(),99999),"")
A95: 92 | B95: Floating wind needs grounded solutions | C95: Offshore, Coasts & Water | D95: 5 | E95: Feature lead | F95: To review | I95: What geotechnical challenges arise in anchoring floating offshore wind foundations in variable seabed soils under extreme loading? | J95: Ground Engineering | K95: 46319 | R95: 46318 | S95: 2026-Q4 | T95: offshore wind | U95: 6 | V95: https://www.geplus.co.uk/key-topics/sustainability/floating-wind-needs-grounded-solutions-23-10-2026/ | W95: =IF($B95="",0,IF(AND(OR(OR(Dashboard!$B$5="All themes",Dashboard!$B$5=""),$C95=Dashboard!$B$5),OR(OR(Dashboard!$G$5="All uses",Dashboard!$G$5=""),$E95=Dashboard!$G$5),N($D95)>=Lists!$H$2,OR(OR(Dashboard!$N$5="All windows",Dashboard!$N$5=""),$S95=Dashboard!$N$5)),1,0)) | X95: =IF($W95=1,N($D95)*1E14+MIN(MAX(N($U95),0),9999)*1E10+MIN(N($K95),99999)*1E5+99999-MIN(ROW(),99999),"")
A96: 93 | B96: Sinkhole at excavation site: ground sank even after underground safety assessment | C96: Infrastructure & the Underground City | D96: 5 | E96: Feature lead | F96: To review | I96: Why did ground sink at an excavation despite a completed underground safety assessment, and what gaps exist in such assessments? | J96: 충청신문 | K96: 46319 | L96: 장종태, "굴착 현장 싱크홀...지하안전평가 받고도 땅 꺼졌다" | N96: South Korea | Q96: South Korea | R96: 46317 | S96: 2026-Q4 | T96: sinkhole, excavation | U96: 6 | V96: https://news.google.com/rss/articles/CBMibkFVX3lxTE9HOUMyWW5vRXVWOG5ZemlXOFFsQWYwVl9lRW53VTV1MVFFQUF4eGgwWTRKQ0p5RGlWLUgzdUNUSW9aQXRRMkduTGFBVmhOVWluT19OLXU5REgzMVdVOUwtTVRmY3Y5WGdwaE9RcG9B0gFuQVVfeXFMT0c5QzJZbm9FdVY4bll6aVc4UWxBZjBWX2VFbndVNXUxUUVBQXh4aDBZNEpDSnlEaVYtSDN1Q1RJb1pBdFEyR25MYUFWaE5VaW5PX04tdTlESDMxV1U5TC1NVGZjdjlYZ3BoT1Fwb0E?oc=5 | W96: =IF($B96="",0,IF(AND(OR(OR(Dashboard!$B$5="All themes",Dashboard!$B$5=""),$C96=Dashboard!$B$5),OR(OR(Dashboard!$G$5="All uses",Dashboard!$G$5=""),$E96=Dashboard!$G$5),N($D96)>=Lists!$H$2,OR(OR(Dashboard!$N$5="All windows",Dashboard!$N$5=""),$S96=Dashboard!$N$5)),1,0)) | X96: =IF($W96=1,N($D96)*1E14+MIN(MAX(N($U96),0),9999)*1E10+MIN(N($K96),99999)*1E5+99999-MIN(ROW(),99999),"")
A97: 94 | B97: Mussolini's engineers drilled 361 holes under Pisa's foundations in 1934 to straighten it, making it lean more. | C97: Ground Improvement & Innovation | D97: 5 | E97: Feature lead | F97: To review | I97: Why did drilling holes beneath Pisa's foundations to correct its tilt backfire, and what does this teach about controlled soil removal and differential settlement in stabilisation works? | J97: Sciencepost | K97: 46319 | L97: En perçant 361 trous dans ses fondations en 1934 pour la redresser, les ingénieurs de Mussolini ont littéralement fait pencher la tour de Pise encore plus | N97: Italy | O97: Pisa | Q97: Senegal | R97: 46319 | S97: 2026-Q4 | T97: foundation | U97: 2 | V97: https://news.google.com/rss/articles/CBMiiAJBVV95cUxPQkl0dnN1WVR0endSWTZuYVpjZTBnV2VWTnVTVjdyb1NJTlFKVjJWY21lS0dPZzFrSkdlSlI2VU5Cc1NMQ0VHNTlPWUFkSVRZWEhWbFRxaU91bXRRMTF6LW9kYWVKSHFBOUptTVZuTGdTX1lZYzBDQkZ5QTJGUmVXcVd3c3lmU01zM3Zjd1VmZ183aFkxOERqQWJHbVlqMU5EbzBRSWpHRjNMeFVHRXlVSURpZHFnRXZIX1Q0X3RSMW8zcVZKVFZoOWViVlYzVnNWZloxTW5LNThJTWV2bURLSjJ1eEZiRFhnd2phLVVjUV9mdHVjN0Q0dE93WE9wRVR1ZlFFTE8tNnk?oc=5 | W97: =IF($B97="",0,IF(AND(OR(OR(Dashboard!$B$5="All themes",Dashboard!$B$5=""),$C97=Dashboard!$B$5),OR(OR(Dashboard!$G$5="All uses",Dashboard!$G$5=""),$E97=Dashboard!$G$5),N($D97)>=Lists!$H$2,OR(OR(Dashboard!$N$5="All windows",Dashboard!$N$5=""),$S97=Dashboard!$N$5)),1,0)) | X97: =IF($W97=1,N($D97)*1E14+MIN(MAX(N($U97),0),9999)*1E10+MIN(N($K97),99999)*1E5+99999-MIN(ROW(),99999),"")
A98: 95 | B98: Serious landslides in South Gia Nghia | C98: Hazards & Resilience | D98: 5 | E98: Feature lead | F98: To review | I98: What rainfall and slope geometry triggered this serious landslide in Nam Gia Nghia, and how should weathered residual soils on such slopes be investigated and stabilised? | J98: Vietnam.vn | K98: 46319 | L98: Sụt trượt đất nghiêm trọng ở Nam Gia Nghĩa | N98: Vietnam | O98: Nam Gia Nghia, Dak Nong | Q98: Vietnam | R98: 46317 | S98: 2026-Q4 | U98: 0 | V98: https://news.google.com/rss/articles/CBMic0FVX3lxTE1zSGZTbjJtMlg2SGZxUUtTSjJMZVdlSUkxSjZBeEV1WExBUUh4ZjdOZWIzcGRHczE1dVZiOWgyQUxTdkZWOEJfM0Y1dk1mcGpKekl0dGR4VE1YRVhoYTFjV09IZGQ3dUNQcl9BSlN0QzhUSkE?oc=5 | W98: =IF($B98="",0,IF(AND(OR(OR(Dashboard!$B$5="All themes",Dashboard!$B$5=""),$C98=Dashboard!$B$5),OR(OR(Dashboard!$G$5="All uses",Dashboard!$G$5=""),$E98=Dashboard!$G$5),N($D98)>=Lists!$H$2,OR(OR(Dashboard!$N$5="All windows",Dashboard!$N$5=""),$S98=Dashboard!$N$5)),1,0)) | X98: =IF($W98=1,N($D98)*1E14+MIN(MAX(N($U98),0),9999)*1E10+MIN(N($K98),99999)*1E5+99999-MIN(ROW(),99999),"")
A99: 96 | B99: Automatic segmentation of rock mass fracture networks from UAV imagery using cross-domain transfer learning under scarce labels. | C99: Digital Geotechnics | D99: 5 | E99: Academia-to-Industry topic | F99: To review | I99: Can transfer learning from related image domains reliably segment rock fracture networks in UAV imagery when labelled data are scarce, and how accurate are the results? | J99: 生物通 | K99: 46319 | L99: 标签稀缺条件下基于跨域迁移学习的无人机岩体裂隙网络自动分割方法 | Q99: China | R99: 46318 | S99: 2026-Q4 | U99: 0 | V99: https://news.google.com/rss/articles/CBMibkFVX3lxTE8wdVhYVXYyQ3RwMHAtOTNnUkh5TnhCcEtVem9XenhDMFo2UVFHbWtIaGIzVHhLb1BFQmd2akRLZkFMd1pQNWJDRElESUY1SUdvLWFfd1ZaUW5tZ0ZFcmIxckZxbXg1Z1RrbXI5V0Zn?oc=5 | W99: =IF($B99="",0,IF(AND(OR(OR(Dashboard!$B$5="All themes",Dashboard!$B$5=""),$C99=Dashboard!$B$5),OR(OR(Dashboard!$G$5="All uses",Dashboard!$G$5=""),$E99=Dashboard!$G$5),N($D99)>=Lists!$H$2,OR(OR(Dashboard!$N$5="All windows",Dashboard!$N$5=""),$S99=Dashboard!$N$5)),1,0)) | X99: =IF($W99=1,N($D99)*1E14+MIN(MAX(N($U99),0),9999)*1E10+MIN(N($K99),99999)*1E5+99999-MIN(ROW(),99999),"")
A100: 97 | B100: M4 landslip work begins as part of wider repair programme | C100: Hazards & Resilience | D100: 4 | E100: Feature lead | F100: To review | I100: How should engineers diagnose and stabilise a landslipped motorway embankment, and what drainage and monitoring measures prevent recurrence? | J100: Ground Engineering | K100: 46319 | N100: United Kingdom | O100: M4 Wiltshire | R100: 46318 | S100: 2026-Q4 | T100: landslide, landslip, embankment | U100: 14 | V100: https://www.geplus.co.uk/news/project-news/m4-landslip-work-begins-as-part-of-wider-repair-programme-23-10-2026/ | W100: =IF($B100="",0,IF(AND(OR(OR(Dashboard!$B$5="All themes",Dashboard!$B$5=""),$C100=Dashboard!$B$5),OR(OR(Dashboard!$G$5="All uses",Dashboard!$G$5=""),$E100=Dashboard!$G$5),N($D100)>=Lists!$H$2,OR(OR(Dashboard!$N$5="All windows",Dashboard!$N$5=""),$S100=Dashboard!$N$5)),1,0)) | X100: =IF($W100=1,N($D100)*1E14+MIN(MAX(N($U100),0),9999)*1E10+MIN(N($K100),99999)*1E5+99999-MIN(ROW(),99999),"")
...

Sheet By theme
A1: Stories by theme | D1: ← Dashboard | E1: ↑ Start here | F1: Stories →
A2: Read-only view, best stories first. Click − / + in the margin on the left to collapse or expand a theme (or the 1 / 2 buttons for all). Status comes from the Stories sheet.
A4: Sustainability & the Energy Transition · 4 stories · 1 rated 5 / 5 · 1 feature lead
A5: No. | B5: Relevance | C5: Headline | D5: Link | E5: Suggested use | F5: Status | G5: Source | H5: Digest | I5: Magazine angle · check with
A6: 6 | B6: 5 | C6: Ground crumbles and gas escapes: thousands of dangerous sites identified in Yamal (English headline translated by Claude · Original: Грунт рушится, а газ рвётся наружу: На Ямале выявили тысячи опасных участков) | D6: Open article | E6: Feature lead | F6: =IFERROR(INDEX(Stories!$F$4:$F$153,MATCH($A6,Stories!$A$4:$A$153,0))&"","") | G6: Life.ru | H6: 46321 | I6: How is permafrost thaw and gas migration causing ground collapse and craters across Yamal, and what monitoring and foundation strategies can manage thousands of hazardous sites? Check with: Yamal regional authorities and the gas operators
A7: 134 | B7: 3 | C7: Snowy 2.0 cost and completion date revised | D7: Open article | E7: News brief | F7: =IFERROR(INDEX(Stories!$F$4:$F$153,MATCH($A7,Stories!$A$4:$A$153,0))&"","") | G7: Tunnels & Tunnelling | H7: 46319 | I7: What ground-related risks drive cost and schedule overruns in large pumped hydro cavern and tunnel excavations?
A8: 137 | B8: 3 | C8: Abergeldie awarded patent for underground hydrogen storage solution | D8: Open article | E8: Academia-to-Industry topic | F8: =IFERROR(INDEX(Stories!$F$4:$F$153,MATCH($A8,Stories!$A$4:$A$153,0))&"","") | G8: Tunnels & Tunnelling | H8: 46319 | I8: What ground conditions and geomechanical criteria govern underground hydrogen storage, and how does blind boring apply?
A9: 138 | B9: 3 | C9: Snowy 2.0 cost rises to A$22.2bn | D9: Open article | E9: News brief | F9: =IFERROR(INDEX(Stories!$F$4:$F$153,MATCH($A9,Stories!$A$4:$A$153,0))&"","") | G9: Tunnelling Journal | H9: 46319 | I9: What ground-related factors drive repeated cost increases in large underground pumped hydro projects?
A11: Digital Geotechnics · 5 stories · 1 rated 5 / 5 · 2 feature leads
A12: No. | B12: Relevance | C12: Headline | D12: Link | E12: Suggested use | F12: Status | G12: Source | H12: Digest | I12: Magazine angle · check with
A13: 96 | B13: 5 | C13: Automatic segmentation of rock mass fracture networks from UAV imagery using cross-domain transfer learning under scarce labels. (English headline translated by Claude · Original: 标签稀缺条件下基于跨域迁移学习的无人机岩体裂隙网络自动分割方法) | D13: Open article | E13: Academia-to-Industry topic | F13: =IFERROR(INDEX(Stories!$F$4:$F$153,MATCH($A13,Stories!$A$4:$A$153,0))&"","") | G13: 生物通 | H13: 46319 | I13: Can transfer learning from related image domains reliably segment rock fracture networks in UAV imagery when labelled data are scarce, and how accurate are the results?
A14: 55 | B14: 4 | C14: Using AI to provide early warning of landslide risks. | D14: Open article | E14: Feature lead | F14: =IFERROR(INDEX(Stories!$F$4:$F$153,MATCH($A14,Stories!$A$4:$A$153,0))&"","") | G14: Vietnam.vn | H14: 46320 | I14: How reliable are AI-based landslide early-warning models when trained on sparse ground monitoring data?
A15: 26 | B15: 4 | C15: Zero cycle: how Setl Group creates 3D excavation models for residential buildings using nanoCAD GeoniCS (English headline translated by Claude · Original: Нулевой цикл: как в Setl Group создают 3D модели котлованов жилых зданий при помощи nanoCAD GeoniCS) | D15: Open article | E15: Feature lead | F15: =IFERROR(INDEX(Stories!$F$4:$F$153,MATCH($A15,Stories!$A$4:$A$153,0))&"","") | G15: ComNews.ru | H15: 46321 | I15: How reliable are 3D excavation models built from site investigation data for deep pits in dense urban sites, and how should their accuracy be verified before construction? Check with: Setl Group (developer) and the nanoCAD GeoniCS software vendor
A16: 31 | B16: 3 | C16: Using AI to detect landslide risks early. (English headline translated by Claude · Original: Utiliser l'IA pour détecter précocement les risques de glissements de terrain.) | D16: Open article | E16: Academia-to-Industry topic | F16: =IFERROR(INDEX(Stories!$F$4:$F$153,MATCH($A16,Stories!$A$4:$A$153,0))&"","") | G16: Vietnam.vn | H16: 46321 | I16: Can machine learning on rainfall and monitoring data reliably predict landslide initiation, and what validation would engineers need?
A17: 32 | B17: 3 | C17: Using artificial intelligence to provide early warnings of landslide risk. (English headline translated by Claude · Original: Utilizar la inteligencia artificial para proporcionar alertas tempranas sobre riesgos de deslizamientos de tierra.) | D17: Open article | E17: Watch only | F17: =IFERROR(INDEX(Stories!$F$4:$F$153,MATCH($A17,Stories!$A$4:$A$153,0))&"","") | G17: Vietnam.vn | H17: 46321 | I17: Can machine learning on rainfall and monitoring data reliably predict landslide initiation, and what validation would engineers need?
A19: Hazards & Resilience · 53 stories · 13 rated 5 / 5 · 34 feature leads
A20: No. | B20: Relevance | C20: Headline | D20: Link | E20: Suggested use | F20: Status | G20: Source | H20: Digest | I20: Magazine angle · check with
A21: 1 | B21: 5 | C21: Kumamoto earthquake: 96% of liquefaction sites reoccurred (English headline translated by Claude · Original: 熊本地震 液状化地点の96%で再発) | D21: Open article | E21: Feature lead | F21: =IFERROR(INDEX(Stories!$F$4:$F$153,MATCH($A21,Stories!$A$4:$A$153,0))&"","") | G21: Yahoo!ニュース | H21: 46321 | I21: Why do the same sites re-liquefy in repeated earthquakes, and which ground improvement or site-specific measures actually stop recurrence? Check with: Kumamoto Prefectural Government and the research team behind the liquefaction survey
A22: 2 | B22: 5 | C22: 96% of sites with upper seismic intensity 6 in the Kumamoto earthquake re-liquefied; experts urge advance countermeasures. (English headline translated by Claude · Original: 熊本地震「震度６強」の９６％が再液状化…繰り返される被害、専門家は事前対策訴え) | D22: Open article | E22: Watch only | F22: =IFERROR(INDEX(Stories!$F$4:$F$153,MATCH($A22,Stories!$A$4:$A$153,0))&"","") | G22: 読売新聞 | H22: 46321 | I22: Why do the same sites re-liquefy in repeated earthquakes, and which ground improvement or site-specific measures actually stop recurrence? Check with: Kumamoto Prefectural Government and the research team behind the liquefaction survey
A23: 3 | B23: 5 | C23: Ancient Earthquakes Triggered Massive 10,000-Year-Old Landslides In Kashmir Himalaya, New Study Reveals | D23: Open article | E23: Feature lead | F23: =IFERROR(INDEX(Stories!$F$4:$F$153,MATCH($A23,Stories!$A$4:$A$153,0))&"","") | G23: Kashmir Life | H23: 46321 | I23: Can dating of ancient landslide deposits be used to infer earthquake recurrence and slope hazard in tectonically active Himalayan terrain? Check with: the study's lead research institution (check the journal paper)
A24: 44 | B24: 5 | C24: More than 100 days after Kalladi landslip, twin-tunnel road project awaits safety reports | D24: Open article | E24: Feature lead | F24: =IFERROR(INDEX(Stories!$F$4:$F$153,MATCH($A24,Stories!$A$4:$A$153,0))&"","") | G24: Onmanorama | H24: 46320 | I24: How should twin-tunnel road projects be geotechnically assessed and safety-verified in landslide-prone hill terrain after a major slope failure?
A25: 45 | B25: 5 | C25: Fragility of port disaster prevention exposed: liquefaction halts logistics at Yatsushiro (English headline translated by Claude · Original: 港湾防災のもろさ露呈 八代、液状化で物流停止) | D25: Open article | E25: Feature lead | F25: =IFERROR(INDEX(Stories!$F$4:$F$153,MATCH($A25,Stories!$A$4:$A$153,0))&"","") | G25: 山陽新聞 | H25: 46320 | I25: Why do reclaimed port areas liquefy during earthquakes, and how can quay and yard design reduce the risk of losing logistics function after shaking?
A26: 4 | B26: 5 | C26: Niscemi, nine months after the landslide: the town hanging over the void and thirty years of broken promises. (English headline translated by Claude · Original: Niscemi, nove mesi dopo la frana: la città sospesa sul vuoto e trent'anni di promesse tradite) | D26: Open article | E26: Feature lead | F26: =IFERROR(INDEX(Stories!$F$4:$F$153,MATCH($A26,Stories!$A$4:$A$153,0))&"","") | G26: la Repubblica | H26: 46321 | I26: Why does a large landslide keep a hilltop town in limbo months later, and what geotechnical monitoring and stabilisation strategy could justify either remaining or relocating residents? Check with: Italian Civil Protection Department and Comune di Niscemi
A27: 46 | B27: 5 | C27: Arauco sinkhole: government acknowledges earlier warnings about unstable land and keeps 152 families evacuated (English headline translated by Claude · Original: Socavón de Arauco: Gobierno reconoce advertencias previas sobre terrenos inestables y mantiene evacuación de 152 familias) | D27: Open article | E27: Feature lead | F27: =IFERROR(INDEX(Stories!$F$4:$F$153,MATCH($A27,Stories!$A$4:$A$153,0))&"","") | G27: Publimicro | H27: 46320 | I27: How should authorities act on prior geotechnical warnings about unstable ground, and what criteria should govern long-term evacuation and land reuse?
A28: 47 | B28: 5 | C28: Up to 1.20 metres of ground moved during the 7.5 earthquake that shook Panama (English headline translated by Claude · Original: Hasta 1.20 metros se desplazó el suelo durante el terremoto de 7.5 que sacudió Panamá) | D28: Open article | E28: Feature lead | F28: =IFERROR(INDEX(Stories!$F$4:$F$153,MATCH($A28,Stories!$A$4:$A$153,0))&"","") | G28: Infobae | H28: 46320 | I28: What mechanisms produced metre-scale ground displacement during this magnitude 7.5 earthquake, and what do they imply for fault-zone hazard assessment in Panama?
A29: 5 | B29: 5 | C29: Liu Yushui garden earth collapse kills; SAM says it warned repeatedly about hillside development risks (English headline translated by Claude · Original: 刘玉水花园土崩夺命 SAM：已多次警告 山坡发展风险) | D29: Open article | E29: Feature lead | F29: =IFERROR(INDEX(Stories!$F$4:$F$153,MATCH($A29,Stories!$A$4:$A$153,0))&"","") | G29: China Press | H29: 46321 | I29: How do hillside development practices and repeated unheeded warnings contribute to fatal slope failures, and what geotechnical due diligence should apply to hillside housing? Check with: Penang state government and the police
A30: 8 | B30: 5 | C30: Rock blocks over 500 tonnes threaten Turkey–Georgia road; experts demand inspection of 50 km (English headline translated by Claude · Original: كتل صخرية تتجاوز 500 طن تهدد طريق تركيا-جورجيا.. خبراء يطالبون بفحص 50 كيلومترًا) | D30: Open article | E30: Feature lead | F30: =IFERROR(INDEX(Stories!$F$4:$F$153,MATCH($A30,Stories!$A$4:$A$153,0))&"","") | G30: تركيا عاجل | H30: 46321 | I30: How can rockfall hazard along a mountain highway be assessed for very large blocks, and what slope-scaling and stabilisation approach suits a 50 km stretch? Check with: the General Directorate of Highways (KGM)
A31: 9 | B31: 5 | C31: Longwei earth collapse death: autopsy report released, cause is traumatic asphyxia (English headline translated by Claude · Original: 垄尾土崩酿一死｜死者解剖报告出炉 死因是创伤性窒息) | D31: Open article | E31: Feature lead | F31: =IFERROR(INDEX(Stories!$F$4:$F$153,MATCH($A31,Stories!$A$4:$A$153,0))&"","") | G31: China Press | H31: 46321 | I31: What does the post-mortem finding of a traumatic death reveal about the safety of hillside collapse rescue and the failure of earlier slope warnings? Check with: Penang state government and the police
A32: 48 | B32: 5 | C32: Zaruma sits on old gold galleries: where is the sinkhole risk concentrated? (English headline translated by Claude · Original: Zaruma está sobre antiguas galerías de oro: ¿Dónde se concentra el riesgo de hundimiento?) | D32: Open article | E32: Feature lead | F32: =IFERROR(INDEX(Stories!$F$4:$F$153,MATCH($A32,Stories!$A$4:$A$153,0))&"","") | G32: Revista Digital Minera REDIMIN | H32: 46320 | I32: How do abandoned shallow gold mine galleries affect ground stability beneath an urban area, and how can the sinkhole risk be mapped and managed?
... A73: 70 | B73: 4 | C73: Rain batters Nilgiris; landslide buries government bus, driver loses life | D73: Open article | E73: News brief | F73: =IFERROR(INDEX(Stories!$F$4:$F$153,MATCH($A73,Stories!$A$4:$A$153,0))&"","") | G73: The New Indian Express | H73: 46320 | I73: How can landslide risk on hill-road corridors be managed when a government bus is buried during heavy rain?
A75: Ground Improvement & Innovation · 2 stories · 2 rated 5 / 5 · 1 feature lead
A76: No. | B76: Relevance | C76: Headline | D76: Link | E76: Suggested use | F76: Status | G76: Source | H76: Digest | I76: Magazine angle · check with
A77: 91 | B77: 5 | C77: Behavior of Square-Round Shaft Combination Helical Piles and Anchors | D77: Open article | E77: Academia-to-Industry topic | F77: =IFERROR(INDEX(Stories!$F$4:$F$153,MATCH($A77,Stories!$A$4:$A$153,0))&"","") | G77: Geoengineer.org | H77: 46319 | I77: How do square-round shaft combination helical piles and anchors behave under load, and how can their capacity be predicted reliably?
A78: 94 | B78: 5 | C78: Mussolini's engineers drilled 361 holes under Pisa's foundations in 1934 to straighten it, making it lean more. (English headline translated by Claude · Original: En perçant 361 trous dans ses fondations en 1934 pour la redresser, les ingénieurs de Mussolini ont littéralement fait pencher la tour de Pise encore plus) | D78: Open article | E78: Feature lead | F78: =IFERROR(INDEX(Stories!$F$4:$F$153,MATCH($A78,Stories!$A$4:$A$153,0))&"","") | G78: Sciencepost | H78: 46319 | I78: Why did drilling holes beneath Pisa's foundations to correct its tilt backfire, and what does this teach about controlled soil removal and differential settlement in stabilisation works?
A80: Infrastructure & the Underground City · 50 stories · 2 rated 5 / 5 · 14 feature leads
A81: No. | B81: Relevance | C81: Headline | D81: Link | E81: Suggested use | F81: Status | G81: Source | H81: Digest | I81: Magazine angle · check with
A82: 93 | B82: 5 | C82: Sinkhole at excavation site: ground sank even after underground safety assessment (English headline translated by Claude · Original: 장종태, "굴착 현장 싱크홀...지하안전평가 받고도 땅 꺼졌다") | D82: Open article | E82: Feature lead | F82: =IFERROR(INDEX(Stories!$F$4:$F$153,MATCH($A82,Stories!$A$4:$A$153,0))&"","") | G82: 충청신문 | H82: 46319 | I82: Why did ground sink at an excavation despite a completed underground safety assessment, and what gaps exist in such assessments?
A83: 7 | B83: 5 | C83: Silkyara tunnel may open before the upcoming Char Dham yatra, company claims; Yamunotri distance to shrink by 26 km (English headline translated by Claude · Original: सिलक्यारा टनल आगामी चारधाम यात्रा तक खुल सकती है: कंपनी का दावा; यमुनोत्री धाम की 26 किमी दूरी घटेगी, समय औ...) | D83: Open article | E83: Feature lead | F83: =IFERROR(INDEX(Stories!$F$4:$F$153,MATCH($A83,Stories!$A$4:$A$153,0))&"","") | G83: Dainik Bhaskar | H83: 46321 | I83: What ground stabilisation and rock mass conditions must be verified before a collapsed Himalayan tunnel can safely reopen, and how credible is the proposed schedule? Check with: NHIDCL (the project owner) and the contractor
A84: 15 | B84: 4 | C84: Four Tourists Injured After Poolside Patio Collapses Into Sinkhole At Cozumel Resort | D84: Open article | E84: Feature lead | F84: =IFERROR(INDEX(Stories!$F$4:$F$153,MATCH($A84,Stories!$A$4:$A$153,0))&"","") | G84: Cancun Sun | H84: 46321 | I84: How can shallow cavities in karst limestone be detected under resort paving and foundations before a patio collapses into a sinkhole? Check with: Quintana Roo state civil protection and the resort's engineering consultant
A85: 116 | B85: 4 | C85: Osan: Jo Yong-ho's restoration of Seobu-ro retaining wall after road collapse, aiming to restore public trust (English headline translated by Claude · Original: [강대웅의 정문일침(頂門一鍼)] 조용호 시장의 오산시 서부로 옹벽 복구...무너진 도로 넘어 시민 신뢰 회복) | D85: Open article | E85: Feature lead | F85: =IFERROR(INDEX(Stories!$F$4:$F$153,MATCH($A85,Stories!$A$4:$A$153,0))&"","") | G85: 아주경제 | H85: 46319 | I85: What caused the road collapse behind this retaining wall, and how should wall reconstruction address backfill and drainage?
A86: 117 | B86: 4 | C86: Lawmakers warn of major accidents as retaining wall near apartments repeatedly collapses; drainage and private land issues (English headline translated by Claude · Original: 반주영 의원 “인명피해로 이어지면 큰 사고”…황성석 의원도 고촌 옹벽 안전대책 촉구 | 아파트 인접 옹벽 반복 붕괴 우려…상부 배수로·사유지 문제에 시의 적극적인 협의 주문) | D86: Open article | E86: Regional insight | F86: =IFERROR(INDEX(Stories!$F$4:$F$153,MATCH($A86,Stories!$A$4:$A$153,0))&"","") | G86: Naver Blog | H86: 46319 | I86: Why do retaining walls beside apartments collapse repeatedly, and how do drainage and private land ownership complicate remediation?
A87: 118 | B87: 4 | C87: Part of a retaining wall collapsed near Pioneer Park in Yalta after rains (English headline translated by Claude · Original: После ливней у Пионерского парка в Ялте обрушилась часть подпорной стены) | D87: Open article | E87: Regional insight | F87: =IFERROR(INDEX(Stories!$F$4:$F$153,MATCH($A87,Stories!$A$4:$A$153,0))&"","") | G87: Крыминформ | H87: 46319 | I87: Why did this retaining wall fail after heavy rain, and what drainage and wall design checks should coastal slopes receive?
A88: 120 | B88: 4 | C88: Gochang-Buan Noeuldaegyo Enters Geotechnical Survey Phase; Construction Targeted for January 2028 | D88: Open article | E88: News brief | F88: =IFERROR(INDEX(Stories!$F$4:$F$153,MATCH($A88,Stories!$A$4:$A$153,0))&"","") | G88: 아시아경제 | H88: 46319 | I88: What ground conditions will the geotechnical survey reveal for this Korean nuclear-related or major construction project, and how will they shape the 2028 schedule?
A89: 19 | B89: 4 | C89: Ayuntamiento atiende más de 50 socavones su reparación cuesta hasta 700 mil pesos por punto | D89: Open article | E89: Feature lead | F89: =IFERROR(INDEX(Stories!$F$4:$F$153,MATCH($A89,Stories!$A$4:$A$153,0))&"","") | G89: Pulso Diario San Luis | H89: 46321 | I89: Why do dozens of urban sinkholes appear in one city, and what are the economics and engineering options for locating leaking buried pipes and rehabilitating ground before repairs become recurrent? Check with: San Luis Potosí municipal government
A90: 20 | B90: 4 | C90: Ica: nuevo huaico podría repetir el bloqueo de la Panamericana Sur por falta de puente en Ocucaje | D90: Open article | E90: Feature lead | F90: =IFERROR(INDEX(Stories!$F$4:$F$153,MATCH($A90,Stories!$A$4:$A$153,0))&"","") | G90: Diario Correo | H90: 46321 | I90: How do debris flows crossing desert valleys threaten highway embankments and crossings, and what design choices should guide replacement of a missing bridge on this corridor? Check with: Provías Nacional (MTC)
A91: 53 | B91: 4 | C91: Four guests fall into sinkhole at Occidental Cozumel hotel (English headline translated by Claude · Original: Cuatro huéspedes caen en socavón del hotel Occidental Cozumel) | D91: Open article | E91: News brief | F91: =IFERROR(INDEX(Stories!$F$4:$F$153,MATCH($A91,Stories!$A$4:$A$153,0))&"","") | G91: Quintana Roo Hoy | H91: 46320 | I91: How do karst cavities and dissolution features in coastal limestone create sudden collapses beneath hotel and tourist structures?
A92: 56 | B92: 4 | C92: Reconstruction of the Terrazas del Valle bridge begins after sinkhole (English headline translated by Claude · Original: Inician reconstrucción del puente de Terrazas del Valle tras socavón) | D92: Open article | E92: News brief | F92: =IFERROR(INDEX(Stories!$F$4:$F$153,MATCH($A92,Stories!$A$4:$A$153,0))&"","") | G92: NDT Noticias de Tijuana | H92: 46320 | I92: What investigation and foundation design are needed to rebuild a bridge whose support ground has collapsed into a sinkhole?
A93: 125 | B93: 4 | C93: Mystery in El Bosque: sinkhole appears amid rain and swallows a car (English headline translated by Claude · Original: Misterio en El Bosque: socavón aparece en medio de la lluvia y se traga un auto) | D93: Open article | E93: News brief | F93: =IFERROR(INDEX(Stories!$F$4:$F$153,MATCH($A93,Stories!$A$4:$A$153,0))&"","") | G93: BioBioChile | H93: 46319 | I93: How do rainfall, leaking pipes and soil erosion combine to create sudden road sinkholes that swallow vehicles, as in El Bosque?
... A131: 90 | B131: 3 | C131: Experts weigh in on proposal to level Mot Mountain in Quy Nhon (English headline translated by Claude · Original: Para ahli angkat bicara tentang usulan untuk meratakan Gunung Mot di Quy Nhon.) | D131: Open article | E131: Regional insight | F131: =IFERROR(INDEX(Stories!$F$4:$F$153,MATCH($A131,Stories!$A$4:$A$153,0))&"","") | G131: Vietnam.vn | H131: 46320 | I131: How can slope stability, rock cutting and geohazard risks be assessed when a coastal hill is proposed for levelling in an urban area?
A133: Offshore, Coasts & Water · 20 stories · 1 rated 5 / 5 · 8 feature leads
A134: No. | B134: Relevance | C134: Headline | D134: Link | E134: Suggested use | F134: Status | G134: Source | H134: Digest | I134: Magazine angle · check with
A135: 92 | B135: 5 | C135: Floating wind needs grounded solutions | D135: Open article | E135: Feature lead | F135: =IFERROR(INDEX(Stories!$F$4:$F$153,MATCH($A135,Stories!$A$4:$A$153,0))&"","") | G135: Ground Engineering | H135: 46319 | I135: What geotechnical challenges arise in anchoring floating offshore wind foundations in variable seabed soils under extreme loading?
A136: 50 | B136: 4 | C136: Nghe An: urgent measures needed for landslide on the seaside road embankment (English headline translated by Claude · Original: 응에안성: 해안 도로 제방의 산사태 발생에 대한 긴급 조치가 필요합니다.) | D136: Open article | E136: News brief | F136: =IFERROR(INDEX(Stories!$F$4:$F$153,MATCH($A136,Stories!$A$4:$A$153,0))&"","") | G136: Vietnam.vn | H136: 46320 | I136: Why do coastal road embankments fail by landslide, and what emergency stabilisation and monitoring are appropriate for dyke slopes exposed to waves and rainfall?
A137: 108 | B137: 4 | C137: Quang Tri: Severe coastal erosion threatens dikes, embankments, and people's lives. | D137: Open article | E137: Regional insight | F137: =IFERROR(INDEX(Stories!$F$4:$F$153,MATCH($A137,Stories!$A$4:$A$153,0))&"","") | G137: Vietnam.vn | H137: 46319 | I137: What processes drive severe coastal erosion undermining dikes, and what protection measures suit such shorelines?
A138: 109 | B138: 4 | C138: Nghe An: urgent measures needed to prevent landslide on embankment along coastal road (English headline translated by Claude · Original: Нге Ан: Необходимы срочные меры для предотвращения оползня на насыпи вдоль прибрежной дороги.) | D138: Open article | E138: Regional insight | F138: =IFERROR(INDEX(Stories!$F$4:$F$153,MATCH($A138,Stories!$A$4:$A$153,0))&"","") | G138: Vietnam.vn | H138: 46319 | I138: What urgent stabilisation options suit a failing embankment on a coastal road, and how should slope failure risk be assessed?
A139: 115 | B139: 4 | C139: Nghe An: early treatment needed for slope failure on coastal road cut (English headline translated by Claude · Original: Nghệ An: Cần sớm xử lý sạt lở taluy dương trên tuyến đường ven biển) | D139: Open article | E139: Regional insight | F139: =IFERROR(INDEX(Stories!$F$4:$F$153,MATCH($A139,Stories!$A$4:$A$153,0))&"","") | G139: Vietnam.vn | H139: 46319 | I139: What causes slope failure in coastal road cuts, and which stabilisation methods are most suitable for weathered coastal soils?
A140: 51 | B140: 4 | C140: Quang Tri: severe coastal erosion threatens dykes, embankments and residents' lives. (English headline translated by Claude · Original: 꽝찌: 심각한 해안 침식으로 인해 제방과 둑, 그리고 주민들의 생명이 위협받고 있습니다.) | D140: Open article | E140: Feature lead | F140: =IFERROR(INDEX(Stories!$F$4:$F$153,MATCH($A140,Stories!$A$4:$A$153,0))&"","") | G140: Vietnam.vn | H140: 46320 | I140: How can coastal erosion monitoring and erosion-resistant embankment design protect dykes and communities when shoreline retreat accelerates?
A141: 119 | B141: 4 | C141: Two houses collapse due to Tien River bank erosion (English headline translated by Claude · Original: Hai căn nhà đổ sập do sạt lở bờ sông Tiền) | D141: Open article | E141: News brief | F141: =IFERROR(INDEX(Stories!$F$4:$F$153,MATCH($A141,Stories!$A$4:$A$153,0))&"","") | G141: VTV.vn | H141: 46319 | I141: What riverbank erosion processes undermined these houses, and how can bank stability be assessed near settlements?
A142: 17 | B142: 4 | C142: Fuerte oleaje provoca un socavón y daños en un malecón emblemático de México | D142: Open article | E142: Feature lead | F142: =IFERROR(INDEX(Stories!$F$4:$F$153,MATCH($A142,Stories!$A$4:$A$153,0))&"","") | G142: TV Azteca Jalisco | H142: 46321 | I142: How do storm waves undermine the backfill behind a seafront promenade wall to create sinkholes, and what coastal protection and geotechnical checks should follow such damage? Check with: Mazatlán municipal government and Sinaloa civil protection
A143: 18 | B143: 4 | C143: Inician reparación de socavón provocado por fuerte oleaje junto al Monumento a la Mujer Mazatleca | D143: Open article | E143: Regional insight | F143: =IFERROR(INDEX(Stories!$F$4:$F$153,MATCH($A143,Stories!$A$4:$A$153,0))&"","") | G143: Los Noticieristas | H143: 46321 | I143: What repair approach suits a wave-undermined seafront structure, and how should designers balance scour protection, backfill compaction and monument stability at the shoreline? Check with: Mazatlán municipal government
A144: 58 | B144: 4 | C144: Can Tho to invest over 500 billion dong in dykes against erosion at Cu Lao Dung (English headline translated by Claude · Original: Cần Thơ đầu tư hơn 500 tỷ đồng xây dựng đê phòng, chống sạt lở ở Cù Lao Dung) | D144: Open article | E144: Feature lead | F144: =IFERROR(INDEX(Stories!$F$4:$F$153,MATCH($A144,Stories!$A$4:$A$153,0))&"","") | G144: Báo Nhân Dân điện tử | H144: 46320 | I144: How should dyke and bank protection balance erosion control against settlement and stability on soft deltaic soils?
A145: 59 | B145: 4 | C145: Krong No river erosion in Lam Dong threatens irrigation works and farmland (English headline translated by Claude · Original: Sạt lở sông Krông Nô tại Lâm Đồng đe dọa công trình thủy lợi và đất canh tác) | D145: Open article | E145: Feature lead | F145: =IFERROR(INDEX(Stories!$F$4:$F$153,MATCH($A145,Stories!$A$4:$A$153,0))&"","") | G145: tin.skydoor.net | H145: 46320 | I145: How can riverbank erosion be assessed and countered to protect irrigation infrastructure and farmland?
A146: 71 | B146: 4 | C146: [Land disappearing beneath the sea] Double attack of climate-driven sea-level rise and ground subsidence; global lands vanishing from maps. (English headline translated by Claude · Original: [국토가 바닷속으로 사라진다] 기후변화 발 해수면 상승·지반 침하의 이중 습격, 지도에서 지워지는 지구촌) | D146: Open article | E146: Feature lead | F146: =IFERROR(INDEX(Stories!$F$4:$F$153,MATCH($A146,Stories!$A$4:$A$153,0))&"","") | G146: AI넷 | H146: 46320 | I146: How do sea-level rise and land subsidence combine to lower coastal ground, and what engineering responses can slow the loss of land?
... A154: 150 | B154: 3 | C154: Inician rehabilitación tras hundimiento de losa en el Malecón Costero de Coatzacoalcos | D154: Open article | E154: News brief | F154: =IFERROR(INDEX(Stories!$F$4:$F$153,MATCH($A154,Stories!$A$4:$A$153,0))&"","") | G154: :: Foro Coatza :: | H154: 46319 | I154: What causes slab sinking on a coastal promenade exposed to waves, and what foundation and drainage remedies are appropriate?
A156: Characterisation & Modelling · 9 stories · 0 rated 5 / 5 · 6 feature leads
A157: No. | B157: Relevance | C157: Headline | D157: Link | E157: Suggested use | F157: Status | G157: Source | H157: Digest | I157: Magazine angle · check with
A158: 54 | B158: 4 | C158: Close-up of giant 120 m deep sinkhole just discovered in Phong Nha-Ke Bang (English headline translated by Claude · Original: 퐁냐케방에서 방금 발견된 깊이 120m의 거대한 싱크홀 근접 촬영) | D158: Open article | E158: Feature lead | F158: =IFERROR(INDEX(Stories!$F$4:$F$153,MATCH($A158,Stories!$A$4:$A$153,0))&"","") | G158: Laodong.vn | H158: 46320 | I158: How are very deep karst sinkholes investigated, and what does their formation reveal about hazards around cave systems?
A159: 57 | B159: 4 | C159: 120 m deep sinkhole containing primeval forest discovered in Phong Nha-Ke Bang area (English headline translated by Claude · Original: 퐁냐-케방 지역에서 원시림이 포함된 깊이 120미터의 싱크홀이 발견되었습니다.) | D159: Open article | E159: Feature lead | F159: =IFERROR(INDEX(Stories!$F$4:$F$153,MATCH($A159,Stories!$A$4:$A$153,0))&"","") | G159: Vietnam.vn | H159: 46320 | I159: How are very deep karst sinkholes investigated, and what does their formation reveal about hazards around cave systems?
A160: 121 | B160: 4 | C160: Se ha descubierto un socavón del tamaño de casi tres campos de fútbol en Phong Nha Ke Bang. | D160: Open article | E160: Feature lead | F160: =IFERROR(INDEX(Stories!$F$4:$F$153,MATCH($A160,Stories!$A$4:$A$153,0))&"","") | G160: Vietnam.vn | H160: 46319 | I160: How do karst dissolution and roof collapse produce giant dolines like the one in Phong Nha Ke Bang, and how can such cavities be characterised?
A161: 123 | B161: 4 | C161: Vista de cerca del gigantesco socavón de 120 metros de profundidad descubierto recientemente en Vietnam. | D161: Open article | E161: Feature lead | F161: =IFERROR(INDEX(Stories!$F$4:$F$153,MATCH($A161,Stories!$A$4:$A$153,0))&"","") | G161: Vietnam.vn | H161: 46319 | I161: Which geomorphological and hydrogeological processes produced a 120 m deep collapse, and how can the stability of its steep walls be assessed?
A162: 124 | B162: 4 | C162: Primeval forest grows at bottom of 120-meter-deep sinkhole in central Vietnam | D162: Open article | E162: Feature lead | F162: =IFERROR(INDEX(Stories!$F$4:$F$153,MATCH($A162,Stories!$A$4:$A$153,0))&"","") | G162: VnExpress International | H162: 46319 | I162: How do karst collapse sinkholes form in limestone terrain, and what do such deep features reveal about cave ground stability and hazard mapping?
A163: 129 | B163: 4 | C163: What lies inside the hole over two hectares wide in the middle of Phong Nha-Ke Bang forest? (English headline translated by Claude · Original: ما الذي يوجد داخل الحفرة التي تزيد مساحتها عن هكتارين في وسط غابة فونغ نها - كي بانغ؟) | D163: Open article | E163: Feature lead | F163: =IFERROR(INDEX(Stories!$F$4:$F$153,MATCH($A163,Stories!$A$4:$A$153,0))&"","") | G163: Vietnam.vn | H163: 46319 | I163: What karst processes, such as collapse or dissolution, could create a large sinkhole of over two hectares in a tropical forest, and how should it be investigated and monitored?
A164: 130 | B164: 4 | C164: Analytical study of 3D transient dynamic response of a cylindrical cavity in an elastic medium under triangular pulse load. (English headline translated by Claude · Original: 弹性介质中圆柱形空腔受三角形脉冲冲击载荷的三维瞬态动力响应解析研究) | D164: Open article | E164: Academia-to-Industry topic | F164: =IFERROR(INDEX(Stories!$F$4:$F$153,MATCH($A164,Stories!$A$4:$A$153,0))&"","") | G164: 生物通 | H164: 46319 | I164: How do analytical solutions for a cylindrical cavity under triangular pulse loads inform the validation of numerical models for underground openings under impact?
A165: 139 | B165: 3 | C165: Minvu advances 121 housing support cases in Villa El Mirador, Arauco, and prepares soil study (English headline translated by Claude · Original: Minvu avanza en 121 casos de apoyo habitacional en la Villa El Mirador de Arauco y prepara estudio de suelos) | D165: Open article | E165: News brief | F165: =IFERROR(INDEX(Stories!$F$4:$F$153,MATCH($A165,Stories!$A$4:$A$153,0))&"","") | G165: Trade-news.cl | H165: 46319 | I165: What soil investigation is needed before housing support works on this site, and how should ground conditions shape foundation choice?
A166: 77 | B166: 3 | C166: Exploring Phong Nha-Ke Bang’s famous sinkholes | D166: Open article | E166: Regional insight | F166: =IFERROR(INDEX(Stories!$F$4:$F$153,MATCH($A166,Stories!$A$4:$A$153,0))&"","") | G166: DTiNews | H166: 46320 | I166: How can karst cave systems and sinkhole susceptibility be mapped and characterised in tropical limestone terrain for tourism and infrastructure?
A168: Geotechnics & Society · 7 stories · 0 rated 5 / 5 · 2 feature leads
A169: No. | B169: Relevance | C169: Headline | D169: Link | E169: Suggested use | F169: Status | G169: Source | H169: Digest | I169: Magazine angle · check with
A170: 122 | B170: 4 | C170: CEDH finds negligence by Guasave municipality in death of teacher who fell into sinkhole (English headline translated by Claude · Original: CEDH acredita negligencia del Ayuntamiento de Guasave por muerte de profesor que cayó en socavón) | D170: Open article | E170: Feature lead | F170: =IFERROR(INDEX(Stories!$F$4:$F$153,MATCH($A170,Stories!$A$4:$A$153,0))&"","") | G170: www.noroeste.com.mx | H170: 46319 | I170: What duty of care should municipalities meet in managing known ground-collapse hazards in urban areas, as the Guasave case suggests?
A171: 30 | B171: 3 | C171: Concentrer les ressources sur le relogement des personnes vivant dans les zones à risque de glissements de terrain. | D171: Open article | E171: Feature lead | F171: =IFERROR(INDEX(Stories!$F$4:$F$153,MATCH($A171,Stories!$A$4:$A$153,0))&"","") | G171: Vietnam.vn | H171: 46321 | I171: How should relocation programmes for households in landslide-prone zones be prioritised using ground hazard evidence? Check with: Vietnam's ministry responsible for disaster prevention
A172: 75 | B172: 3 | C172: SAM demands answers over fatal Penang landslide which killed doctor | D172: Open article | E172: News brief | F172: =IFERROR(INDEX(Stories!$F$4:$F$153,MATCH($A172,Stories!$A$4:$A$153,0))&"","") | G172: NST Online | H172: 46320 | I172: What accountability and slope regulation gaps are revealed after a fatal landslide in a hillside urban area?
A173: 76 | B173: 3 | C173: 'The 1956 Landslide and the Church of San Pietro': photographic exhibition extended (English headline translated by Claude · Original: "La Frana del 1956 e la Chiesa di San Pietro", prorogata la mostra fotografica) | D173: Open article | E173: Watch only | F173: =IFERROR(INDEX(Stories!$F$4:$F$153,MATCH($A173,Stories!$A$4:$A$153,0))&"","") | G173: Trigno.net | H173: 46320 | I173: How did the 1956 landslide shape settlement decisions and church site safety, and what does that history teach about landslide memory?
A174: 140 | B174: 3 | C174: Body of miner trapped in a tunnel collapse in Gámeza recovered (English headline translated by Claude · Original: Rescatan el cuerpo sin vida del minero que había quedado atrapado en un socavón en Gámeza) | D174: Open article | E174: News brief | F174: =IFERROR(INDEX(Stories!$F$4:$F$153,MATCH($A174,Stories!$A$4:$A$153,0))&"","") | G174: Boyacá 7 Días | H174: 46319 | I174: What ground and support conditions lead to tunnel collapses in small mines, and how can rescue operations account for ground instability?
A175: 147 | B175: 3 | C175: Gia Lai province People's Committee chairman discusses proposal to level Mot Mountain. (English headline translated by Claude · Original: رئيس اللجنة الشعبية لمقاطعة جيا لاي يتحدث عن اقتراح تسوية جبل موت.) | D175: Open article | E175: Regional insight | F175: =IFERROR(INDEX(Stories!$F$4:$F$153,MATCH($A175,Stories!$A$4:$A$153,0))&"","") | G175: Vietnam.vn | H175: 46319 | I175: What are the geotechnical feasibility issues of levelling a hill, including rock quality, slope excavation and stability, compared with preservation?
A176: 148 | B176: 3 | C176: What are the options for Mot Mountain in Quy Nhon: level it or preserve the historic site? (English headline translated by Claude · Original: Quais são as opções para o Monte Mot em Quy Nhon: nivelá-lo ou preservar o sítio histórico?) | D176: Open article | E176: Regional insight | F176: =IFERROR(INDEX(Stories!$F$4:$F$153,MATCH($A176,Stories!$A$4:$A$153,0))&"","") | G176: Vietnam.vn | H176: 46319 | I176: What geotechnical assessments would be needed to compare levelling Mot Mountain with conserving its historic site, including rock stability and foundation implications?

Sheet Research
A1: Research · 31 new papers | C1: ← Dashboard | D1: ↑ Start here
C2: Papers from geotechnical journals (via Crossref), best rated for use in practice first. Click a title to open the paper, and read it before you write about it. Status and Editor notes are yours, as in Stories.
A3: No. | B3: Paper | C3: Theme | D3: Use in practice | E3: Status | F3: Editor notes | G3: Why it matters in practice | H3: Journal | I3: Authors | J3: Published | K3: Digest date | L3: Keywords | M3: DOI link
A4: 1 | B4: Seismic performance assessment of high-speed railway track-bridge system with CFRP-repaired piers under near-fault pulse-like ground motions | C4: Infrastructure & the Underground City | D4: 4 | E4: To review | G4: Seismic response results for CFRP-repaired bridge piers under pulse-like motions help engineers judge whether repair strategies protect high-speed rail track-bridge systems. | H4: Soil Dynamics and Earthquake Engineering | I4: Kang Z, Jiang L, Jiang L | J4: 46321 | K4: 46321 | L4: railway | M4: https://doi.org/10.1016/j.soildyn.2026.110792
A5: 2 | B5: A modified triaxial test for characterising soil–structure interface behaviour | C5: Characterisation & Modelling | D5: 4 | E5: To review | G5: A modified triaxial set-up that yields interface friction comparable to direct shear lets labs measure soil-structure interface strength with equipment they already own. | H5: Acta Geotechnica | I5: Ho CYR, Khoshghalb A, Khalili N | J5: 46320 | K5: 46321 | L5: soil | M5: https://doi.org/10.1007/s11440-026-03248-3
A6: 3 | B6: Fine particle migration of gravel-sand mixtures under coupled hydraulic gradient and cyclic loading | C6: Hazards & Resilience | D6: 4 | E6: To review | G6: Showing how fines wash out of gravel-sand mixtures under combined seepage and cyclic loading flags internal erosion risks for dams, levees and filters that engineers must assess. | H6: Acta Geotechnica | I6: Li ZQ, Zhang S et al. | J6: 46320 | K6: 46321 | M6: https://doi.org/10.1007/s11440-026-03237-6
A7: 4 | B7: Secondary Compression of Deep Foundations in Carbonate Soils: An InSAR Study of Sunny Isles, Florida | C7: Infrastructure & the Underground City | D7: 4 | E7: To review | G7: Six years of InSAR data show building-specific settlements in carbonate soils that continue after construction, so engineers should plan for long-term deformation and monitoring of deep foundations. | H7: Journal of Geotechnical and Geoenvironmental Engineering | I7: Bardet JP | J7: 46319 | K7: 46319 | L7: subsidence, settlement, deep foundation, foundation, pile, soil | M7: https://doi.org/10.1061/jggefk.gteng-15394
A8: 5 | B8: Experimental investigation on deformation behavior of pile-supported embankments with geogrid-tire cells reinforcement | C8: Ground Improvement & Innovation | D8: 4 | E8: To review | G8: Experimental results on pile-supported embankments with geogrid-tire cells give practical guidance on deformation behaviour and load transfer for low-cost reinforced embankment design. | H8: Transportation Geotechnics | I8: Zhang H, Jia Y et al. | J8: 46318 | K8: 46319 | L8: pile, embankment, geogrid | M8: https://doi.org/10.1016/j.trgeo.2026.102499
A9: 6 | B9: Stiffness compatibility in geosynthetic-reinforced column-supported embankment widening over soft ground: numerical insights and a design framework | C9: Ground Improvement & Innovation | D9: 4 | E9: To review | G9: A stiffness-compatibility design framework for geosynthetic-reinforced column-supported embankment widening addresses differential settlement issues that practitioners face when widening existing embankments. | H9: Soils and Foundations | I9: Pham TA | J9: 46317 | K9: 46319 | L9: embankment, geosynthetic | M9: https://doi.org/10.1016/j.sandf.2026.101892
A10: 7 | B10: Extended soil-arching analysis for piled embankments with rectangular pile layouts | C10: Ground Improvement & Innovation | D10: 4 | E10: To review | G10: Extended soil-arching solutions for rectangular pile layouts, with error quantified against the equivalent-square simplification, give designers a more accurate load-transfer method for piled embankments. | H10: Proceedings of the Institution of Civil Engineers - Geotechnical Engineering | I10: He X, Li G et al. | J10: 46316 | K10: 46319 | L10: pile, embankment, soil | M10: https://doi.org/10.1680/jgeen.26.00025
A11: 8 | B11: Development and properties of thixotropic cementitious slurry for ultra-long horizontal directional pre-grouting | C11: Infrastructure & the Underground City | D11: 4 | E11: To review | G11: A thixotropic cementitious slurry for ultra-long horizontal directional pre-grouting offers a practical grout formulation with properties engineers can specify for long drilled crossings. | H11: Tunnelling and Underground Space Technology | I11: Gong J, Xi F et al. | J11: 46316 | K11: 46319 | L11: grouting | M11: https://doi.org/10.1016/j.tust.2026.108244
A12: 9 | B12: Probabilistic State Parameter–Based Liquefaction Triggering Model | C12: Hazards & Resilience | D12: 4 | E12: To review | G12: A lab-anchored, state-parameter liquefaction triggering model offers an alternative to case-history procedures that can be biased, and it is validated against CPTu data practitioners already use. | H12: Journal of Geotechnical and Geoenvironmental Engineering | I12: Reyes P, Montalva G et al. | J12: 46315 | K12: 46319 | L12: geotechnical, liquefaction, earthquake, soil | M12: https://doi.org/10.1061/jggefk.gteng-15418
A13: 10 | B13: From rockfall to landslide: early warning based on video monitoring in open-pit mines | C13: Hazards & Resilience | D13: 4 | E13: To review | G13: Video monitoring workflows that link rockfall events to developing landslides give open-pit mine operators a practical early-warning approach they could deploy now. | H13: Landslides | I13: Liu F, Deng W et al. | J13: 46315 | K13: 46319 | L13: landslide, rockfall | M13: https://doi.org/10.1007/s10346-026-02861-3
A14: 11 | B14: Stability analysis of geotextile tube tailings dams under inclined stacking: composite failure mechanism and oblique horizontal slice method | C14: Sustainability & the Energy Transition | D14: 4 | E14: To review | G14: A composite failure mechanism and slice method for geotextile tube tailings dams under inclined stacking provide a stability check that practitioners can use for tailings management. | H14: Acta Geotechnica | I14: Wu Z, Liu X et al. | J14: 46315 | K14: 46319 | L14: tailings, dam | M14: https://doi.org/10.1007/s11440-026-03261-6
A15: 12 | B15: A unified experimental-numerical assessment of Cable, Pile, and Zone solid rockbolt models in FLAC3D: bond-slip, load transfer, and model selection | C15: Digital Geotechnics | D15: 4 | E15: To review | G15: A combined experimental and numerical comparison of FLAC3D rockbolt models helps engineers select the appropriate bolt model and calibrate bond-slip parameters for support design. | H15: Computers and Geotechnics | I15: Chen J, Ma S, Yuan L | J15: 46315 | K15: 46319 | L15: pile | M15: https://doi.org/10.1016/j.compgeo.2026.108759
A16: 13 | B16: Integrated seismic and electrical imaging with clustering for the hydro-mechanical screening of a high-altitude earthfill dam | C16: Characterisation & Modelling | D16: 4 | E16: To review | G16: Integrated seismic and electrical imaging with clustering offers a practical screening approach for assessing hydro-mechanical condition in earthfill dams. | H16: Engineering Geology | I16: Strallo V, Colombero C, Godio A | J16: 46315 | K16: 46319 | L16: dam | M16: https://doi.org/10.1016/j.enggeo.2026.109161
A17: 14 | B17: Geophysical site characterization and scenario-based seismic hazard mapping with slope-based topographic amplification factors: case study of the hilltop Trakošćan castle, Croatia | C17: Hazards & Resilience | D17: 4 | E17: To review | G17: A case study combining geophysical characterisation with slope-based topographic amplification factors shows a practical workflow for seismic hazard mapping at hilltop sites. | H17: Engineering Geology | I17: Stanko D, Korbar T, Markušić S | J17: 46315 | K17: 46319 | L17: slope | M17: https://doi.org/10.1016/j.enggeo.2026.109162
A18: 15 | B18: Evaluation of cyclic response of local subgrade materials in Thailand conforming to Chinese high-speed rail standard | C18: Infrastructure & the Underground City | D18: 4 | E18: To review | G18: Cyclic testing of Thai subgrade materials against Chinese high-speed rail standards gives engineers local performance data for railway subgrade design. | H18: Soil Dynamics and Earthquake Engineering | I18: Kaewdee N, Suddeepong A et al. | J18: 46315 | K18: 46319 | M18: https://doi.org/10.1016/j.soildyn.2026.110756
A19: 16 | B19: Data-driven approach for stability analysis of river embankments in Bengkulu City, Indonesia | C19: Hazards & Resilience | D19: 3 | E19: To review | G19: A data-driven stability tool for river embankments could give practitioners a quicker screening method for flood-prone levees, provided it is validated against local failure records. | H19: Bulletin of Engineering Geology and the Environment | I19: Apriadi AA, Mase LZ et al. | J19: 46321 | K19: 46321 | L19: embankment | M19: https://doi.org/10.1007/s10064-026-05359-3
A20: 17 | B20: Origin, General Definition, and Implications of Cryosuction in Frozen Soil | C20: Sustainability & the Energy Transition | D20: 3 | E20: To review | G20: Explaining cryosuction thermodynamically clarifies moisture migration and frost heave mechanisms, which helps engineers judge ice lens risk in cold-region foundations and cut-off design. | H20: Journal of Geotechnical and Geoenvironmental Engineering | I20: Gou L, Likos WJ et al. | J20: 46321 | K20: 46321 | L20: soil | M20: https://doi.org/10.1061/jggefk.gteng-15318
A21: 18 | B21: Eco-friendly urease-independent MICP through bio-stimulation of indigenous soil microorganisms for soil strength improvement: Potential involvement of carbonic anhydrase-associated processes | C21: Ground Improvement & Innovation | D21: 3 | E21: To review | G21: Stimulating native microbes to cement soil without added urease could make biological ground improvement more acceptable and easier to permit on real sites. | H21: Bulletin of Engineering Geology and the Environment | I21: Oulapour M, Ghezelbash GR, Rabeiazadeh M | J21: 46321 | K21: 46321 | L21: soil | M21: https://doi.org/10.1007/s10064-026-05357-5
A22: 19 | B22: Surrogate models for forward simulation and inverse parameter identification using numerical cone penetration test data | C22: Digital Geotechnics | D22: 3 | E22: To review | G22: Trained surrogate models can invert CPT data for soil parameters in seconds, offering a fast route to calibrating site-specific models from penetration records. | H22: Computers and Geotechnics | I22: Felić H, Wijaya AE et al. | J22: 46320 | K22: 46321 | L22: cone penetration | M22: https://doi.org/10.1016/j.compgeo.2026.108749
